Workbook

Sheet README
A1: Tengo review: financial model
A2: Prepared 2026-10-20 for docs/review/REPORT.pdf. A model of possibilities, not a forecast of results.
A4: How it works
A5: Inputs: every number the model uses, with low, base and high values, a source URL and access date, or the label Assumption.
A6: Scenarios: Conservative uses the unfavourable end of every range, Base the central value, Ambitious the favourable end (column G gives the direction).
A7: Model: market funnel, unit economics per active user, four business models, value to a bank, impact and break-even, for all three scenarios side by side.
A8: Projection: 24 months for the recommended model (a, bank licence) in each scenario, with monthly and cumulative cash.
A9: Sensitivity: tornado tables for break-even users and for the bank value case, and a two-way table of licence fee against fixed costs.
A10: Metrics: product, forecast-quality, technical and impact metrics, with sources (test outputs and the backtest).
A12: Colour code
A13: Blue text: hard-coded inputs. Black text: formulas. Green text: links to another sheet. Yellow fill: key assumptions with no source.
A15: Important
... A18: The workbook is set to recalculate fully when opened.

Sheet Scenarios
A1: Scenario summary
A3: Output | B3: Conservative | C3: Base | D3: Ambitious
A4: Serviceable market (people) | B4: =Model!B72 | C4: =Model!C72 | D4: =Model!D72
A5: Steady-state MAU, one partner bank | B5: =Model!B76 | C5: =Model!C76 | D5: =Model!D76
A6: Variable cost per MAU per month, embedded (ZAR) | B6: =Model!B84 | C6: =Model!C84 | D6: =Model!D84
A7: Fixed cost per month (ZAR) | B7: =Model!B87 | C7: =Model!C87 | D7: =Model!D87
A8: (a) Licence: contribution per MAU per month | B8: =Model!B105 | C8: =Model!C105 | D8: =Model!D105
A9: (a) Licence: MAU to break even | B9: =Model!B112 | C9: =Model!C112 | D9: =Model!D112
A10: (b) Revenue share: contribution per MAU per month | B10: =Model!B113 | C10: =Model!C113 | D10: =Model!D113
A11: (b) Revenue share: MAU to break even | B11: =Model!B120 | C11: =Model!C120 | D11: =Model!D120
A12: (c) Consumer: contribution per MAU per month | B12: =Model!B121 | C12: =Model!C121 | D12: =Model!D121
A13: (c) Consumer: LTV to CAC | B13: =Model!B126 | C13: =Model!C126 | D13: =Model!D126
A14: (d) Sponsored: contribution per user per month | B14: =Model!B129 | C14: =Model!C129 | D14: =Model!D129
A15: Bank value per MAU per year (ZAR) | B15: =Model!B95 | C15: =Model!C95 | D15: =Model!D95
A16: Bank value per rand of licence | B16: =Model!B98 | C16: =Model!C98 | D16: =Model!D98
A17: People reached per year | B17: =Model!B138 | C17: =Model!C138 | D17: =Model!D138
A18: Days of cover gained per year | B18: =Model!B140 | C18: =Model!C140 | D18: =Model!D140
A19: Fees avoided by users per year (ZAR) | B19: =Model!B142 | C19: =Model!C142 | D19: =Model!D142
A20: First profitable month, model (a) | B20: =Projection!B14 | C20: =Projection!B30 | D20: =Projection!B46
A21: Peak funding need, model (a) (ZAR) | B21: =Projection!B15 | C21: =Projection!B31 | D21: =Projection!B47
A22: Cumulative cash at month 24, model (a) (ZAR) | B22: =Projection!B16 | C22: =Projection!B32 | D22: =Projection!B48

Sheet Inputs
A1: key | B1: description | C1: unit | D1: low | E1: base | F1: high | G1: direction | H1: source or Assumption | I1: access date | J1: notes | K1: Conservative | L1: Base | M1: Ambitious
A2: pop_total | B2: South African mid-year population 2026 | C2: people | D2: 63100945 | E2: 63522380 | F2: 63522380 | G2: + | H2: https://www.statssa.gov.za/publications/P0302/P03022026.pdf (Table 1) | I2: 2026-10-20 | J2: Low is the 2025 estimate from https://www.statssa.gov.za/?p=18613 | K2: =IF($G2="+",MIN(D2,F2),MAX(D2,F2)) | L2: =E2 | M2: =IF($G2="+",MAX(D2,F2),MIN(D2,F2))
A3: pop_15plus | B3: Population aged 15 and over, 2026 | C3: people | D3: 46700000 | E3: 47276319 | F3: 47276319 | G3: + | H3: Derived from https://www.statssa.gov.za/publications/P0302/P03022026.pdf (Table 5) | I3: 2026-10-20 | J3: 63 522 380 minus ages 0 to 14 (5 325 401 + 5 448 245 + 5 472 415). Low is Findex population 15+ (46.7m) | K3: =IF($G3="+",MIN(D3,F3),MAX(D3,F3)) | L3: =E3 | M3: =IF($G3="+",MAX(D3,F3),MIN(D3,F3))
A4: pop_18plus | B4: Adults aged 18 and over, 2026 (estimate) | C4: people | D4: 43300000 | E4: 43905000 | F4: 44500000 | G4: + | H4: Derived from Stats SA Table 5 plus Assumption | I4: 2026-10-20 | J4: 15+ minus 3/5 of the 15 to 19 cohort (5 618 124). Assumes even spread by single year of age | K4: =IF($G4="+",MIN(D4,F4),MAX(D4,F4)) | L4: =E4 | M4: =IF($G4="+",MAX(D4,F4),MIN(D4,F4))
A5: acct_ownership | B5: Adults 15+ with any account (bank, FI or mobile money), 2024 | C5: fraction | D5: 0.784 | E5: 0.811 | F5: 0.854 | G5: + | H5: https://thedocs.worldbank.org/en/doc/be6615202d1f08a25855c8ac2d615122-0050012025/related/Little-Data-Book-2025-Web.pdf (South Africa page) | I5: 2026-10-20 | J5: Global Findex 2025. Low is bank or FI account only (78.4). High is the 2021 value (85.4). Ownership fell from 2021 to 2024 | K5: =IF($G5="+",MIN(D5,F5),MAX(D5,F5)) | L5: =E5 | M5: =IF($G5="+",MAX(D5,F5),MIN(D5,F5))
A6: acct_digital_enabled | B6: Adults 15+ with an account used with a card or phone | C6: fraction | D6: 0.6 | E6: 0.678 | F6: 0.72 | G6: + | H6: Same Little Data Book, South Africa page | I6: 2026-10-20 | J6: Range is Assumption around the point value | K6: =IF($G6="+",MIN(D6,F6),MAX(D6,F6)) | L6: =E6 | M6: =IF($G6="+",MAX(D6,F6),MIN(D6,F6))
A7: acct_poorest40 | B7: Account ownership, poorest 40 percent of households | C7: fraction | D7: 0.7 | E7: 0.742 | F7: 0.78 | G7: + | H7: Same Little Data Book, South Africa page | I7: 2026-10-20 | J7: Range Assumption | K7: =IF($G7="+",MIN(D7,F7),MAX(D7,F7)) | L7: =E7 | M7: =IF($G7="+",MAX(D7,F7),MIN(D7,F7))
A8: smartphone_own | B8: Adults 15+ with a personal smartphone | C8: fraction | D8: 0.526 | E8: 0.675 | F8: 0.75 | G8: + | H8: Same Little Data Book, South Africa page | I8: 2026-10-20 | J8: Low is the poorest 40 percent (52.6). High is Assumption for 2026 growth | K8: =IF($G8="+",MIN(D8,F8),MAX(D8,F8)) | L8: =E8 | M8: =IF($G8="+",MAX(D8,F8),MIN(D8,F8))
A9: mobile_phone_own | B9: Adults 15+ with any personal mobile phone | C9: fraction | D9: 0.825 | E9: 0.87 | F9: 0.9 | G9: + | H9: Same Little Data Book, South Africa page | I9: 2026-10-20 | J9: Relevant to SMS reach. Low is poorest 40 percent | K9: =IF($G9="+",MIN(D9,F9),MAX(D9,F9)) | L9: =E9 | M9: =IF($G9="+",MAX(D9,F9),MIN(D9,F9))
A10: internet_users | B10: Internet users, October 2025 | C10: people | D10: 50000000 | E10: 51700000 | F10: 52500000 | G10: + | H10: https://datareportal.com/reports/digital-2026-south-africa | I10: 2026-10-20 | J10: 79.6 percent penetration. Range Assumption | K10: =IF($G10="+",MIN(D10,F10),MAX(D10,F10)) | L10: =E10 | M10: =IF($G10="+",MAX(D10,F10),MIN(D10,F10))
A11: internet_pen | B11: Internet penetration of total population | C11: fraction | D11: 0.75 | E11: 0.796 | F11: 0.82 | G11: + | H11: https://datareportal.com/reports/digital-2026-south-africa | I11: 2026-10-20 | J11: Range Assumption | K11: =IF($G11="+",MIN(D11,F11),MAX(D11,F11)) | L11: =E11 | M11: =IF($G11="+",MAX(D11,F11),MIN(D11,F11))
A12: employed | B12: Employed persons, QLFS Q2 2026 | C12: people | D12: 16700000 | E12: 16700000 | F12: 16700000 | G12: + | H12: https://www.sanews.gov.za/south-africa/sa-official-unemployment-rate-rises-336 and https://www.statssa.gov.za/publications/P0211/Media%20Release%20QLFS%20Q2%202026.pdf | I12: 2026-10-20 | J12: Released 11 August 2026 | K12: =IF($G12="+",MIN(D12,F12),MAX(D12,F12)) | L12: =E12 | M12: =IF($G12="+",MAX(D12,F12),MIN(D12,F12))
A13: unemployed | B13: Unemployed persons, QLFS Q2 2026 | C13: people | D13: 8500000 | E13: 8500000 | F13: 8500000 | G13: + | H13: Same as above | I13: 2026-10-20 | J13: Official rate 33.6 percent | K13: =IF($G13="+",MIN(D13,F13),MAX(D13,F13)) | L13: =E13 | M13: =IF($G13="+",MAX(D13,F13),MIN(D13,F13))
... A46: db_compute | B46: Supabase compute add-on (Large) | C46: USD per month | D46: 15 | E46: 110 | F46: 410 | G46: - | H46: https://supabase.com/pricing | I46: 2026-10-20 | J46: Low is Small, high is 2XL. A bank will likely require hosting in its own cloud tenancy, which changes this line entirely | K46: =IF($G46="+",MIN(D46,F46),MAX(D46,F46)) | L46: =E46 | M46: =IF($G46="+",MAX(D46,F46),MIN(D46,F46))
A47: db_egress_overage | B47: Egress above included 250 GB | C47: USD per GB | D47: 0.09 | E47: 0.09 | F47: 0.09 | G47: - | H47: https://supabase.com/pricing | I47: 2026-10-20 | K47: =IF($G47="+",MIN(D47,F47),MAX(D47,F47)) | L47: =E47 | M47: =IF($G47="+",MAX(D47,F47),MIN(D47,F47))
A48: hosting_per_mau | B48: All-in cloud, database and hosting cost per MAU | C48: ZAR per MAU per month | D48: 0.05 | E48: 0.15 | F48: 0.6 | G48: - | H48: Assumption | I48: 2026-10-20 | J48: Fixed base above spread over 20k to 200k MAU, plus storage of about 2 000 transactions per user. Bank tenancy or on-premises could be higher | K48: =IF($G48="+",MIN(D48,F48),MAX(D48,F48)) | L48: =E48 | M48: =IF($G48="+",MAX(D48,F48),MIN(D48,F48))
A49: forecast_compute | B49: Forecast engine compute per MAU | C49: ZAR per MAU per month | D49: 0.005 | E49: 0.02 | F49: 0.1 | G49: - | H49: Assumption | I49: 2026-10-20 | J49: Engine is pure TypeScript percentile maths (`src/engine/forecast.ts`); one run per user per day is negligible | K49: =IF($G49="+",MIN(D49,F49),MAX(D49,F49)) | L49: =E49 | M49: =IF($G49="+",MAX(D49,F49),MIN(D49,F49))
A50: llm_in_price | B50: Claude Haiku 5.5 input price (prompts up to 100K tokens) | C50: USD per million tokens | D50: 0.1 | E50: 0.1 | F50: 2 | G50: - | H50: https://claude.com/pricing | I50: 2026-10-20 | J50: High is Sonnet 5.5 input | K50: =IF($G50="+",MIN(D50,F50),MAX(D50,F50)) | L50: =E50 | M50: =IF($G50="+",MAX(D50,F50),MIN(D50,F50))
A51: llm_out_price | B51: Claude Haiku 5.5 output price | C51: USD per million tokens | D51: 0.5 | E51: 0.5 | F51: 10 | G51: - | H51: https://claude.com/pricing | I51: 2026-10-20 | J51: High is Sonnet 5.5 output. Batch processing is 50 percent off (same page) | K51: =IF($G51="+",MIN(D51,F51),MAX(D51,F51)) | L51: =E51 | M51: =IF($G51="+",MAX(D51,F51),MIN(D51,F51))
A52: tokens_in_msg | B52: Input tokens per generated message | C52: tokens | D52: 300 | E52: 600 | F52: 1500 | G52: - | H52: Assumption | I52: 2026-10-20 | J52: System prompt, forecast summary and language instruction | K52: =IF($G52="+",MIN(D52,F52),MAX(D52,F52)) | L52: =E52 | M52: =IF($G52="+",MAX(D52,F52),MIN(D52,F52))
A53: tokens_out_msg | B53: Output tokens per generated message | C53: tokens | D53: 60 | E53: 120 | F53: 250 | G53: - | H53: Assumption | I53: 2026-10-20 | J53: WhatsApp template in `src/messages/templates.ts` is five short lines | K53: =IF($G53="+",MIN(D53,F53),MAX(D53,F53)) | L53: =E53 | M53: =IF($G53="+",MAX(D53,F53),MIN(D53,F53))
A54: msgs_per_month | B54: Proactive messages per MAU per month | C54: messages | D54: 4 | E54: 8 | F54: 30 | G54: - | H54: Assumption | I54: 2026-10-20 | J54: Brief describes a daily message (30). Base is twice weekly plus state changes, because daily paid messaging breaks the unit economics (see commercial.md COMM-03) | K54: =IF($G54="+",MIN(D54,F54),MAX(D54,F54)) | L54: =E54 | M54: =IF($G54="+",MAX(D54,F54),MIN(D54,F54))
A55: wa_utility | B55: WhatsApp utility template message, South Africa, from 1 Oct 2026 | C55: USD per delivered message | D55: 0.0071 | E55: 0.0095 | F55: 0.0379 | G55: - | H55: https://chatmaxima.com/whatsapp-api-pricing/south-africa/ | I55: 2026-10-20 | J55: Meta's own page https://developers.facebook.com/docs/whatsapp/pricing confirms a utility increase for South Africa on 1 Oct 2026 but the amount was in a linked CSV not read. Low applies the maximum 25 percent volume tier. High is the marketing rate, if Meta classes daily nudges as marketing. Excludes VAT and BSP fees | K55: =IF($G55="+",MIN(D55,F55),MAX(D55,F55)) | L55: =E55 | M55: =IF($G55="+",MAX(D55,F55),MIN(D55,F55))
A56: wa_marketing | B56: WhatsApp marketing template message, South Africa | C56: USD per delivered message | D56: 0.0379 | E56: 0.0379 | F56: 0.0379 | G56: - | H56: https://chatmaxima.com/whatsapp-api-pricing/south-africa/ | I56: 2026-10-20 | J56: Reseller page quoting Meta list rate. Not tiered | K56: =IF($G56="+",MIN(D56,F56),MAX(D56,F56)) | L56: =E56 | M56: =IF($G56="+",MAX(D56,F56),MIN(D56,F56))
A57: wa_service_free | B57: Free service messages per phone number per month | C57: messages | D57: 1000 | E57: 1000 | F57: 1000 | G57: + | H57: https://chatmaxima.com/whatsapp-api-pricing/south-africa/ | I57: 2026-10-20 | J57: Only user-initiated conversations. Utility inside an open 24 hour window is free | K57: =IF($G57="+",MIN(D57,F57),MAX(D57,F57)) | L57: =E57 | M57: =IF($G57="+",MAX(D57,F57),MIN(D57,F57))
A58: wa_bsp_fee | B58: Business solution provider fee per message | C58: ZAR per message | D58: 0 | E58: 0.05 | F58: 0.15 | G58: - | H58: Assumption | I58: 2026-10-20 | J58: BSPs add platform fees (noted on the ChatMaxima page) but no SA rate card was found | K58: =IF($G58="+",MIN(D58,F58),MAX(D58,F58)) | L58: =E58 | M58: =IF($G58="+",MAX(D58,F58),MIN(D58,F58))
A59: sms_price | B59: Bulk SMS to South Africa, 0 to 10 000 per month | C59: ZAR per SMS excl. VAT | D59: 0.14 | E59: 0.24 | F59: 0.24 | G59: - | H59: https://www.panaceamobile.com/gateways/bulk-sms-gateway/ | I59: 2026-10-20 | J59: Panacea tiers fall to R0.17 at 250k+. Low is SMSFlow 14c reported at https://www.itweb.co.za/office/datanamix/content/xA9POvNE6a9qo4J8 (sponsored article) | K59: =IF($G59="+",MIN(D59,F59),MAX(D59,F59)) | L59: =E59 | M59: =IF($G59="+",MAX(D59,F59),MIN(D59,F59))
... A81: capitec_returned_do | B81: Capitec returned debit order fee (insufficient funds), personal | C81: ZAR per item | D81: 6 | E81: 6 | F81: 6 | G81: + | H81: https://www.capitecbank.co.za/globalassets/pages/documents-library/transact/personal-banking-fees-2026.pdf | I81: 2026-10-20 | J81: Valid from 1 March 2026 | K81: =IF($G81="+",MIN(D81,F81),MAX(D81,F81)) | L81: =E81 | M81: =IF($G81="+",MAX(D81,F81),MIN(D81,F81))
A82: capitec_do_fee | B82: Capitec debit order fee | C82: ZAR per item | D82: 3 | E82: 3 | F82: 3 | G82: + | H82: Same Capitec PDF | I82: 2026-10-20 | K82: =IF($G82="+",MIN(D82,F82),MAX(D82,F82)) | L82: =E82 | M82: =IF($G82="+",MAX(D82,F82),MIN(D82,F82))
A83: capitec_monthly_fee | B83: Capitec main account monthly fee | C83: ZAR per month | D83: 7.5 | E83: 7.5 | F83: 7.5 | G83: + | H83: Same Capitec PDF | I83: 2026-10-20 | J83: Price anchor for the segment | K83: =IF($G83="+",MIN(D83,F83),MAX(D83,F83)) | L83: =E83 | M83: =IF($G83="+",MAX(D83,F83),MIN(D83,F83))
A84: sb_unpaid_payt | B84: Standard Bank Access Account unpaid debit order, pay as you transact | C84: ZAR per item | D84: 25 | E84: 25 | F84: 25 | G84: + | H84: https://www.standardbank.co.za/static_file/South%20Africa/PDF/Personal%20Pricing/2026/Access_Account_Pricing_Guide_2026.pdf | I84: 2026-10-20 | J84: 2026 guide | K84: =IF($G84="+",MIN(D84,F84),MAX(D84,F84)) | L84: =E84 | M84: =IF($G84="+",MAX(D84,F84),MIN(D84,F84))
A85: sb_unpaid_bundle | B85: Standard Bank Access Account bundle: unpaid debit orders after 3 free per 12 months | C85: ZAR per item | D85: 130 | E85: 130 | F85: 130 | G85: + | H85: Same Standard Bank PDF | I85: 2026-10-20 | J85: First 3 in a rolling 12 months are free | K85: =IF($G85="+",MIN(D85,F85),MAX(D85,F85)) | L85: =E85 | M85: =IF($G85="+",MAX(D85,F85),MIN(D85,F85))
A86: sb_business_unpaid | B86: Standard Bank business current account unpaid debit order | C86: ZAR per item | D86: 155 | E86: 155 | F86: 155 | G86: + | H86: https://www.standardbank.co.za/static_file/South%20Africa/PDF/Business%20Pricing/2026/Business%20Current%20Account%20Pricing%20Guide%202026.pdf | I86: 2026-10-20 | J86: From search snippet, not opened. Relevant for spaza owners on business accounts | K86: =IF($G86="+",MIN(D86,F86),MAX(D86,F86)) | L86: =E86 | M86: =IF($G86="+",MAX(D86,F86),MIN(D86,F86))
A87: fnb_unpaid_fee | B87: FNB personal unpaid debit order fee | C87: ZAR per item | D87: 0 | E87: 0 | F87: 0 | G87: + | H87: Not sourced | I87: 2026-10-20 | J87: fnb.co.za pricing pages returned a bot check and the 2025/26 SA guide was not retrievable. Use Capitec and Standard Bank as the range until the FNB guide is checked by hand | K87: =IF($G87="+",MIN(D87,F87),MAX(D87,F87)) | L87: =E87 | M87: =IF($G87="+",MAX(D87,F87),MIN(D87,F87))
A88: repo_rate | B88: SARB repo rate | C88: fraction | D88: 0.07 | E88: 0.07 | F88: 0.0725 | G88: + | H88: https://www.ewn.co.za/2026/07/23/sarb-keeps-interest-rates-unchanged-surprising-markets-and-analysts | I88: 2026-10-20 | J88: July 2026 hold at 7 percent. High is a single-source report of a September hike to 7.25 at https://briefly.co.za/business-economy/money/254111-sarb-raises-repo-rate-725-what-means-bills-sa/ | K88: =IF($G88="+",MIN(D88,F88),MAX(D88,F88)) | L88: =E88 | M88: =IF($G88="+",MAX(D88,F88),MIN(D88,F88))
A89: nca_cap_unsecured | B89: NCA maximum rate, unsecured credit | C89: fraction | D89: 0.21 | E89: 0.21 | F89: 0.21 | G89: + | H89: https://mjkinc.co.za/finance-credit-law/interest-cap-and-in-duplum-calculator | I89: 2026-10-20 | J89: Regulation 42 Table A per a law firm summary. 28 percent at 7 percent repo | K89: =IF($G89="+",MIN(D89,F89),MAX(D89,F89)) | L89: =E89 | M89: =IF($G89="+",MAX(D89,F89),MIN(D89,F89))
A90: nca_cap_facility | B90: NCA maximum rate, credit facilities (cards, overdrafts likely) | C90: fraction | D90: 0.14 | E90: 0.14 | F90: 0.14 | G90: + | H90: Same page | I90: 2026-10-20 | J90: Whether overdrafts fall here is not confirmed by the source | K90: =IF($G90="+",MIN(D90,F90),MAX(D90,F90)) | L90: =E90 | M90: =IF($G90="+",MAX(D90,F90),MIN(D90,F90))
A91: pasa_unpaid_benchmark | B91: Acceptable unpaid debit order ratio for collectors | C91: fraction | D91: 0.04 | E91: 0.1 | F91: 0.1 | G91: + | H91: https://help.netcash.co.za/?p=9799 | I91: 2026-10-20 | J91: Undated. Low is 2016 PASA data (1.2m unpaid of 31m a month, 3.9 percent) at https://businesstech.co.za/news/?p=136339 | K91: =IF($G91="+",MIN(D91,F91),MAX(D91,F91)) | L91: =E91 | M91: =IF($G91="+",MAX(D91,F91),MIN(D91,F91))
A92: share_users_unpaid | B92: Share of target users with at least one unpaid debit order a year | C92: fraction | D92: 0.1 | E92: 0.25 | F92: 0.4 | G92: + | H92: Assumption | I92: 2026-10-20 | J92: Informed by 41 percent of credit-active consumers in default (credit_default_share) | K92: =IF($G92="+",MIN(D92,F92),MAX(D92,F92)) | L92: =E92 | M92: =IF($G92="+",MAX(D92,F92),MIN(D92,F92))
A93: unpaid_events_per_user | B93: Unpaid events a year among affected users | C93: events per year | D93: 1 | E93: 2 | F93: 4 | G93: + | H93: Assumption | I93: 2026-10-20 | K93: =IF($G93="+",MIN(D93,F93),MAX(D93,F93)) | L93: =E93 | M93: =IF($G93="+",MAX(D93,F93),MIN(D93,F93))
A94: unpaid_reduction | B94: Reduction in unpaid events among active users | C94: fraction | D94: 0 | E94: 0.1 | F94: 0.3 | G94: + | H94: Assumption | I94: 2026-10-20 | J94: No evidence yet. Must be measured in a pilot with a control group | K94: =IF($G94="+",MIN(D94,F94),MAX(D94,F94)) | L94: =E94 | M94: =IF($G94="+",MAX(D94,F94),MIN(D94,F94))
A95: bank_cost_per_unpaid | B95: Bank operational cost per unpaid item (processing, contact) | C95: ZAR per item | D95: 5 | E95: 15 | F95: 40 | G95: + | H95: Assumption | I95: 2026-10-20 | J95: Not public | K95: =IF($G95="+",MIN(D95,F95),MAX(D95,F95)) | L95: =E95 | M95: =IF($G95="+",MAX(D95,F95),MIN(D95,F95))
A96: deposit_uplift | B96: Change in average balance held by an active user | C96: ZAR per user | D96: 0 | E96: 200 | F96: 1000 | G96: + | H96: Assumption | I96: 2026-10-20 | J96: Could also be negative if users spend up to "safe to spend" | K96: =IF($G96="+",MIN(D96,F96),MAX(D96,F96)) | L96: =E96 | M96: =IF($G96="+",MAX(D96,F96),MIN(D96,F96))
A97: nim_on_deposits | B97: Bank margin earned on retail deposits | C97: fraction | D97: 0.02 | E97: 0.04 | F97: 0.06 | G97: + | H97: Assumption | I97: 2026-10-20 | J97: Not taken from any bank disclosure | K97: =IF($G97="+",MIN(D97,F97),MAX(D97,F97)) | L97: =E97 | M97: =IF($G97="+",MAX(D97,F97),MIN(D97,F97))
A98: attrition_reduction | B98: Reduction in annual customer attrition among active users | C98: fraction | D98: 0 | E98: 0.01 | F98: 0.03 | G98: + | H98: Assumption | I98: 2026-10-20 | K98: =IF($G98="+",MIN(D98,F98),MAX(D98,F98)) | L98: =E98 | M98: =IF($G98="+",MAX(D98,F98),MIN(D98,F98))
A99: value_per_customer_year | B99: Annual net revenue per retained retail customer in segment | C99: ZAR per year | D99: 800 | E99: 1500 | F99: 3000 | G99: + | H99: Assumption | I99: 2026-10-20 | J99: Not public at segment level | K99: =IF($G99="+",MIN(D99,F99),MAX(D99,F99)) | L99: =E99 | M99: =IF($G99="+",MAX(D99,F99),MIN(D99,F99))
A100: contact_avoided | B100: Contact centre calls avoided per MAU per year | C100: calls per year | D100: 0 | E100: 0.2 | F100: 1 | G100: + | H100: Assumption | I100: 2026-10-20 | J100: Balance and "why was I charged" calls | K100: =IF($G100="+",MIN(D100,F100),MAX(D100,F100)) | L100: =E100 | M100: =IF($G100="+",MAX(D100,F100),MIN(D100,F100))
A101: cost_per_call | B101: Bank cost per contact centre call | C101: ZAR per call | D101: 20 | E101: 40 | F101: 80 | G101: + | H101: Assumption | I101: 2026-10-20 | K101: =IF($G101="+",MIN(D101,F101),MAX(D101,F101)) | L101: =E101 | M101: =IF($G101="+",MAX(D101,F101),MIN(D101,F101))
A102: share_behaviour_change | B102: Share of MAU who change a decision because of the forecast in a month | C102: fraction | D102: 0.05 | E102: 0.2 | F102: 0.35 | G102: + | H102: Assumption | I102: 2026-10-20 | J102: Outcome metric: track "state transitions acted on" | K102: =IF($G102="+",MIN(D102,F102),MAX(D102,F102)) | L102: =E102 | M102: =IF($G102="+",MAX(D102,F102),MIN(D102,F102))
A103: days_cover_gained | B103: Days of cover gained per behaviour-changing user per month | C103: days | D103: 0.5 | E103: 2 | F103: 5 | G103: + | H103: Assumption | I103: 2026-10-20 | J103: Measured as forecast date versus actual run-out | K103: =IF($G103="+",MIN(D103,F103),MAX(D103,F103)) | L103: =E103 | M103: =IF($G103="+",MAX(D103,F103),MIN(D103,F103))
A104: shortfalls_avoided | B104: Short episodes avoided per active user per year | C104: episodes per year | D104: 0 | E104: 0.5 | F104: 2 | G104: + | H104: Assumption | I104: 2026-10-20 | K104: =IF($G104="+",MIN(D104,F104),MAX(D104,F104)) | L104: =E104 | M104: =IF($G104="+",MAX(D104,F104),MIN(D104,F104))
A105: fees_avoided | B105: Bank and informal fees avoided per active user per year | C105: ZAR per year | D105: 0 | E105: 30 | F105: 260 | G105: + | H105: Assumption | I105: 2026-10-20 | J105: Unpaid debit order fees alone give share_users_unpaid x unpaid_events_per_user x unpaid_reduction x fee: 0.25 x 2 x 0.10 x R25 = R1.25 in the base. The rest of the R30 is assumed avoided late-payment and informal lending costs. High uses 0.40 x 4 x 0.30 x R130 plus other costs, capped at R260 | K105: =IF($G105="+",MIN(D105,F105),MAX(D105,F105)) | L105: =E105 | M105: =IF($G105="+",MAX(D105,F105),MIN(D105,F105))
A106: confidence_baseline | B106: Baseline share able to raise money in 30 days (proxy for confidence) | C106: fraction | D106: 0.183 | E106: 0.308 | F106: 0.308 | G106: + | H106: Little Data Book 2025, South Africa page | I106: 2026-10-20 | J106: Proposed survey item: "How sure are you that your money will last until your next money?" (5 point scale) | K106: =IF($G106="+",MIN(D106,F106),MAX(D106,F106)) | L106: =E106 | M106: =IF($G106="+",MAX(D106,F106),MIN(D106,F106))
A107: confidence_change | B107: Change in share reporting confidence after 3 months | C107: fraction | D107: 0 | E107: 0.05 | F107: 0.1 | G107: + | H107: Assumption | I107: 2026-10-20 | J107: Needs a pre and post survey with a comparison group | K107: =IF($G107="+",MIN(D107,F107),MAX(D107,F107)) | L107: =E107 | M107: =IF($G107="+",MAX(D107,F107),MIN(D107,F107))
A108: d30_finance_apps | B108: Day 30 retention, finance apps | C108: fraction | D108: 0.042 | E108: 0.042 | F108: 0.15 | G108: + | H108: https://www.getpanto.ai/blog/mobile-app-retention-statistics | I108: 2026-10-20 | J108: Vendor blog, unattributed figure. High is the same page's 10 to 15 percent for fintech and banking apps | K108: =IF($G108="+",MIN(D108,F108),MAX(D108,F108)) | L108: =E108 | M108: =IF($G108="+",MAX(D108,F108),MIN(D108,F108))
A109: d1_fintech | B109: Day 1 retention, fintech apps | C109: fraction | D109: 0.15 | E109: 0.22 | F109: 0.3 | G109: + | H109: Same page | I109: 2026-10-20 | J109: Weak source. Range Assumption | K109: =IF($G109="+",MIN(D109,F109),MAX(D109,F109)) | L109: =E109 | M109: =IF($G109="+",MAX(D109,F109),MIN(D109,F109))
A110: uninstall_m1 | B110: Share of finance app installs uninstalled in month one | C110: fraction | D110: 0.45 | E110: 0.475 | F110: 0.5 | G110: - | H110: https://clevertap.com/wp-content/uploads/2025/11/BFSI-Benchmark-Report-Retention.pdf | I110: 2026-10-20 | J110: From search snippet, not opened | K110: =IF($G110="+",MIN(D110,F110),MAX(D110,F110)) | L110: =E110 | M110: =IF($G110="+",MAX(D110,F110),MIN(D110,F110))
A111: churn_embedded | B111: Monthly churn of activated users, embedded in a bank app | C111: fraction | D111: 0.02 | E111: 0.04 | F111: 0.08 | G111: - | H111: Assumption | I111: 2026-10-20 | J111: Bank app is opened anyway; feature churn is lower than app churn | K111: =IF($G111="+",MIN(D111,F111),MAX(D111,F111)) | L111: =E111 | M111: =IF($G111="+",MAX(D111,F111),MIN(D111,F111))
A112: churn_consumer | B112: Monthly churn of paying subscribers, standalone | C112: fraction | D112: 0.08 | E112: 0.12 | F112: 0.25 | G112: - | H112: Assumption | I112: 2026-10-20 | J112: Above the weak public figure of about 10 percent for budgeting subscriptions | K112: =IF($G112="+",MIN(D112,F112),MAX(D112,F112)) | L112: =E112 | M112: =IF($G112="+",MAX(D112,F112),MIN(D112,F112))
A113: cpi_global | B113: Facebook cost per app install, global median baseline | C113: USD per install | D113: 1.98 | E113: 15.6 | F113: 26.21 | G113: - | H113: https://www.superads.ai/facebook-ads-costs/cost-per-app-install/marketplaces/south-africa | I113: 2026-10-20 | J113: Vendor tool, global not South African, not finance specific. Use only as a ceiling check. SA CPI is likely lower (Assumption) | K113: =IF($G113="+",MIN(D113,F113),MAX(D113,F113)) | L113: =E113 | M113: =IF($G113="+",MAX(D113,F113),MIN(D113,F113))
A114: install_to_active | B114: Share of installs that become monthly active | C114: fraction | D114: 0.1 | E114: 0.25 | F114: 0.4 | G114: + | H114: Assumption | I114: 2026-10-20 | K114: =IF($G114="+",MIN(D114,F114),MAX(D114,F114)) | L114: =E114 | M114: =IF($G114="+",MAX(D114,F114),MIN(D114,F114))
A115: cac_consumer | B115: Blended CAC for a standalone consumer user | C115: ZAR per MAU | D115: 40 | E115: 120 | F115: 400 | G115: - | H115: Assumption | I115: 2026-10-20 | J115: Assumes SA CPI of R30 (R10 to R100) divided by install_to_active | K115: =IF($G115="+",MIN(D115,F115),MAX(D115,F115)) | L115: =E115 | M115: =IF($G115="+",MAX(D115,F115),MIN(D115,F115))
A116: cac_embedded | B116: Tengo's CAC per MAU when the bank distributes | C116: ZAR per MAU | D116: 0 | E116: 10 | F116: 50 | G116: - | H116: Assumption | I116: 2026-10-20 | J116: Bank bears placement cost; Tengo bears onboarding content and co-marketing | K116: =IF($G116="+",MIN(D116,F116),MAX(D116,F116)) | L116: =E116 | M116: =IF($G116="+",MAX(D116,F116),MIN(D116,F116))
A117: cac_sponsor | B117: Cost to onboard one user through agents or NGOs | C117: ZAR per user | D117: 30 | E117: 80 | F117: 200 | G117: - | H117: Assumption | I117: 2026-10-20 | J117: Field onboarding, data-light | K117: =IF($G117="+",MIN(D117,F117),MAX(D117,F117)) | L117: =E117 | M117: =IF($G117="+",MAX(D117,F117),MIN(D117,F117))
A118: pilot_months | B118: Months of paid pilot before rollout | C118: months | D118: 9 | E118: 6 | F118: 4 | G118: - | H118: Assumption | I118: 2026-10-20 | J118: Typical bank pilots run one to two quarters | K118: =IF($G118="+",MIN(D118,F118),MAX(D118,F118)) | L118: =E118 | M118: =IF($G118="+",MAX(D118,F118),MIN(D118,F118))
A119: pilot_mau_share | B119: Pilot MAU as a share of steady-state MAU | C119: fraction | D119: 0.02 | E119: 0.05 | F119: 0.1 | G119: + | H119: Assumption | I119: 2026-10-20 | J119: Pilot cohort behind a feature flag | K119: =IF($G119="+",MIN(D119,F119),MAX(D119,F119)) | L119: =E119 | M119: =IF($G119="+",MAX(D119,F119),MIN(D119,F119))
A120: ramp_months | B120: Months from end of pilot to steady-state MAU | C120: months | D120: 18 | E120: 12 | F120: 9 | G120: - | H120: Assumption | I120: 2026-10-20 | J120: Linear ramp | K120: =IF($G120="+",MIN(D120,F120),MAX(D120,F120)) | L120: =E120 | M120: =IF($G120="+",MAX(D120,F120),MIN(D120,F120))
A121: opening_cash | B121: Cash available at month 0 | C121: ZAR | D121: 0 | E121: 0 | F121: 0 | G121: + | H121: Assumption | I121: 2026-10-20 | J121: Set to zero so the projection shows the funding need | K121: =IF($G121="+",MIN(D121,F121),MAX(D121,F121)) | L121: =E121 | M121: =IF($G121="+",MAX(D121,F121),MIN(D121,F121))

Sheet Model
A1: Model: three scenarios side by side
A3: Line | B3: Conservative | C3: Base | D3: Ambitious | E3: Formula or note
A4: Inputs used (linked from the Inputs sheet)
A5: Input: pop_15plus | B5: =INDEX(Inputs!$K$2:$K$121,MATCH("pop_15plus",Inputs!$A$2:$A$121,0)) | C5: =INDEX(Inputs!$L$2:$L$121,MATCH("pop_15plus",Inputs!$A$2:$A$121,0)) | D5: =INDEX(Inputs!$M$2:$M$121,MATCH("pop_15plus",Inputs!$A$2:$A$121,0)) | E5: From Inputs, key pop_15plus
A6: Input: acct_ownership | B6: =INDEX(Inputs!$K$2:$K$121,MATCH("acct_ownership",Inputs!$A$2:$A$121,0)) | C6: =INDEX(Inputs!$L$2:$L$121,MATCH("acct_ownership",Inputs!$A$2:$A$121,0)) | D6: =INDEX(Inputs!$M$2:$M$121,MATCH("acct_ownership",Inputs!$A$2:$A$121,0)) | E6: From Inputs, key acct_ownership
A7: Input: smartphone_own | B7: =INDEX(Inputs!$K$2:$K$121,MATCH("smartphone_own",Inputs!$A$2:$A$121,0)) | C7: =INDEX(Inputs!$L$2:$L$121,MATCH("smartphone_own",Inputs!$A$2:$A$121,0)) | D7: =INDEX(Inputs!$M$2:$M$121,MATCH("smartphone_own",Inputs!$A$2:$A$121,0)) | E7: From Inputs, key smartphone_own
A8: Input: informal_sector_emp | B8: =INDEX(Inputs!$K$2:$K$121,MATCH("informal_sector_emp",Inputs!$A$2:$A$121,0)) | C8: =INDEX(Inputs!$L$2:$L$121,MATCH("informal_sector_emp",Inputs!$A$2:$A$121,0)) | D8: =INDEX(Inputs!$M$2:$M$121,MATCH("informal_sector_emp",Inputs!$A$2:$A$121,0)) | E8: From Inputs, key informal_sector_emp
A9: Input: household_sector_emp | B9: =INDEX(Inputs!$K$2:$K$121,MATCH("household_sector_emp",Inputs!$A$2:$A$121,0)) | C9: =INDEX(Inputs!$L$2:$L$121,MATCH("household_sector_emp",Inputs!$A$2:$A$121,0)) | D9: =INDEX(Inputs!$M$2:$M$121,MATCH("household_sector_emp",Inputs!$A$2:$A$121,0)) | E9: From Inputs, key household_sector_emp
A10: Input: tam_irregular_adults | B10: =INDEX(Inputs!$K$2:$K$121,MATCH("tam_irregular_adults",Inputs!$A$2:$A$121,0)) | C10: =INDEX(Inputs!$L$2:$L$121,MATCH("tam_irregular_adults",Inputs!$A$2:$A$121,0)) | D10: =INDEX(Inputs!$M$2:$M$121,MATCH("tam_irregular_adults",Inputs!$A$2:$A$121,0)) | E10: From Inputs, key tam_irregular_adults
A11: Input: sam_share_banked_smartphone | B11: =INDEX(Inputs!$K$2:$K$121,MATCH("sam_share_banked_smartphone",Inputs!$A$2:$A$121,0)) | C11: =INDEX(Inputs!$L$2:$L$121,MATCH("sam_share_banked_smartphone",Inputs!$A$2:$A$121,0)) | D11: =INDEX(Inputs!$M$2:$M$121,MATCH("sam_share_banked_smartphone",Inputs!$A$2:$A$121,0)) | E11: From Inputs, key sam_share_banked_smartphone
A12: Input: partner_base | B12: =INDEX(Inputs!$K$2:$K$121,MATCH("partner_base",Inputs!$A$2:$A$121,0)) | C12: =INDEX(Inputs!$L$2:$L$121,MATCH("partner_base",Inputs!$A$2:$A$121,0)) | D12: =INDEX(Inputs!$M$2:$M$121,MATCH("partner_base",Inputs!$A$2:$A$121,0)) | E12: From Inputs, key partner_base
A13: Input: share_partner_irregular | B13: =INDEX(Inputs!$K$2:$K$121,MATCH("share_partner_irregular",Inputs!$A$2:$A$121,0)) | C13: =INDEX(Inputs!$L$2:$L$121,MATCH("share_partner_irregular",Inputs!$A$2:$A$121,0)) | D13: =INDEX(Inputs!$M$2:$M$121,MATCH("share_partner_irregular",Inputs!$A$2:$A$121,0)) | E13: From Inputs, key share_partner_irregular
A14: Input: share_eligible_offered | B14: =INDEX(Inputs!$K$2:$K$121,MATCH("share_eligible_offered",Inputs!$A$2:$A$121,0)) | C14: =INDEX(Inputs!$L$2:$L$121,MATCH("share_eligible_offered",Inputs!$A$2:$A$121,0)) | D14: =INDEX(Inputs!$M$2:$M$121,MATCH("share_eligible_offered",Inputs!$A$2:$A$121,0)) | E14: From Inputs, key share_eligible_offered
A15: Input: offered_to_activated | B15: =INDEX(Inputs!$K$2:$K$121,MATCH("offered_to_activated",Inputs!$A$2:$A$121,0)) | C15: =INDEX(Inputs!$L$2:$L$121,MATCH("offered_to_activated",Inputs!$A$2:$A$121,0)) | D15: =INDEX(Inputs!$M$2:$M$121,MATCH("offered_to_activated",Inputs!$A$2:$A$121,0)) | E15: From Inputs, key offered_to_activated
A16: Input: activated_to_mau | B16: =INDEX(Inputs!$K$2:$K$121,MATCH("activated_to_mau",Inputs!$A$2:$A$121,0)) | C16: =INDEX(Inputs!$L$2:$L$121,MATCH("activated_to_mau",Inputs!$A$2:$A$121,0)) | D16: =INDEX(Inputs!$M$2:$M$121,MATCH("activated_to_mau",Inputs!$A$2:$A$121,0)) | E16: From Inputs, key activated_to_mau
A17: Input: sponsor_reach | B17: =INDEX(Inputs!$K$2:$K$121,MATCH("sponsor_reach",Inputs!$A$2:$A$121,0)) | C17: =INDEX(Inputs!$L$2:$L$121,MATCH("sponsor_reach",Inputs!$A$2:$A$121,0)) | D17: =INDEX(Inputs!$M$2:$M$121,MATCH("sponsor_reach",Inputs!$A$2:$A$121,0)) | E17: From Inputs, key sponsor_reach
A18: Input: usd_zar | B18: =INDEX(Inputs!$K$2:$K$121,MATCH("usd_zar",Inputs!$A$2:$A$121,0)) | C18: =INDEX(Inputs!$L$2:$L$121,MATCH("usd_zar",Inputs!$A$2:$A$121,0)) | D18: =INDEX(Inputs!$M$2:$M$121,MATCH("usd_zar",Inputs!$A$2:$A$121,0)) | E18: From Inputs, key usd_zar
A19: Input: vat | B19: =INDEX(Inputs!$K$2:$K$121,MATCH("vat",Inputs!$A$2:$A$121,0)) | C19: =INDEX(Inputs!$L$2:$L$121,MATCH("vat",Inputs!$A$2:$A$121,0)) | D19: =INDEX(Inputs!$M$2:$M$121,MATCH("vat",Inputs!$A$2:$A$121,0)) | E19: From Inputs, key vat
A20: Input: hosting_per_mau | B20: =INDEX(Inputs!$K$2:$K$121,MATCH("hosting_per_mau",Inputs!$A$2:$A$121,0)) | C20: =INDEX(Inputs!$L$2:$L$121,MATCH("hosting_per_mau",Inputs!$A$2:$A$121,0)) | D20: =INDEX(Inputs!$M$2:$M$121,MATCH("hosting_per_mau",Inputs!$A$2:$A$121,0)) | E20: From Inputs, key hosting_per_mau
A21: Input: forecast_compute | B21: =INDEX(Inputs!$K$2:$K$121,MATCH("forecast_compute",Inputs!$A$2:$A$121,0)) | C21: =INDEX(Inputs!$L$2:$L$121,MATCH("forecast_compute",Inputs!$A$2:$A$121,0)) | D21: =INDEX(Inputs!$M$2:$M$121,MATCH("forecast_compute",Inputs!$A$2:$A$121,0)) | E21: From Inputs, key forecast_compute
A22: Input: llm_in_price | B22: =INDEX(Inputs!$K$2:$K$121,MATCH("llm_in_price",Inputs!$A$2:$A$121,0)) | C22: =INDEX(Inputs!$L$2:$L$121,MATCH("llm_in_price",Inputs!$A$2:$A$121,0)) | D22: =INDEX(Inputs!$M$2:$M$121,MATCH("llm_in_price",Inputs!$A$2:$A$121,0)) | E22: From Inputs, key llm_in_price
A23: Input: llm_out_price | B23: =INDEX(Inputs!$K$2:$K$121,MATCH("llm_out_price",Inputs!$A$2:$A$121,0)) | C23: =INDEX(Inputs!$L$2:$L$121,MATCH("llm_out_price",Inputs!$A$2:$A$121,0)) | D23: =INDEX(Inputs!$M$2:$M$121,MATCH("llm_out_price",Inputs!$A$2:$A$121,0)) | E23: From Inputs, key llm_out_price
A24: Input: tokens_in_msg | B24: =INDEX(Inputs!$K$2:$K$121,MATCH("tokens_in_msg",Inputs!$A$2:$A$121,0)) | C24: =INDEX(Inputs!$L$2:$L$121,MATCH("tokens_in_msg",Inputs!$A$2:$A$121,0)) | D24: =INDEX(Inputs!$M$2:$M$121,MATCH("tokens_in_msg",Inputs!$A$2:$A$121,0)) | E24: From Inputs, key tokens_in_msg
A25: Input: tokens_out_msg | B25: =INDEX(Inputs!$K$2:$K$121,MATCH("tokens_out_msg",Inputs!$A$2:$A$121,0)) | C25: =INDEX(Inputs!$L$2:$L$121,MATCH("tokens_out_msg",Inputs!$A$2:$A$121,0)) | D25: =INDEX(Inputs!$M$2:$M$121,MATCH("tokens_out_msg",Inputs!$A$2:$A$121,0)) | E25: From Inputs, key tokens_out_msg
A26: Input: msgs_per_month | B26: =INDEX(Inputs!$K$2:$K$121,MATCH("msgs_per_month",Inputs!$A$2:$A$121,0)) | C26: =INDEX(Inputs!$L$2:$L$121,MATCH("msgs_per_month",Inputs!$A$2:$A$121,0)) | D26: =INDEX(Inputs!$M$2:$M$121,MATCH("msgs_per_month",Inputs!$A$2:$A$121,0)) | E26: From Inputs, key msgs_per_month
A27: Input: wa_utility | B27: =INDEX(Inputs!$K$2:$K$121,MATCH("wa_utility",Inputs!$A$2:$A$121,0)) | C27: =INDEX(Inputs!$L$2:$L$121,MATCH("wa_utility",Inputs!$A$2:$A$121,0)) | D27: =INDEX(Inputs!$M$2:$M$121,MATCH("wa_utility",Inputs!$A$2:$A$121,0)) | E27: From Inputs, key wa_utility
A28: Input: wa_bsp_fee | B28: =INDEX(Inputs!$K$2:$K$121,MATCH("wa_bsp_fee",Inputs!$A$2:$A$121,0)) | C28: =INDEX(Inputs!$L$2:$L$121,MATCH("wa_bsp_fee",Inputs!$A$2:$A$121,0)) | D28: =INDEX(Inputs!$M$2:$M$121,MATCH("wa_bsp_fee",Inputs!$A$2:$A$121,0)) | E28: From Inputs, key wa_bsp_fee
A29: Input: sms_price | B29: =INDEX(Inputs!$K$2:$K$121,MATCH("sms_price",Inputs!$A$2:$A$121,0)) | C29: =INDEX(Inputs!$L$2:$L$121,MATCH("sms_price",Inputs!$A$2:$A$121,0)) | D29: =INDEX(Inputs!$M$2:$M$121,MATCH("sms_price",Inputs!$A$2:$A$121,0)) | E29: From Inputs, key sms_price
A30: Input: push_cost | B30: =INDEX(Inputs!$K$2:$K$121,MATCH("push_cost",Inputs!$A$2:$A$121,0)) | C30: =INDEX(Inputs!$L$2:$L$121,MATCH("push_cost",Inputs!$A$2:$A$121,0)) | D30: =INDEX(Inputs!$M$2:$M$121,MATCH("push_cost",Inputs!$A$2:$A$121,0)) | E30: From Inputs, key push_cost
A31: Input: support_per_mau | B31: =INDEX(Inputs!$K$2:$K$121,MATCH("support_per_mau",Inputs!$A$2:$A$121,0)) | C31: =INDEX(Inputs!$L$2:$L$121,MATCH("support_per_mau",Inputs!$A$2:$A$121,0)) | D31: =INDEX(Inputs!$M$2:$M$121,MATCH("support_per_mau",Inputs!$A$2:$A$121,0)) | E31: From Inputs, key support_per_mau
A32: Input: compliance_fixed | B32: =INDEX(Inputs!$K$2:$K$121,MATCH("compliance_fixed",Inputs!$A$2:$A$121,0)) | C32: =INDEX(Inputs!$L$2:$L$121,MATCH("compliance_fixed",Inputs!$A$2:$A$121,0)) | D32: =INDEX(Inputs!$M$2:$M$121,MATCH("compliance_fixed",Inputs!$A$2:$A$121,0)) | E32: From Inputs, key compliance_fixed
A33: Input: team_fixed | B33: =INDEX(Inputs!$K$2:$K$121,MATCH("team_fixed",Inputs!$A$2:$A$121,0)) | C33: =INDEX(Inputs!$L$2:$L$121,MATCH("team_fixed",Inputs!$A$2:$A$121,0)) | D33: =INDEX(Inputs!$M$2:$M$121,MATCH("team_fixed",Inputs!$A$2:$A$121,0)) | E33: From Inputs, key team_fixed
A34: Input: db_base | B34: =INDEX(Inputs!$K$2:$K$121,MATCH("db_base",Inputs!$A$2:$A$121,0)) | C34: =INDEX(Inputs!$L$2:$L$121,MATCH("db_base",Inputs!$A$2:$A$121,0)) | D34: =INDEX(Inputs!$M$2:$M$121,MATCH("db_base",Inputs!$A$2:$A$121,0)) | E34: From Inputs, key db_base
A35: Input: payfast_card_pct | B35: =INDEX(Inputs!$K$2:$K$121,MATCH("payfast_card_pct",Inputs!$A$2:$A$121,0)) | C35: =INDEX(Inputs!$L$2:$L$121,MATCH("payfast_card_pct",Inputs!$A$2:$A$121,0)) | D35: =INDEX(Inputs!$M$2:$M$121,MATCH("payfast_card_pct",Inputs!$A$2:$A$121,0)) | E35: From Inputs, key payfast_card_pct
A36: Input: payfast_card_fixed | B36: =INDEX(Inputs!$K$2:$K$121,MATCH("payfast_card_fixed",Inputs!$A$2:$A$121,0)) | C36: =INDEX(Inputs!$L$2:$L$121,MATCH("payfast_card_fixed",Inputs!$A$2:$A$121,0)) | D36: =INDEX(Inputs!$M$2:$M$121,MATCH("payfast_card_fixed",Inputs!$A$2:$A$121,0)) | E36: From Inputs, key payfast_card_fixed
A37: Input: lic_fee_per_mau | B37: =INDEX(Inputs!$K$2:$K$121,MATCH("lic_fee_per_mau",Inputs!$A$2:$A$121,0)) | C37: =INDEX(Inputs!$L$2:$L$121,MATCH("lic_fee_per_mau",Inputs!$A$2:$A$121,0)) | D37: =INDEX(Inputs!$M$2:$M$121,MATCH("lic_fee_per_mau",Inputs!$A$2:$A$121,0)) | E37: From Inputs, key lic_fee_per_mau
A38: Input: lic_pilot_fee | B38: =INDEX(Inputs!$K$2:$K$121,MATCH("lic_pilot_fee",Inputs!$A$2:$A$121,0)) | C38: =INDEX(Inputs!$L$2:$L$121,MATCH("lic_pilot_fee",Inputs!$A$2:$A$121,0)) | D38: =INDEX(Inputs!$M$2:$M$121,MATCH("lic_pilot_fee",Inputs!$A$2:$A$121,0)) | E38: From Inputs, key lic_pilot_fee
A39: Input: lic_platform_floor | B39: =INDEX(Inputs!$K$2:$K$121,MATCH("lic_platform_floor",Inputs!$A$2:$A$121,0)) | C39: =INDEX(Inputs!$L$2:$L$121,MATCH("lic_platform_floor",Inputs!$A$2:$A$121,0)) | D39: =INDEX(Inputs!$M$2:$M$121,MATCH("lic_platform_floor",Inputs!$A$2:$A$121,0)) | E39: From Inputs, key lic_platform_floor
A40: Input: outcome_share | B40: =INDEX(Inputs!$K$2:$K$121,MATCH("outcome_share",Inputs!$A$2:$A$121,0)) | C40: =INDEX(Inputs!$L$2:$L$121,MATCH("outcome_share",Inputs!$A$2:$A$121,0)) | D40: =INDEX(Inputs!$M$2:$M$121,MATCH("outcome_share",Inputs!$A$2:$A$121,0)) | E40: From Inputs, key outcome_share
A41: Input: sub_price | B41: =INDEX(Inputs!$K$2:$K$121,MATCH("sub_price",Inputs!$A$2:$A$121,0)) | C41: =INDEX(Inputs!$L$2:$L$121,MATCH("sub_price",Inputs!$A$2:$A$121,0)) | D41: =INDEX(Inputs!$M$2:$M$121,MATCH("sub_price",Inputs!$A$2:$A$121,0)) | E41: From Inputs, key sub_price
A42: Input: free_to_paid | B42: =INDEX(Inputs!$K$2:$K$121,MATCH("free_to_paid",Inputs!$A$2:$A$121,0)) | C42: =INDEX(Inputs!$L$2:$L$121,MATCH("free_to_paid",Inputs!$A$2:$A$121,0)) | D42: =INDEX(Inputs!$M$2:$M$121,MATCH("free_to_paid",Inputs!$A$2:$A$121,0)) | E42: From Inputs, key free_to_paid
A43: Input: sponsor_per_user_year | B43: =INDEX(Inputs!$K$2:$K$121,MATCH("sponsor_per_user_year",Inputs!$A$2:$A$121,0)) | C43: =INDEX(Inputs!$L$2:$L$121,MATCH("sponsor_per_user_year",Inputs!$A$2:$A$121,0)) | D43: =INDEX(Inputs!$M$2:$M$121,MATCH("sponsor_per_user_year",Inputs!$A$2:$A$121,0)) | E43: From Inputs, key sponsor_per_user_year
A44: Input: share_users_unpaid | B44: =INDEX(Inputs!$K$2:$K$121,MATCH("share_users_unpaid",Inputs!$A$2:$A$121,0)) | C44: =INDEX(Inputs!$L$2:$L$121,MATCH("share_users_unpaid",Inputs!$A$2:$A$121,0)) | D44: =INDEX(Inputs!$M$2:$M$121,MATCH("share_users_unpaid",Inputs!$A$2:$A$121,0)) | E44: From Inputs, key share_users_unpaid
A45: Input: unpaid_events_per_user | B45: =INDEX(Inputs!$K$2:$K$121,MATCH("unpaid_events_per_user",Inputs!$A$2:$A$121,0)) | C45: =INDEX(Inputs!$L$2:$L$121,MATCH("unpaid_events_per_user",Inputs!$A$2:$A$121,0)) | D45: =INDEX(Inputs!$M$2:$M$121,MATCH("unpaid_events_per_user",Inputs!$A$2:$A$121,0)) | E45: From Inputs, key unpaid_events_per_user
A46: Input: unpaid_reduction | B46: =INDEX(Inputs!$K$2:$K$121,MATCH("unpaid_reduction",Inputs!$A$2:$A$121,0)) | C46: =INDEX(Inputs!$L$2:$L$121,MATCH("unpaid_reduction",Inputs!$A$2:$A$121,0)) | D46: =INDEX(Inputs!$M$2:$M$121,MATCH("unpaid_reduction",Inputs!$A$2:$A$121,0)) | E46: From Inputs, key unpaid_reduction
A47: Input: bank_cost_per_unpaid | B47: =INDEX(Inputs!$K$2:$K$121,MATCH("bank_cost_per_unpaid",Inputs!$A$2:$A$121,0)) | C47: =INDEX(Inputs!$L$2:$L$121,MATCH("bank_cost_per_unpaid",Inputs!$A$2:$A$121,0)) | D47: =INDEX(Inputs!$M$2:$M$121,MATCH("bank_cost_per_unpaid",Inputs!$A$2:$A$121,0)) | E47: From Inputs, key bank_cost_per_unpaid
A48: Input: sb_unpaid_payt | B48: =INDEX(Inputs!$K$2:$K$121,MATCH("sb_unpaid_payt",Inputs!$A$2:$A$121,0)) | C48: =INDEX(Inputs!$L$2:$L$121,MATCH("sb_unpaid_payt",Inputs!$A$2:$A$121,0)) | D48: =INDEX(Inputs!$M$2:$M$121,MATCH("sb_unpaid_payt",Inputs!$A$2:$A$121,0)) | E48: From Inputs, key sb_unpaid_payt
A49: Input: deposit_uplift | B49: =INDEX(Inputs!$K$2:$K$121,MATCH("deposit_uplift",Inputs!$A$2:$A$121,0)) | C49: =INDEX(Inputs!$L$2:$L$121,MATCH("deposit_uplift",Inputs!$A$2:$A$121,0)) | D49: =INDEX(Inputs!$M$2:$M$121,MATCH("deposit_uplift",Inputs!$A$2:$A$121,0)) | E49: From Inputs, key deposit_uplift
A50: Input: nim_on_deposits | B50: =INDEX(Inputs!$K$2:$K$121,MATCH("nim_on_deposits",Inputs!$A$2:$A$121,0)) | C50: =INDEX(Inputs!$L$2:$L$121,MATCH("nim_on_deposits",Inputs!$A$2:$A$121,0)) | D50: =INDEX(Inputs!$M$2:$M$121,MATCH("nim_on_deposits",Inputs!$A$2:$A$121,0)) | E50: From Inputs, key nim_on_deposits
A51: Input: attrition_reduction | B51: =INDEX(Inputs!$K$2:$K$121,MATCH("attrition_reduction",Inputs!$A$2:$A$121,0)) | C51: =INDEX(Inputs!$L$2:$L$121,MATCH("attrition_reduction",Inputs!$A$2:$A$121,0)) | D51: =INDEX(Inputs!$M$2:$M$121,MATCH("attrition_reduction",Inputs!$A$2:$A$121,0)) | E51: From Inputs, key attrition_reduction
A52: Input: value_per_customer_year | B52: =INDEX(Inputs!$K$2:$K$121,MATCH("value_per_customer_year",Inputs!$A$2:$A$121,0)) | C52: =INDEX(Inputs!$L$2:$L$121,MATCH("value_per_customer_year",Inputs!$A$2:$A$121,0)) | D52: =INDEX(Inputs!$M$2:$M$121,MATCH("value_per_customer_year",Inputs!$A$2:$A$121,0)) | E52: From Inputs, key value_per_customer_year
A53: Input: contact_avoided | B53: =INDEX(Inputs!$K$2:$K$121,MATCH("contact_avoided",Inputs!$A$2:$A$121,0)) | C53: =INDEX(Inputs!$L$2:$L$121,MATCH("contact_avoided",Inputs!$A$2:$A$121,0)) | D53: =INDEX(Inputs!$M$2:$M$121,MATCH("contact_avoided",Inputs!$A$2:$A$121,0)) | E53: From Inputs, key contact_avoided
A54: Input: cost_per_call | B54: =INDEX(Inputs!$K$2:$K$121,MATCH("cost_per_call",Inputs!$A$2:$A$121,0)) | C54: =INDEX(Inputs!$L$2:$L$121,MATCH("cost_per_call",Inputs!$A$2:$A$121,0)) | D54: =INDEX(Inputs!$M$2:$M$121,MATCH("cost_per_call",Inputs!$A$2:$A$121,0)) | E54: From Inputs, key cost_per_call
A55: Input: share_behaviour_change | B55: =INDEX(Inputs!$K$2:$K$121,MATCH("share_behaviour_change",Inputs!$A$2:$A$121,0)) | C55: =INDEX(Inputs!$L$2:$L$121,MATCH("share_behaviour_change",Inputs!$A$2:$A$121,0)) | D55: =INDEX(Inputs!$M$2:$M$121,MATCH("share_behaviour_change",Inputs!$A$2:$A$121,0)) | E55: From Inputs, key share_behaviour_change
A56: Input: days_cover_gained | B56: =INDEX(Inputs!$K$2:$K$121,MATCH("days_cover_gained",Inputs!$A$2:$A$121,0)) | C56: =INDEX(Inputs!$L$2:$L$121,MATCH("days_cover_gained",Inputs!$A$2:$A$121,0)) | D56: =INDEX(Inputs!$M$2:$M$121,MATCH("days_cover_gained",Inputs!$A$2:$A$121,0)) | E56: From Inputs, key days_cover_gained
A57: Input: shortfalls_avoided | B57: =INDEX(Inputs!$K$2:$K$121,MATCH("shortfalls_avoided",Inputs!$A$2:$A$121,0)) | C57: =INDEX(Inputs!$L$2:$L$121,MATCH("shortfalls_avoided",Inputs!$A$2:$A$121,0)) | D57: =INDEX(Inputs!$M$2:$M$121,MATCH("shortfalls_avoided",Inputs!$A$2:$A$121,0)) | E57: From Inputs, key shortfalls_avoided
A58: Input: fees_avoided | B58: =INDEX(Inputs!$K$2:$K$121,MATCH("fees_avoided",Inputs!$A$2:$A$121,0)) | C58: =INDEX(Inputs!$L$2:$L$121,MATCH("fees_avoided",Inputs!$A$2:$A$121,0)) | D58: =INDEX(Inputs!$M$2:$M$121,MATCH("fees_avoided",Inputs!$A$2:$A$121,0)) | E58: From Inputs, key fees_avoided
A59: Input: confidence_change | B59: =INDEX(Inputs!$K$2:$K$121,MATCH("confidence_change",Inputs!$A$2:$A$121,0)) | C59: =INDEX(Inputs!$L$2:$L$121,MATCH("confidence_change",Inputs!$A$2:$A$121,0)) | D59: =INDEX(Inputs!$M$2:$M$121,MATCH("confidence_change",Inputs!$A$2:$A$121,0)) | E59: From Inputs, key confidence_change
A60: Input: churn_embedded | B60: =INDEX(Inputs!$K$2:$K$121,MATCH("churn_embedded",Inputs!$A$2:$A$121,0)) | C60: =INDEX(Inputs!$L$2:$L$121,MATCH("churn_embedded",Inputs!$A$2:$A$121,0)) | D60: =INDEX(Inputs!$M$2:$M$121,MATCH("churn_embedded",Inputs!$A$2:$A$121,0)) | E60: From Inputs, key churn_embedded
A61: Input: churn_consumer | B61: =INDEX(Inputs!$K$2:$K$121,MATCH("churn_consumer",Inputs!$A$2:$A$121,0)) | C61: =INDEX(Inputs!$L$2:$L$121,MATCH("churn_consumer",Inputs!$A$2:$A$121,0)) | D61: =INDEX(Inputs!$M$2:$M$121,MATCH("churn_consumer",Inputs!$A$2:$A$121,0)) | E61: From Inputs, key churn_consumer
A62: Input: cac_embedded | B62: =INDEX(Inputs!$K$2:$K$121,MATCH("cac_embedded",Inputs!$A$2:$A$121,0)) | C62: =INDEX(Inputs!$L$2:$L$121,MATCH("cac_embedded",Inputs!$A$2:$A$121,0)) | D62: =INDEX(Inputs!$M$2:$M$121,MATCH("cac_embedded",Inputs!$A$2:$A$121,0)) | E62: From Inputs, key cac_embedded
A63: Input: cac_consumer | B63: =INDEX(Inputs!$K$2:$K$121,MATCH("cac_consumer",Inputs!$A$2:$A$121,0)) | C63: =INDEX(Inputs!$L$2:$L$121,MATCH("cac_consumer",Inputs!$A$2:$A$121,0)) | D63: =INDEX(Inputs!$M$2:$M$121,MATCH("cac_consumer",Inputs!$A$2:$A$121,0)) | E63: From Inputs, key cac_consumer
A64: Input: cac_sponsor | B64: =INDEX(Inputs!$K$2:$K$121,MATCH("cac_sponsor",Inputs!$A$2:$A$121,0)) | C64: =INDEX(Inputs!$L$2:$L$121,MATCH("cac_sponsor",Inputs!$A$2:$A$121,0)) | D64: =INDEX(Inputs!$M$2:$M$121,MATCH("cac_sponsor",Inputs!$A$2:$A$121,0)) | E64: From Inputs, key cac_sponsor
A65: Input: pilot_months | B65: =INDEX(Inputs!$K$2:$K$121,MATCH("pilot_months",Inputs!$A$2:$A$121,0)) | C65: =INDEX(Inputs!$L$2:$L$121,MATCH("pilot_months",Inputs!$A$2:$A$121,0)) | D65: =INDEX(Inputs!$M$2:$M$121,MATCH("pilot_months",Inputs!$A$2:$A$121,0)) | E65: From Inputs, key pilot_months
A66: Input: pilot_mau_share | B66: =INDEX(Inputs!$K$2:$K$121,MATCH("pilot_mau_share",Inputs!$A$2:$A$121,0)) | C66: =INDEX(Inputs!$L$2:$L$121,MATCH("pilot_mau_share",Inputs!$A$2:$A$121,0)) | D66: =INDEX(Inputs!$M$2:$M$121,MATCH("pilot_mau_share",Inputs!$A$2:$A$121,0)) | E66: From Inputs, key pilot_mau_share
A67: Input: ramp_months | B67: =INDEX(Inputs!$K$2:$K$121,MATCH("ramp_months",Inputs!$A$2:$A$121,0)) | C67: =INDEX(Inputs!$L$2:$L$121,MATCH("ramp_months",Inputs!$A$2:$A$121,0)) | D67: =INDEX(Inputs!$M$2:$M$121,MATCH("ramp_months",Inputs!$A$2:$A$121,0)) | E67: From Inputs, key ramp_months
A68: 1. Market sizing and funnel (people)
A69: Adults 15+ with an account | B69: =B5*B6 | C69: =C5*C6 | D69: =D5*D6 | E69: Context: population 15+ x account ownership (Findex 2025)
A70: Informal plus private household workers (sourced floor) | B70: =B8+B9 | C70: =C8+C9 | D70: =D8+D9 | E70: Stats SA QLFS Q2 2026
A71: Total market: adults with irregular or informal income | B71: =B10 | C71: =C10 | D71: =D10 | E71: Assumption built up from the sourced floor
A72: Serviceable market: with an account and a smartphone | B72: =B71*B11 | C72: =C71*C11 | D72: =D71*D11 | E72: tam*sam_share_banked_smartphone
A73: Partner bank digital customers with irregular income | B73: =B12*B13 | C73: =C12*C13 | D73: =D12*D13 | E73: partner_base*share_partner_irregular
A74: Shown the feature by the bank | B74: =B73*B14 | C74: =C73*C14 | D74: =D73*D14 | E74: partner_irregular*share_eligible_offered
A75: Activated | B75: =B74*B15 | C75: =C74*C15 | D75: =D74*D15 | E75: offered*offered_to_activated
A76: Steady-state monthly active users (one partner bank) | B76: =B75*B16 | C76: =C75*C16 | D76: =D75*D16 | E76: activated*activated_to_mau
A77: Share of the serviceable market reached | B77: =IFERROR(B76/B72,0) | C77: =IFERROR(C76/C72,0) | D77: =IFERROR(D76/D72,0) | E77: IFERROR(mau/sam,0)
A78: 2. Unit costs per active user per month (ZAR)
A79: LLM cost per generated message | B79: =(B24*B22+B25*B23)/1000000*B18 | C79: =(C24*C22+C25*C23)/1000000*C18 | D79: =(D24*D22+D25*D23)/1000000*D18 | E79: (tokens_in_msg*llm_in_price+tokens_out_msg*llm_out_price)/1000000*usd_zar
A80: LLM cost per MAU | B80: =B79*B26 | C80: =C79*C26 | D80: =D79*D26 | E80: llm_per_msg*msgs_per_month
A81: In-app push messages per MAU (embedded channel) | B81: =B30*B26 | C81: =C30*C26 | D81: =D30*D26 | E81: push_cost*msgs_per_month
A82: WhatsApp messages per MAU (standalone channel) | B82: =(B27*B18+B28)*B26 | C82: =(C27*C18+C28)*C26 | D82: =(D27*D18+D28)*D26 | E82: (wa_utility*usd_zar+wa_bsp_fee)*msgs_per_month
A83: SMS messages per MAU (sponsor channel, feature phones) | B83: =B29*B26 | C83: =C29*C26 | D83: =D29*D26 | E83: sms_price*msgs_per_month
A84: Variable cost per MAU, embedded in a bank app | B84: =B20+B21+B80+B81+B31 | C84: =C20+C21+C80+C81+C31 | D84: =D20+D21+D80+D81+D31 | E84: hosting_per_mau+forecast_compute+llm_per_mau+push_per_mau+support_per_mau
A85: Variable cost per MAU, standalone consumer app | B85: =B20+B21+B80+B82+B31 | C85: =C20+C21+C80+C82+C31 | D85: =D20+D21+D80+D82+D31 | E85: hosting_per_mau+forecast_compute+llm_per_mau+wa_per_mau+support_per_mau
A86: Variable cost per MAU, sponsored programme | B86: =B20+B21+B80+B83+B31 | C86: =C20+C21+C80+C83+C31 | D86: =D20+D21+D80+D83+D31 | E86: hosting_per_mau+forecast_compute+llm_per_mau+sms_per_mau+support_per_mau
A87: Fixed cost per month (team, compliance, database base fee) | B87: =B33+B32+B34*B18 | C87: =C33+C32+C34*C18 | D87: =D33+D32+D34*D18 | E87: team_fixed+compliance_fixed+db_base*usd_zar
A88: 3. Value to a bank per active user per year (ZAR, all assumptions)
A89: Unpaid debit orders avoided per MAU per year | B89: =B44*B45*B46 | C89: =C44*C45*C46 | D89: =D44*D45*D46 | E89: share_users_unpaid*unpaid_events_per_user*unpaid_reduction
A90: Operational cost saved on unpaid items | B90: =B89*B47 | C90: =C89*C47 | D90: =D89*D47 | E90: unpaid_avoided*bank_cost_per_unpaid
A91: Fee income the bank no longer earns (negative) | B91: =-B89*B48 | C91: =-C89*C48 | D91: =-D89*D48 | E91: Standard Bank pay-as-you-transact unpaid fee used as the proxy
A92: Margin on higher balances held | B92: =B49*B50 | C92: =C49*C50 | D92: =D49*D50 | E92: deposit_uplift*nim_on_deposits
A93: Value of lower attrition | B93: =B51*B52 | C93: =C51*C52 | D93: =D51*D52 | E93: attrition_reduction*value_per_customer_year
A94: Contact centre calls avoided | B94: =B53*B54 | C94: =C53*C54 | D94: =D53*D54 | E94: contact_avoided*cost_per_call
A95: Net value to the bank per MAU per year | B95: =B90+B91+B92+B93+B94 | C95: =C90+C91+C92+C93+C94 | D95: =D90+D91+D92+D93+D94 | E95: bv_ops+bv_fees_lost+bv_deposits+bv_retention+bv_contact
A96: Net value to the bank per year at steady-state MAU | B96: =B95*B76 | C96: =C95*C76 | D96: =D95*D76 | E96: bank_value_year*mau
A97: Licence the bank pays per MAU per year (model a) | B97: =B37*12 | C97: =C37*12 | D97: =D37*12 | E97: lic_fee_per_mau*12
A98: Bank value per rand of licence fee | B98: =IFERROR(B95/B97,0) | C98: =IFERROR(C95/C97,0) | D98: =IFERROR(D95/D97,0) | E98: IFERROR(bank_value_year/bank_cost_year,0)
A99: 4. Revenue per active user per month, by business model (ZAR)
A100: (a) Bank licence per MAU | B100: =B37 | C100: =C37 | D100: =D37 | E100: lic_fee_per_mau
A101: (b) Revenue share on measured bank benefit | B101: =B40*B95/12 | C101: =C40*C95/12 | D101: =D40*D95/12 | E101: outcome_share*bank_value_year/12
...

Sheet Projection
A1: Projection: 24 months, model (a) bank licence, one partner bank
A2: Pilot fee spread over the pilot months, then the larger of licence revenue and the platform floor. Costs are fixed plus embedded variable cost per MAU.
A4: Conservative
A5: Month | B5: 1 | C5: 2 | D5: 3 | E5: 4 | F5: 5 | G5: 6 | H5: 7 | I5: 8 | J5: 9 | K5: 10 | L5: 11 | M5: 12 | N5: 13 | O5: 14 | P5: 15 | Q5: 16 | R5: 17 | S5: 18 | T5: 19 | U5: 20 | V5: 21 | W5: 22 | X5: 23 | Y5: 24
A6: MAU | B6: =IF(B$5<=Model!$B$65,Model!$B$76*Model!$B$66*B$5/Model!$B$65,MIN(Model!$B$76,Model!$B$76*Model!$B$66+(Model!$B$76-Model!$B$76*Model!$B$66)*(B$5-Model!$B$65)/Model!$B$67)) | C6: =IF(C$5<=Model!$B$65,Model!$B$76*Model!$B$66*C$5/Model!$B$65,MIN(Model!$B$76,Model!$B$76*Model!$B$66+(Model!$B$76-Model!$B$76*Model!$B$66)*(C$5-Model!$B$65)/Model!$B$67)) | D6: =IF(D$5<=Model!$B$65,Model!$B$76*Model!$B$66*D$5/Model!$B$65,MIN(Model!$B$76,Model!$B$76*Model!$B$66+(Model!$B$76-Model!$B$76*Model!$B$66)*(D$5-Model!$B$65)/Model!$B$67)) | E6: =IF(E$5<=Model!$B$65,Model!$B$76*Model!$B$66*E$5/Model!$B$65,MIN(Model!$B$76,Model!$B$76*Model!$B$66+(Model!$B$76-Model!$B$76*Model!$B$66)*(E$5-Model!$B$65)/Model!$B$67)) | F6: =IF(F$5<=Model!$B$65,Model!$B$76*Model!$B$66*F$5/Model!$B$65,MIN(Model!$B$76,Model!$B$76*Model!$B$66+(Model!$B$76-Model!$B$76*Model!$B$66)*(F$5-Model!$B$65)/Model!$B$67)) | G6: =IF(G$5<=Model!$B$65,Model!$B$76*Model!$B$66*G$5/Model!$B$65,MIN(Model!$B$76,Model!$B$76*Model!$B$66+(Model!$B$76-Model!$B$76*Model!$B$66)*(G$5-Model!$B$65)/Model!$B$67)) | H6: =IF(H$5<=Model!$B$65,Model!$B$76*Model!$B$66*H$5/Model!$B$65,MIN(Model!$B$76,Model!$B$76*Model!$B$66+(Model!$B$76-Model!$B$76*Model!$B$66)*(H$5-Model!$B$65)/Model!$B$67)) | I6: =IF(I$5<=Model!$B$65,Model!$B$76*Model!$B$66*I$5/Model!$B$65,MIN(Model!$B$76,Model!$B$76*Model!$B$66+(Model!$B$76-Model!$B$76*Model!$B$66)*(I$5-Model!$B$65)/Model!$B$67)) | ... Y6: =IF(Y$5<=Model!$B$65,Model!$B$76*Model!$B$66*Y$5/Model!$B$65,MIN(Model!$B$76,Model!$B$76*Model!$B$66+(Model!$B$76-Model!$B$76*Model!$B$66)*(Y$5-Model!$B$65)/Model!$B$67))
A7: Revenue | B7: =IF(B$5<=Model!$B$65,Model!$B$38/Model!$B$65,MAX(Model!$B$37*B6,Model!$B$39/12)) | C7: =IF(C$5<=Model!$B$65,Model!$B$38/Model!$B$65,MAX(Model!$B$37*C6,Model!$B$39/12)) | D7: =IF(D$5<=Model!$B$65,Model!$B$38/Model!$B$65,MAX(Model!$B$37*D6,Model!$B$39/12)) | E7: =IF(E$5<=Model!$B$65,Model!$B$38/Model!$B$65,MAX(Model!$B$37*E6,Model!$B$39/12)) | F7: =IF(F$5<=Model!$B$65,Model!$B$38/Model!$B$65,MAX(Model!$B$37*F6,Model!$B$39/12)) | G7: =IF(G$5<=Model!$B$65,Model!$B$38/Model!$B$65,MAX(Model!$B$37*G6,Model!$B$39/12)) | H7: =IF(H$5<=Model!$B$65,Model!$B$38/Model!$B$65,MAX(Model!$B$37*H6,Model!$B$39/12)) | I7: =IF(I$5<=Model!$B$65,Model!$B$38/Model!$B$65,MAX(Model!$B$37*I6,Model!$B$39/12)) | ... Y7: =IF(Y$5<=Model!$B$65,Model!$B$38/Model!$B$65,MAX(Model!$B$37*Y6,Model!$B$39/12))
A8: Fixed cost | B8: =Model!$B$87 | C8: =Model!$B$87 | D8: =Model!$B$87 | E8: =Model!$B$87 | F8: =Model!$B$87 | G8: =Model!$B$87 | H8: =Model!$B$87 | I8: =Model!$B$87 | ... Y8: =Model!$B$87
A9: Variable cost | B9: =Model!$B$84*B6 | C9: =Model!$B$84*C6 | D9: =Model!$B$84*D6 | E9: =Model!$B$84*E6 | F9: =Model!$B$84*F6 | G9: =Model!$B$84*G6 | H9: =Model!$B$84*H6 | I9: =Model!$B$84*I6 | ... Y9: =Model!$B$84*Y6
A10: Net cash flow | B10: =B7-B8-B9 | C10: =C7-C8-C9 | D10: =D7-D8-D9 | E10: =E7-E8-E9 | F10: =F7-F8-F9 | G10: =G7-G8-G9 | H10: =H7-H8-H9 | I10: =I7-I8-I9 | ... Y10: =Y7-Y8-Y9
A11: Cumulative cash | B11: =B10+INDEX(Inputs!$L$2:$L$121,MATCH("opening_cash",Inputs!$A$2:$A$121,0)) | C11: =C10+B11 | D11: =D10+C11 | E11: =E10+D11 | F11: =F10+E11 | G11: =G10+F11 | H11: =H10+G11 | I11: =I10+H11 | J11: =J10+I11 | ... Y11: =Y10+X11
A12: Profitable month flag | B12: =IF(B10>0,1,0) | C12: =IF(C10>0,1,0) | D12: =IF(D10>0,1,0) | E12: =IF(E10>0,1,0) | F12: =IF(F10>0,1,0) | G12: =IF(G10>0,1,0) | H12: =IF(H10>0,1,0) | I12: =IF(I10>0,1,0) | ... Y12: =IF(Y10>0,1,0)
A14: First profitable month | B14: =IFERROR(MATCH(1,B12:Y12,0),"beyond 24")
A15: Peak funding need (ZAR) | B15: =MAX(0,-MIN(B11:Y11))
A16: Cumulative cash at month 24 (ZAR) | B16: =Y11
A17: Revenue in year 2 (ZAR) | B17: =SUM(N7:Y7)
A20: Base
A21: Month | B21: 1 | C21: 2 | D21: 3 | E21: 4 | F21: 5 | G21: 6 | H21: 7 | I21: 8 | J21: 9 | K21: 10 | L21: 11 | M21: 12 | N21: 13 | O21: 14 | P21: 15 | Q21: 16 | R21: 17 | S21: 18 | T21: 19 | U21: 20 | V21: 21 | W21: 22 | X21: 23 | Y21: 24
A22: MAU | B22: =IF(B$21<=Model!$C$65,Model!$C$76*Model!$C$66*B$21/Model!$C$65,MIN(Model!$C$76,Model!$C$76*Model!$C$66+(Model!$C$76-Model!$C$76*Model!$C$66)*(B$21-Model!$C$65)/Model!$C$67)) | C22: =IF(C$21<=Model!$C$65,Model!$C$76*Model!$C$66*C$21/Model!$C$65,MIN(Model!$C$76,Model!$C$76*Model!$C$66+(Model!$C$76-Model!$C$76*Model!$C$66)*(C$21-Model!$C$65)/Model!$C$67)) | D22: =IF(D$21<=Model!$C$65,Model!$C$76*Model!$C$66*D$21/Model!$C$65,MIN(Model!$C$76,Model!$C$76*Model!$C$66+(Model!$C$76-Model!$C$76*Model!$C$66)*(D$21-Model!$C$65)/Model!$C$67)) | E22: =IF(E$21<=Model!$C$65,Model!$C$76*Model!$C$66*E$21/Model!$C$65,MIN(Model!$C$76,Model!$C$76*Model!$C$66+(Model!$C$76-Model!$C$76*Model!$C$66)*(E$21-Model!$C$65)/Model!$C$67)) | F22: =IF(F$21<=Model!$C$65,Model!$C$76*Model!$C$66*F$21/Model!$C$65,MIN(Model!$C$76,Model!$C$76*Model!$C$66+(Model!$C$76-Model!$C$76*Model!$C$66)*(F$21-Model!$C$65)/Model!$C$67)) | G22: =IF(G$21<=Model!$C$65,Model!$C$76*Model!$C$66*G$21/Model!$C$65,MIN(Model!$C$76,Model!$C$76*Model!$C$66+(Model!$C$76-Model!$C$76*Model!$C$66)*(G$21-Model!$C$65)/Model!$C$67)) | H22: =IF(H$21<=Model!$C$65,Model!$C$76*Model!$C$66*H$21/Model!$C$65,MIN(Model!$C$76,Model!$C$76*Model!$C$66+(Model!$C$76-Model!$C$76*Model!$C$66)*(H$21-Model!$C$65)/Model!$C$67)) | I22: =IF(I$21<=Model!$C$65,Model!$C$76*Model!$C$66*I$21/Model!$C$65,MIN(Model!$C$76,Model!$C$76*Model!$C$66+(Model!$C$76-Model!$C$76*Model!$C$66)*(I$21-Model!$C$65)/Model!$C$67)) | ... Y22: =IF(Y$21<=Model!$C$65,Model!$C$76*Model!$C$66*Y$21/Model!$C$65,MIN(Model!$C$76,Model!$C$76*Model!$C$66+(Model!$C$76-Model!$C$76*Model!$C$66)*(Y$21-Model!$C$65)/Model!$C$67))
A23: Revenue | B23: =IF(B$21<=Model!$C$65,Model!$C$38/Model!$C$65,MAX(Model!$C$37*B22,Model!$C$39/12)) | C23: =IF(C$21<=Model!$C$65,Model!$C$38/Model!$C$65,MAX(Model!$C$37*C22,Model!$C$39/12)) | D23: =IF(D$21<=Model!$C$65,Model!$C$38/Model!$C$65,MAX(Model!$C$37*D22,Model!$C$39/12)) | E23: =IF(E$21<=Model!$C$65,Model!$C$38/Model!$C$65,MAX(Model!$C$37*E22,Model!$C$39/12)) | F23: =IF(F$21<=Model!$C$65,Model!$C$38/Model!$C$65,MAX(Model!$C$37*F22,Model!$C$39/12)) | G23: =IF(G$21<=Model!$C$65,Model!$C$38/Model!$C$65,MAX(Model!$C$37*G22,Model!$C$39/12)) | H23: =IF(H$21<=Model!$C$65,Model!$C$38/Model!$C$65,MAX(Model!$C$37*H22,Model!$C$39/12)) | I23: =IF(I$21<=Model!$C$65,Model!$C$38/Model!$C$65,MAX(Model!$C$37*I22,Model!$C$39/12)) | ... Y23: =IF(Y$21<=Model!$C$65,Model!$C$38/Model!$C$65,MAX(Model!$C$37*Y22,Model!$C$39/12))
A24: Fixed cost | B24: =Model!$C$87 | C24: =Model!$C$87 | D24: =Model!$C$87 | E24: =Model!$C$87 | F24: =Model!$C$87 | G24: =Model!$C$87 | H24: =Model!$C$87 | I24: =Model!$C$87 | ... Y24: =Model!$C$87
A25: Variable cost | B25: =Model!$C$84*B22 | C25: =Model!$C$84*C22 | D25: =Model!$C$84*D22 | E25: =Model!$C$84*E22 | F25: =Model!$C$84*F22 | G25: =Model!$C$84*G22 | H25: =Model!$C$84*H22 | I25: =Model!$C$84*I22 | ... Y25: =Model!$C$84*Y22
A26: Net cash flow | B26: =B23-B24-B25 | C26: =C23-C24-C25 | D26: =D23-D24-D25 | E26: =E23-E24-E25 | F26: =F23-F24-F25 | G26: =G23-G24-G25 | H26: =H23-H24-H25 | I26: =I23-I24-I25 | ... Y26: =Y23-Y24-Y25
A27: Cumulative cash | B27: =B26+INDEX(Inputs!$L$2:$L$121,MATCH("opening_cash",Inputs!$A$2:$A$121,0)) | C27: =C26+B27 | D27: =D26+C27 | E27: =E26+D27 | F27: =F26+E27 | G27: =G26+F27 | H27: =H26+G27 | I27: =I26+H27 | J27: =J26+I27 | ... Y27: =Y26+X27
A28: Profitable month flag | B28: =IF(B26>0,1,0) | C28: =IF(C26>0,1,0) | D28: =IF(D26>0,1,0) | E28: =IF(E26>0,1,0) | F28: =IF(F26>0,1,0) | G28: =IF(G26>0,1,0) | H28: =IF(H26>0,1,0) | I28: =IF(I26>0,1,0) | ... Y28: =IF(Y26>0,1,0)
A30: First profitable month | B30: =IFERROR(MATCH(1,B28:Y28,0),"beyond 24")
A31: Peak funding need (ZAR) | B31: =MAX(0,-MIN(B27:Y27))
A32: Cumulative cash at month 24 (ZAR) | B32: =Y27
A33: Revenue in year 2 (ZAR) | B33: =SUM(N23:Y23)
A36: Ambitious
A37: Month | B37: 1 | C37: 2 | D37: 3 | E37: 4 | F37: 5 | G37: 6 | H37: 7 | I37: 8 | J37: 9 | K37: 10 | L37: 11 | M37: 12 | N37: 13 | O37: 14 | P37: 15 | Q37: 16 | R37: 17 | S37: 18 | T37: 19 | U37: 20 | V37: 21 | W37: 22 | X37: 23 | Y37: 24
A38: MAU | B38: =IF(B$37<=Model!$D$65,Model!$D$76*Model!$D$66*B$37/Model!$D$65,MIN(Model!$D$76,Model!$D$76*Model!$D$66+(Model!$D$76-Model!$D$76*Model!$D$66)*(B$37-Model!$D$65)/Model!$D$67)) | C38: =IF(C$37<=Model!$D$65,Model!$D$76*Model!$D$66*C$37/Model!$D$65,MIN(Model!$D$76,Model!$D$76*Model!$D$66+(Model!$D$76-Model!$D$76*Model!$D$66)*(C$37-Model!$D$65)/Model!$D$67)) | D38: =IF(D$37<=Model!$D$65,Model!$D$76*Model!$D$66*D$37/Model!$D$65,MIN(Model!$D$76,Model!$D$76*Model!$D$66+(Model!$D$76-Model!$D$76*Model!$D$66)*(D$37-Model!$D$65)/Model!$D$67)) | E38: =IF(E$37<=Model!$D$65,Model!$D$76*Model!$D$66*E$37/Model!$D$65,MIN(Model!$D$76,Model!$D$76*Model!$D$66+(Model!$D$76-Model!$D$76*Model!$D$66)*(E$37-Model!$D$65)/Model!$D$67)) | F38: =IF(F$37<=Model!$D$65,Model!$D$76*Model!$D$66*F$37/Model!$D$65,MIN(Model!$D$76,Model!$D$76*Model!$D$66+(Model!$D$76-Model!$D$76*Model!$D$66)*(F$37-Model!$D$65)/Model!$D$67)) | G38: =IF(G$37<=Model!$D$65,Model!$D$76*Model!$D$66*G$37/Model!$D$65,MIN(Model!$D$76,Model!$D$76*Model!$D$66+(Model!$D$76-Model!$D$76*Model!$D$66)*(G$37-Model!$D$65)/Model!$D$67)) | H38: =IF(H$37<=Model!$D$65,Model!$D$76*Model!$D$66*H$37/Model!$D$65,MIN(Model!$D$76,Model!$D$76*Model!$D$66+(Model!$D$76-Model!$D$76*Model!$D$66)*(H$37-Model!$D$65)/Model!$D$67)) | I38: =IF(I$37<=Model!$D$65,Model!$D$76*Model!$D$66*I$37/Model!$D$65,MIN(Model!$D$76,Model!$D$76*Model!$D$66+(Model!$D$76-Model!$D$76*Model!$D$66)*(I$37-Model!$D$65)/Model!$D$67)) | ... Y38: =IF(Y$37<=Model!$D$65,Model!$D$76*Model!$D$66*Y$37/Model!$D$65,MIN(Model!$D$76,Model!$D$76*Model!$D$66+(Model!$D$76-Model!$D$76*Model!$D$66)*(Y$37-Model!$D$65)/Model!$D$67))
A39: Revenue | B39: =IF(B$37<=Model!$D$65,Model!$D$38/Model!$D$65,MAX(Model!$D$37*B38,Model!$D$39/12)) | C39: =IF(C$37<=Model!$D$65,Model!$D$38/Model!$D$65,MAX(Model!$D$37*C38,Model!$D$39/12)) | D39: =IF(D$37<=Model!$D$65,Model!$D$38/Model!$D$65,MAX(Model!$D$37*D38,Model!$D$39/12)) | E39: =IF(E$37<=Model!$D$65,Model!$D$38/Model!$D$65,MAX(Model!$D$37*E38,Model!$D$39/12)) | F39: =IF(F$37<=Model!$D$65,Model!$D$38/Model!$D$65,MAX(Model!$D$37*F38,Model!$D$39/12)) | G39: =IF(G$37<=Model!$D$65,Model!$D$38/Model!$D$65,MAX(Model!$D$37*G38,Model!$D$39/12)) | H39: =IF(H$37<=Model!$D$65,Model!$D$38/Model!$D$65,MAX(Model!$D$37*H38,Model!$D$39/12)) | I39: =IF(I$37<=Model!$D$65,Model!$D$38/Model!$D$65,MAX(Model!$D$37*I38,Model!$D$39/12)) | ... Y39: =IF(Y$37<=Model!$D$65,Model!$D$38/Model!$D$65,MAX(Model!$D$37*Y38,Model!$D$39/12))
A40: Fixed cost | B40: =Model!$D$87 | C40: =Model!$D$87 | D40: =Model!$D$87 | E40: =Model!$D$87 | F40: =Model!$D$87 | G40: =Model!$D$87 | H40: =Model!$D$87 | I40: =Model!$D$87 | ... Y40: =Model!$D$87
A41: Variable cost | B41: =Model!$D$84*B38 | C41: =Model!$D$84*C38 | D41: =Model!$D$84*D38 | E41: =Model!$D$84*E38 | F41: =Model!$D$84*F38 | G41: =Model!$D$84*G38 | H41: =Model!$D$84*H38 | I41: =Model!$D$84*I38 | ... Y41: =Model!$D$84*Y38
A42: Net cash flow | B42: =B39-B40-B41 | C42: =C39-C40-C41 | D42: =D39-D40-D41 | E42: =E39-E40-E41 | F42: =F39-F40-F41 | G42: =G39-G40-G41 | H42: =H39-H40-H41 | I42: =I39-I40-I41 | ... Y42: =Y39-Y40-Y41
A43: Cumulative cash | B43: =B42+INDEX(Inputs!$L$2:$L$121,MATCH("opening_cash",Inputs!$A$2:$A$121,0)) | C43: =C42+B43 | D43: =D42+C43 | E43: =E42+D43 | F43: =F42+E43 | G43: =G42+F43 | H43: =H42+G43 | I43: =I42+H43 | J43: =J42+I43 | ... Y43: =Y42+X43
A44: Profitable month flag | B44: =IF(B42>0,1,0) | C44: =IF(C42>0,1,0) | D44: =IF(D42>0,1,0) | E44: =IF(E42>0,1,0) | F44: =IF(F42>0,1,0) | G44: =IF(G42>0,1,0) | H44: =IF(H42>0,1,0) | I44: =IF(I42>0,1,0) | ... Y44: =IF(Y42>0,1,0)
A46: First profitable month | B46: =IFERROR(MATCH(1,B44:Y44,0),"beyond 24")
A47: Peak funding need (ZAR) | B47: =MAX(0,-MIN(B43:Y43))
A48: Cumulative cash at month 24 (ZAR) | B48: =Y43
A49: Revenue in year 2 (ZAR) | B49: =SUM(N39:Y39)

Sheet Sensitivity
A1: Sensitivity (Base scenario, one input at a time)
A3: Break-even MAU for model (a) | B3: Input at low | C3: Input at high | D3: MAU at low | E3: MAU at high | F3: Swing | G3: Base MAU
A4: Base case | G4: =IFERROR(IF(INDEX(Inputs!$E$2:$E$121,MATCH("lic_fee_per_mau",Inputs!$A$2:$A$121,0))-(INDEX(Inputs!$E$2:$E$121,MATCH("hosting_per_mau",Inputs!$A$2:$A$121,0))+INDEX(Inputs!$E$2:$E$121,MATCH("forecast_compute",Inputs!$A$2:$A$121,0))+(INDEX(Inputs!$E$2:$E$121,MATCH("tokens_in_msg",Inputs!$A$2:$A$121,0))*INDEX(Inputs!$E$2:$E$121,MATCH("llm_in_price",Inputs!$A$2:$A$121,0))+INDEX(Inputs!$E$2:$E$121,MATCH("tokens_out_msg",Inputs!$A$2:$A$121,0))*INDEX(Inputs!$E$2:$E$121,MATCH("llm_out_price",Inputs!$A$2:$A$121,0)))/1000000*INDEX(Inputs!$E$2:$E$121,MATCH("usd_zar",Inputs!$A$2:$A$121,0))*INDEX(Inputs!$E$2:$E$121,MATCH("msgs_per_month",Inputs!$A$2:$A$121,0))+INDEX(Inputs!$E$2:$E$121,MATCH("push_cost",Inputs!$A$2:$A$121,0))*INDEX(Inputs!$E$2:$E$121,MATCH("msgs_per_month",Inputs!$A$2:$A$121,0))+INDEX(Inputs!$E$2:$E$121,MATCH("support_per_mau",Inputs!$A$2:$A$121,0)))>0,(INDEX(Inputs!$E$2:$E$121,MATCH("team_fixed",Inputs!$A$2:$A$121,0))+INDEX(Inputs!$E$2:$E$121,MATCH("compliance_fixed",Inputs!$A$2:$A$121,0))+INDEX(Inputs!$E$2:$E$121,MATCH("db_base",Inputs!$A$2:$A$121,0))*INDEX(Inputs!$E$2:$E$121,MATCH("usd_zar",Inputs!$A$2:$A$121,0)))/(INDEX(Inputs!$E$2:$E$121,MATCH("lic_fee_per_mau",Inputs!$A$2:$A$121,0))-(INDEX(Inputs!$E$2:$E$121,MATCH("hosting_per_mau",Inputs!$A$2:$A$121,0))+INDEX(Inputs!$E$2:$E$121,MATCH("forecast_compute",Inputs!$A$2:$A$121,0))+(INDEX(Inputs!$E$2:$E$121,MATCH("tokens_in_msg",Inputs!$A$2:$A$121,0))*INDEX(Inputs!$E$2:$E$121,MATCH("llm_in_price",Inputs!$A$2:$A$121,0))+INDEX(Inputs!$E$2:$E$121,MATCH("tokens_out_msg",Inputs!$A$2:$A$121,0))*INDEX(Inputs!$E$2:$E$121,MATCH("llm_out_price",Inputs!$A$2:$A$121,0)))/1000000*INDEX(Inputs!$E$2:$E$121,MATCH("usd_zar",Inputs!$A$2:$A$121,0))*INDEX(Inputs!$E$2:$E$121,MATCH("msgs_per_month",Inputs!$A$2:$A$121,0))+INDEX(Inputs!$E$2:$E$121,MATCH("push_cost",Inputs!$A$2:$A$121,0))*INDEX(Inputs!$E$2:$E$121,MATCH("msgs_per_month",Inputs!$A$2:$A$121,0))+INDEX(Inputs!$E$2:$E$121,MATCH("support_per_mau",Inputs!$A$2:$A$121,0)))),""),"")
A5: lic_fee_per_mau | B5: =INDEX(Inputs!$D$2:$D$121,MATCH("lic_fee_per_mau",Inputs!$A$2:$A$121,0)) | C5: =INDEX(Inputs!$F$2:$F$121,MATCH("lic_fee_per_mau",Inputs!$A$2:$A$121,0)) | D5: =IFERROR(IF(INDEX(Inputs!$D$2:$D$121,MATCH("lic_fee_per_mau",Inputs!$A$2:$A$121,0))-(INDEX(Inputs!$E$2:$E$121,MATCH("hosting_per_mau",Inputs!$A$2:$A$121,0))+INDEX(Inputs!$E$2:$E$121,MATCH("forecast_compute",Inputs!$A$2:$A$121,0))+(INDEX(Inputs!$E$2:$E$121,MATCH("tokens_in_msg",Inputs!$A$2:$A$121,0))*INDEX(Inputs!$E$2:$E$121,MATCH("llm_in_price",Inputs!$A$2:$A$121,0))+INDEX(Inputs!$E$2:$E$121,MATCH("tokens_out_msg",Inputs!$A$2:$A$121,0))*INDEX(Inputs!$E$2:$E$121,MATCH("llm_out_price",Inputs!$A$2:$A$121,0)))/1000000*INDEX(Inputs!$E$2:$E$121,MATCH("usd_zar",Inputs!$A$2:$A$121,0))*INDEX(Inputs!$E$2:$E$121,MATCH("msgs_per_month",Inputs!$A$2:$A$121,0))+INDEX(Inputs!$E$2:$E$121,MATCH("push_cost",Inputs!$A$2:$A$121,0))*INDEX(Inputs!$E$2:$E$121,MATCH("msgs_per_month",Inputs!$A$2:$A$121,0))+INDEX(Inputs!$E$2:$E$121,MATCH("support_per_mau",Inputs!$A$2:$A$121,0)))>0,(INDEX(Inputs!$E$2:$E$121,MATCH("team_fixed",Inputs!$A$2:$A$121,0))+INDEX(Inputs!$E$2:$E$121,MATCH("compliance_fixed",Inputs!$A$2:$A$121,0))+INDEX(Inputs!$E$2:$E$121,MATCH("db_base",Inputs!$A$2:$A$121,0))*INDEX(Inputs!$E$2:$E$121,MATCH("usd_zar",Inputs!$A$2:$A$121,0)))/(INDEX(Inputs!$D$2:$D$121,MATCH("lic_fee_per_mau",Inputs!$A$2:$A$121,0))-(INDEX(Inputs!$E$2:$E$121,MATCH("hosting_per_mau",Inputs!$A$2:$A$121,0))+INDEX(Inputs!$E$2:$E$121,MATCH("forecast_compute",Inputs!$A$2:$A$121,0))+(INDEX(Inputs!$E$2:$E$121,MATCH("tokens_in_msg",Inputs!$A$2:$A$121,0))*INDEX(Inputs!$E$2:$E$121,MATCH("llm_in_price",Inputs!$A$2:$A$121,0))+INDEX(Inputs!$E$2:$E$121,MATCH("tokens_out_msg",Inputs!$A$2:$A$121,0))*INDEX(Inputs!$E$2:$E$121,MATCH("llm_out_price",Inputs!$A$2:$A$121,0)))/1000000*INDEX(Inputs!$E$2:$E$121,MATCH("usd_zar",Inputs!$A$2:$A$121,0))*INDEX(Inputs!$E$2:$E$121,MATCH("msgs_per_month",Inputs!$A$2:$A$121,0))+INDEX(Inputs!$E$2:$E$121,MATCH("push_cost",Inputs!$A$2:$A$121,0))*INDEX(Inputs!$E$2:$E$121,MATCH("msgs_per_month",Inputs!$A$2:$A$121,0))+INDEX(Inputs!$E$2:$E$121,MATCH("support_per_mau",Inputs!$A$2:$A$121,0)))),""),"") | E5: =IFERROR(IF(INDEX(Inputs!$F$2:$F$121,MATCH("lic_fee_per_mau",Inputs!$A$2:$A$121,0))-(INDEX(Inputs!$E$2:$E$121,MATCH("hosting_per_mau",Inputs!$A$2:$A$121,0))+INDEX(Inputs!$E$2:$E$121,MATCH("forecast_compute",Inputs!$A$2:$A$121,0))+(INDEX(Inputs!$E$2:$E$121,MATCH("tokens_in_msg",Inputs!$A$2:$A$121,0))*INDEX(Inputs!$E$2:$E$121,MATCH("llm_in_price",Inputs!$A$2:$A$121,0))+INDEX(Inputs!$E$2:$E$121,MATCH("tokens_out_msg",Inputs!$A$2:$A$121,0))*INDEX(Inputs!$E$2:$E$121,MATCH("llm_out_price",Inputs!$A$2:$A$121,0)))/1000000*INDEX(Inputs!$E$2:$E$121,MATCH("usd_zar",Inputs!$A$2:$A$121,0))*INDEX(Inputs!$E$2:$E$121,MATCH("msgs_per_month",Inputs!$A$2:$A$121,0))+INDEX(Inputs!$E$2:$E$121,MATCH("push_cost",Inputs!$A$2:$A$121,0))*INDEX(Inputs!$E$2:$E$121,MATCH("msgs_per_month",Inputs!$A$2:$A$121,0))+INDEX(Inputs!$E$2:$E$121,MATCH("support_per_mau",Inputs!$A$2:$A$121,0)))>0,(INDEX(Inputs!$E$2:$E$121,MATCH("team_fixed",Inputs!$A$2:$A$121,0))+INDEX(Inputs!$E$2:$E$121,MATCH("compliance_fixed",Inputs!$A$2:$A$121,0))+INDEX(Inputs!$E$2:$E$121,MATCH("db_base",Inputs!$A$2:$A$121,0))*INDEX(Inputs!$E$2:$E$121,MATCH("usd_zar",Inputs!$A$2:$A$121,0)))/(INDEX(Inputs!$F$2:$F$121,MATCH("lic_fee_per_mau",Inputs!$A$2:$A$121,0))-(INDEX(Inputs!$E$2:$E$121,MATCH("hosting_per_mau",Inputs!$A$2:$A$121,0))+INDEX(Inputs!$E$2:$E$121,MATCH("forecast_compute",Inputs!$A$2:$A$121,0))+(INDEX(Inputs!$E$2:$E$121,MATCH("tokens_in_msg",Inputs!$A$2:$A$121,0))*INDEX(Inputs!$E$2:$E$121,MATCH("llm_in_price",Inputs!$A$2:$A$121,0))+INDEX(Inputs!$E$2:$E$121,MATCH("tokens_out_msg",Inputs!$A$2:$A$121,0))*INDEX(Inputs!$E$2:$E$121,MATCH("llm_out_price",Inputs!$A$2:$A$121,0)))/1000000*INDEX(Inputs!$E$2:$E$121,MATCH("usd_zar",Inputs!$A$2:$A$121,0))*INDEX(Inputs!$E$2:$E$121,MATCH("msgs_per_month",Inputs!$A$2:$A$121,0))+INDEX(Inputs!$E$2:$E$121,MATCH("push_cost",Inputs!$A$2:$A$121,0))*INDEX(Inputs!$E$2:$E$121,MATCH("msgs_per_month",Inputs!$A$2:$A$121,0))+INDEX(Inputs!$E$2:$E$121,MATCH("support_per_mau",Inputs!$A$2:$A$121,0)))),""),"") | F5: =IFERROR(ABS(E5-D5),"") | G5: =$G$4
A6: team_fixed | B6: =INDEX(Inputs!$D$2:$D$121,MATCH("team_fixed",Inputs!$A$2:$A$121,0)) | C6: =INDEX(Inputs!$F$2:$F$121,MATCH("team_fixed",Inputs!$A$2:$A$121,0)) | D6: =IFERROR(IF(INDEX(Inputs!$E$2:$E$121,MATCH("lic_fee_per_mau",Inputs!$A$2:$A$121,0))-(INDEX(Inputs!$E$2:$E$121,MATCH("hosting_per_mau",Inputs!$A$2:$A$121,0))+INDEX(Inputs!$E$2:$E$121,MATCH("forecast_compute",Inputs!$A$2:$A$121,0))+(INDEX(Inputs!$E$2:$E$121,MATCH("tokens_in_msg",Inputs!$A$2:$A$121,0))*INDEX(Inputs!$E$2:$E$121,MATCH("llm_in_price",Inputs!$A$2:$A$121,0))+INDEX(Inputs!$E$2:$E$121,MATCH("tokens_out_msg",Inputs!$A$2:$A$121,0))*INDEX(Inputs!$E$2:$E$121,MATCH("llm_out_price",Inputs!$A$2:$A$121,0)))/1000000*INDEX(Inputs!$E$2:$E$121,MATCH("usd_zar",Inputs!$A$2:$A$121,0))*INDEX(Inputs!$E$2:$E$121,MATCH("msgs_per_month",Inputs!$A$2:$A$121,0))+INDEX(Inputs!$E$2:$E$121,MATCH("push_cost",Inputs!$A$2:$A$121,0))*INDEX(Inputs!$E$2:$E$121,MATCH("msgs_per_month",Inputs!$A$2:$A$121,0))+INDEX(Inputs!$E$2:$E$121,MATCH("support_per_mau",Inputs!$A$2:$A$121,0)))>0,(INDEX(Inputs!$D$2:$D$121,MATCH("team_fixed",Inputs!$A$2:$A$121,0))+INDEX(Inputs!$E$2:$E$121,MATCH("compliance_fixed",Inputs!$A$2:$A$121,0))+INDEX(Inputs!$E$2:$E$121,MATCH("db_base",Inputs!$A$2:$A$121,0))*INDEX(Inputs!$E$2:$E$121,MATCH("usd_zar",Inputs!$A$2:$A$121,0)))/(INDEX(Inputs!$E$2:$E$121,MATCH("lic_fee_per_mau",Inputs!$A$2:$A$121,0))-(INDEX(Inputs!$E$2:$E$121,MATCH("hosting_per_mau",Inputs!$A$2:$A$121,0))+INDEX(Inputs!$E$2:$E$121,MATCH("forecast_compute",Inputs!$A$2:$A$121,0))+(INDEX(Inputs!$E$2:$E$121,MATCH("tokens_in_msg",Inputs!$A$2:$A$121,0))*INDEX(Inputs!$E$2:$E$121,MATCH("llm_in_price",Inputs!$A$2:$A$121,0))+INDEX(Inputs!$E$2:$E$121,MATCH("tokens_out_msg",Inputs!$A$2:$A$121,0))*INDEX(Inputs!$E$2:$E$121,MATCH("llm_out_price",Inputs!$A$2:$A$121,0)))/1000000*INDEX(Inputs!$E$2:$E$121,MATCH("usd_zar",Inputs!$A$2:$A$121,0))*INDEX(Inputs!$E$2:$E$121,MATCH("msgs_per_month",Inputs!$A$2:$A$121,0))+INDEX(Inputs!$E$2:$E$121,MATCH("push_cost",Inputs!$A$2:$A$121,0))*INDEX(Inputs!$E$2:$E$121,MATCH("msgs_per_month",Inputs!$A$2:$A$121,0))+INDEX(Inputs!$E$2:$E$121,MATCH("support_per_mau",Inputs!$A$2:$A$121,0)))),""),"") | E6: =IFERROR(IF(INDEX(Inputs!$E$2:$E$121,MATCH("lic_fee_per_mau",Inputs!$A$2:$A$121,0))-(INDEX(Inputs!$E$2:$E$121,MATCH("hosting_per_mau",Inputs!$A$2:$A$121,0))+INDEX(Inputs!$E$2:$E$121,MATCH("forecast_compute",Inputs!$A$2:$A$121,0))+(INDEX(Inputs!$E$2:$E$121,MATCH("tokens_in_msg",Inputs!$A$2:$A$121,0))*INDEX(Inputs!$E$2:$E$121,MATCH("llm_in_price",Inputs!$A$2:$A$121,0))+INDEX(Inputs!$E$2:$E$121,MATCH("tokens_out_msg",Inputs!$A$2:$A$121,0))*INDEX(Inputs!$E$2:$E$121,MATCH("llm_out_price",Inputs!$A$2:$A$121,0)))/1000000*INDEX(Inputs!$E$2:$E$121,MATCH("usd_zar",Inputs!$A$2:$A$121,0))*INDEX(Inputs!$E$2:$E$121,MATCH("msgs_per_month",Inputs!$A$2:$A$121,0))+INDEX(Inputs!$E$2:$E$121,MATCH("push_cost",Inputs!$A$2:$A$121,0))*INDEX(Inputs!$E$2:$E$121,MATCH("msgs_per_month",Inputs!$A$2:$A$121,0))+INDEX(Inputs!$E$2:$E$121,MATCH("support_per_mau",Inputs!$A$2:$A$121,0)))>0,(INDEX(Inputs!$F$2:$F$121,MATCH("team_fixed",Inputs!$A$2:$A$121,0))+INDEX(Inputs!$E$2:$E$121,MATCH("compliance_fixed",Inputs!$A$2:$A$121,0))+INDEX(Inputs!$E$2:$E$121,MATCH("db_base",Inputs!$A$2:$A$121,0))*INDEX(Inputs!$E$2:$E$121,MATCH("usd_zar",Inputs!$A$2:$A$121,0)))/(INDEX(Inputs!$E$2:$E$121,MATCH("lic_fee_per_mau",Inputs!$A$2:$A$121,0))-(INDEX(Inputs!$E$2:$E$121,MATCH("hosting_per_mau",Inputs!$A$2:$A$121,0))+INDEX(Inputs!$E$2:$E$121,MATCH("forecast_compute",Inputs!$A$2:$A$121,0))+(INDEX(Inputs!$E$2:$E$121,MATCH("tokens_in_msg",Inputs!$A$2:$A$121,0))*INDEX(Inputs!$E$2:$E$121,MATCH("llm_in_price",Inputs!$A$2:$A$121,0))+INDEX(Inputs!$E$2:$E$121,MATCH("tokens_out_msg",Inputs!$A$2:$A$121,0))*INDEX(Inputs!$E$2:$E$121,MATCH("llm_out_price",Inputs!$A$2:$A$121,0)))/1000000*INDEX(Inputs!$E$2:$E$121,MATCH("usd_zar",Inputs!$A$2:$A$121,0))*INDEX(Inputs!$E$2:$E$121,MATCH("msgs_per_month",Inputs!$A$2:$A$121,0))+INDEX(Inputs!$E$2:$E$121,MATCH("push_cost",Inputs!$A$2:$A$121,0))*INDEX(Inputs!$E$2:$E$121,MATCH("msgs_per_month",Inputs!$A$2:$A$121,0))+INDEX(Inputs!$E$2:$E$121,MATCH("support_per_mau",Inputs!$A$2:$A$121,0)))),""),"") | F6: =IFERROR(ABS(E6-D6),"") | G6: =$G$4
A7: compliance_fixed | B7: =INDEX(Inputs!$D$2:$D$121,MATCH("compliance_fixed",Inputs!$A$2:$A$121,0)) | C7: =INDEX(Inputs!$F$2:$F$121,MATCH("compliance_fixed",Inputs!$A$2:$A$121,0)) | D7: =IFERROR(IF(INDEX(Inputs!$E$2:$E$121,MATCH("lic_fee_per_mau",Inputs!$A$2:$A$121,0))-(INDEX(Inputs!$E$2:$E$121,MATCH("hosting_per_mau",Inputs!$A$2:$A$121,0))+INDEX(Inputs!$E$2:$E$121,MATCH("forecast_compute",Inputs!$A$2:$A$121,0))+(INDEX(Inputs!$E$2:$E$121,MATCH("tokens_in_msg",Inputs!$A$2:$A$121,0))*INDEX(Inputs!$E$2:$E$121,MATCH("llm_in_price",Inputs!$A$2:$A$121,0))+INDEX(Inputs!$E$2:$E$121,MATCH("tokens_out_msg",Inputs!$A$2:$A$121,0))*INDEX(Inputs!$E$2:$E$121,MATCH("llm_out_price",Inputs!$A$2:$A$121,0)))/1000000*INDEX(Inputs!$E$2:$E$121,MATCH("usd_zar",Inputs!$A$2:$A$121,0))*INDEX(Inputs!$E$2:$E$121,MATCH("msgs_per_month",Inputs!$A$2:$A$121,0))+INDEX(Inputs!$E$2:$E$121,MATCH("push_cost",Inputs!$A$2:$A$121,0))*INDEX(Inputs!$E$2:$E$121,MATCH("msgs_per_month",Inputs!$A$2:$A$121,0))+INDEX(Inputs!$E$2:$E$121,MATCH("support_per_mau",Inputs!$A$2:$A$121,0)))>0,(INDEX(Inputs!$E$2:$E$121,MATCH("team_fixed",Inputs!$A$2:$A$121,0))+INDEX(Inputs!$D$2:$D$121,MATCH("compliance_fixed",Inputs!$A$2:$A$121,0))+INDEX(Inputs!$E$2:$E$121,MATCH("db_base",Inputs!$A$2:$A$121,0))*INDEX(Inputs!$E$2:$E$121,MATCH("usd_zar",Inputs!$A$2:$A$121,0)))/(INDEX(Inputs!$E$2:$E$121,MATCH("lic_fee_per_mau",Inputs!$A$2:$A$121,0))-(INDEX(Inputs!$E$2:$E$121,MATCH("hosting_per_mau",Inputs!$A$2:$A$121,0))+INDEX(Inputs!$E$2:$E$121,MATCH("forecast_compute",Inputs!$A$2:$A$121,0))+(INDEX(Inputs!$E$2:$E$121,MATCH("tokens_in_msg",Inputs!$A$2:$A$121,0))*INDEX(Inputs!$E$2:$E$121,MATCH("llm_in_price",Inputs!$A$2:$A$121,0))+INDEX(Inputs!$E$2:$E$121,MATCH("tokens_out_msg",Inputs!$A$2:$A$121,0))*INDEX(Inputs!$E$2:$E$121,MATCH("llm_out_price",Inputs!$A$2:$A$121,0)))/1000000*INDEX(Inputs!$E$2:$E$121,MATCH("usd_zar",Inputs!$A$2:$A$121,0))*INDEX(Inputs!$E$2:$E$121,MATCH("msgs_per_month",Inputs!$A$2:$A$121,0))+INDEX(Inputs!$E$2:$E$121,MATCH("push_cost",Inputs!$A$2:$A$121,0))*INDEX(Inputs!$E$2:$E$121,MATCH("msgs_per_month",Inputs!$A$2:$A$121,0))+INDEX(Inputs!$E$2:$E$121,MATCH("support_per_mau",Inputs!$A$2:$A$121,0)))),""),"") | E7: =IFERROR(IF(INDEX(Inputs!$E$2:$E$121,MATCH("lic_fee_per_mau",Inputs!$A$2:$A$121,0))-(INDEX(Inputs!$E$2:$E$121,MATCH("hosting_per_mau",Inputs!$A$2:$A$121,0))+INDEX(Inputs!$E$2:$E$121,MATCH("forecast_compute",Inputs!$A$2:$A$121,0))+(INDEX(Inputs!$E$2:$E$121,MATCH("tokens_in_msg",Inputs!$A$2:$A$121,0))*INDEX(Inputs!$E$2:$E$121,MATCH("llm_in_price",Inputs!$A$2:$A$121,0))+INDEX(Inputs!$E$2:$E$121,MATCH("tokens_out_msg",Inputs!$A$2:$A$121,0))*INDEX(Inputs!$E$2:$E$121,MATCH("llm_out_price",Inputs!$A$2:$A$121,0)))/1000000*INDEX(Inputs!$E$2:$E$121,MATCH("usd_zar",Inputs!$A$2:$A$121,0))*INDEX(Inputs!$E$2:$E$121,MATCH("msgs_per_month",Inputs!$A$2:$A$121,0))+INDEX(Inputs!$E$2:$E$121,MATCH("push_cost",Inputs!$A$2:$A$121,0))*INDEX(Inputs!$E$2:$E$121,MATCH("msgs_per_month",Inputs!$A$2:$A$121,0))+INDEX(Inputs!$E$2:$E$121,MATCH("support_per_mau",Inputs!$A$2:$A$121,0)))>0,(INDEX(Inputs!$E$2:$E$121,MATCH("team_fixed",Inputs!$A$2:$A$121,0))+INDEX(Inputs!$F$2:$F$121,MATCH("compliance_fixed",Inputs!$A$2:$A$121,0))+INDEX(Inputs!$E$2:$E$121,MATCH("db_base",Inputs!$A$2:$A$121,0))*INDEX(Inputs!$E$2:$E$121,MATCH("usd_zar",Inputs!$A$2:$A$121,0)))/(INDEX(Inputs!$E$2:$E$121,MATCH("lic_fee_per_mau",Inputs!$A$2:$A$121,0))-(INDEX(Inputs!$E$2:$E$121,MATCH("hosting_per_mau",Inputs!$A$2:$A$121,0))+INDEX(Inputs!$E$2:$E$121,MATCH("forecast_compute",Inputs!$A$2:$A$121,0))+(INDEX(Inputs!$E$2:$E$121,MATCH("tokens_in_msg",Inputs!$A$2:$A$121,0))*INDEX(Inputs!$E$2:$E$121,MATCH("llm_in_price",Inputs!$A$2:$A$121,0))+INDEX(Inputs!$E$2:$E$121,MATCH("tokens_out_msg",Inputs!$A$2:$A$121,0))*INDEX(Inputs!$E$2:$E$121,MATCH("llm_out_price",Inputs!$A$2:$A$121,0)))/1000000*INDEX(Inputs!$E$2:$E$121,MATCH("usd_zar",Inputs!$A$2:$A$121,0))*INDEX(Inputs!$E$2:$E$121,MATCH("msgs_per_month",Inputs!$A$2:$A$121,0))+INDEX(Inputs!$E$2:$E$121,MATCH("push_cost",Inputs!$A$2:$A$121,0))*INDEX(Inputs!$E$2:$E$121,MATCH("msgs_per_month",Inputs!$A$2:$A$121,0))+INDEX(Inputs!$E$2:$E$121,MATCH("support_per_mau",Inputs!$A$2:$A$121,0)))),""),"") | F7: =IFERROR(ABS(E7-D7),"") | G7: =$G$4
A8: support_per_mau | B8: =INDEX(Inputs!$D$2:$D$121,MATCH("support_per_mau",Inputs!$A$2:$A$121,0)) | C8: =INDEX(Inputs!$F$2:$F$121,MATCH("support_per_mau",Inputs!$A$2:$A$121,0)) | D8: =IFERROR(IF(INDEX(Inputs!$E$2:$E$121,MATCH("lic_fee_per_mau",Inputs!$A$2:$A$121,0))-(INDEX(Inputs!$E$2:$E$121,MATCH("hosting_per_mau",Inputs!$A$2:$A$121,0))+INDEX(Inputs!$E$2:$E$121,MATCH("forecast_compute",Inputs!$A$2:$A$121,0))+(INDEX(Inputs!$E$2:$E$121,MATCH("tokens_in_msg",Inputs!$A$2:$A$121,0))*INDEX(Inputs!$E$2:$E$121,MATCH("llm_in_price",Inputs!$A$2:$A$121,0))+INDEX(Inputs!$E$2:$E$121,MATCH("tokens_out_msg",Inputs!$A$2:$A$121,0))*INDEX(Inputs!$E$2:$E$121,MATCH("llm_out_price",Inputs!$A$2:$A$121,0)))/1000000*INDEX(Inputs!$E$2:$E$121,MATCH("usd_zar",Inputs!$A$2:$A$121,0))*INDEX(Inputs!$E$2:$E$121,MATCH("msgs_per_month",Inputs!$A$2:$A$121,0))+INDEX(Inputs!$E$2:$E$121,MATCH("push_cost",Inputs!$A$2:$A$121,0))*INDEX(Inputs!$E$2:$E$121,MATCH("msgs_per_month",Inputs!$A$2:$A$121,0))+INDEX(Inputs!$D$2:$D$121,MATCH("support_per_mau",Inputs!$A$2:$A$121,0)))>0,(INDEX(Inputs!$E$2:$E$121,MATCH("team_fixed",Inputs!$A$2:$A$121,0))+INDEX(Inputs!$E$2:$E$121,MATCH("compliance_fixed",Inputs!$A$2:$A$121,0))+INDEX(Inputs!$E$2:$E$121,MATCH("db_base",Inputs!$A$2:$A$121,0))*INDEX(Inputs!$E$2:$E$121,MATCH("usd_zar",Inputs!$A$2:$A$121,0)))/(INDEX(Inputs!$E$2:$E$121,MATCH("lic_fee_per_mau",Inputs!$A$2:$A$121,0))-(INDEX(Inputs!$E$2:$E$121,MATCH("hosting_per_mau",Inputs!$A$2:$A$121,0))+INDEX(Inputs!$E$2:$E$121,MATCH("forecast_compute",Inputs!$A$2:$A$121,0))+(INDEX(Inputs!$E$2:$E$121,MATCH("tokens_in_msg",Inputs!$A$2:$A$121,0))*INDEX(Inputs!$E$2:$E$121,MATCH("llm_in_price",Inputs!$A$2:$A$121,0))+INDEX(Inputs!$E$2:$E$121,MATCH("tokens_out_msg",Inputs!$A$2:$A$121,0))*INDEX(Inputs!$E$2:$E$121,MATCH("llm_out_price",Inputs!$A$2:$A$121,0)))/1000000*INDEX(Inputs!$E$2:$E$121,MATCH("usd_zar",Inputs!$A$2:$A$121,0))*INDEX(Inputs!$E$2:$E$121,MATCH("msgs_per_month",Inputs!$A$2:$A$121,0))+INDEX(Inputs!$E$2:$E$121,MATCH("push_cost",Inputs!$A$2:$A$121,0))*INDEX(Inputs!$E$2:$E$121,MATCH("msgs_per_month",Inputs!$A$2:$A$121,0))+INDEX(Inputs!$D$2:$D$121,MATCH("support_per_mau",Inputs!$A$2:$A$121,0)))),""),"") | E8: =IFERROR(IF(INDEX(Inputs!$E$2:$E$121,MATCH("lic_fee_per_mau",Inputs!$A$2:$A$121,0))-(INDEX(Inputs!$E$2:$E$121,MATCH("hosting_per_mau",Inputs!$A$2:$A$121,0))+INDEX(Inputs!$E$2:$E$121,MATCH("forecast_compute",Inputs!$A$2:$A$121,0))+(INDEX(Inputs!$E$2:$E$121,MATCH("tokens_in_msg",Inputs!$A$2:$A$121,0))*INDEX(Inputs!$E$2:$E$121,MATCH("llm_in_price",Inputs!$A$2:$A$121,0))+INDEX(Inputs!$E$2:$E$121,MATCH("tokens_out_msg",Inputs!$A$2:$A$121,0))*INDEX(Inputs!$E$2:$E$121,MATCH("llm_out_price",Inputs!$A$2:$A$121,0)))/1000000*INDEX(Inputs!$E$2:$E$121,MATCH("usd_zar",Inputs!$A$2:$A$121,0))*INDEX(Inputs!$E$2:$E$121,MATCH("msgs_per_month",Inputs!$A$2:$A$121,0))+INDEX(Inputs!$E$2:$E$121,MATCH("push_cost",Inputs!$A$2:$A$121,0))*INDEX(Inputs!$E$2:$E$121,MATCH("msgs_per_month",Inputs!$A$2:$A$121,0))+INDEX(Inputs!$F$2:$F$121,MATCH("support_per_mau",Inputs!$A$2:$A$121,0)))>0,(INDEX(Inputs!$E$2:$E$121,MATCH("team_fixed",Inputs!$A$2:$A$121,0))+INDEX(Inputs!$E$2:$E$121,MATCH("compliance_fixed",Inputs!$A$2:$A$121,0))+INDEX(Inputs!$E$2:$E$121,MATCH("db_base",Inputs!$A$2:$A$121,0))*INDEX(Inputs!$E$2:$E$121,MATCH("usd_zar",Inputs!$A$2:$A$121,0)))/(INDEX(Inputs!$E$2:$E$121,MATCH("lic_fee_per_mau",Inputs!$A$2:$A$121,0))-(INDEX(Inputs!$E$2:$E$121,MATCH("hosting_per_mau",Inputs!$A$2:$A$121,0))+INDEX(Inputs!$E$2:$E$121,MATCH("forecast_compute",Inputs!$A$2:$A$121,0))+(INDEX(Inputs!$E$2:$E$121,MATCH("tokens_in_msg",Inputs!$A$2:$A$121,0))*INDEX(Inputs!$E$2:$E$121,MATCH("llm_in_price",Inputs!$A$2:$A$121,0))+INDEX(Inputs!$E$2:$E$121,MATCH("tokens_out_msg",Inputs!$A$2:$A$121,0))*INDEX(Inputs!$E$2:$E$121,MATCH("llm_out_price",Inputs!$A$2:$A$121,0)))/1000000*INDEX(Inputs!$E$2:$E$121,MATCH("usd_zar",Inputs!$A$2:$A$121,0))*INDEX(Inputs!$E$2:$E$121,MATCH("msgs_per_month",Inputs!$A$2:$A$121,0))+INDEX(Inputs!$E$2:$E$121,MATCH("push_cost",Inputs!$A$2:$A$121,0))*INDEX(Inputs!$E$2:$E$121,MATCH("msgs_per_month",Inputs!$A$2:$A$121,0))+INDEX(Inputs!$F$2:$F$121,MATCH("support_per_mau",Inputs!$A$2:$A$121,0)))),""),"") | F8: =IFERROR(ABS(E8-D8),"") | G8: =$G$4
A9: hosting_per_mau | B9: =INDEX(Inputs!$D$2:$D$121,MATCH("hosting_per_mau",Inputs!$A$2:$A$121,0)) | C9: =INDEX(Inputs!$F$2:$F$121,MATCH("hosting_per_mau",Inputs!$A$2:$A$121,0)) | D9: =IFERROR(IF(INDEX(Inputs!$E$2:$E$121,MATCH("lic_fee_per_mau",Inputs!$A$2:$A$121,0))-(INDEX(Inputs!$D$2:$D$121,MATCH("hosting_per_mau",Inputs!$A$2:$A$121,0))+INDEX(Inputs!$E$2:$E$121,MATCH("forecast_compute",Inputs!$A$2:$A$121,0))+(INDEX(Inputs!$E$2:$E$121,MATCH("tokens_in_msg",Inputs!$A$2:$A$121,0))*INDEX(Inputs!$E$2:$E$121,MATCH("llm_in_price",Inputs!$A$2:$A$121,0))+INDEX(Inputs!$E$2:$E$121,MATCH("tokens_out_msg",Inputs!$A$2:$A$121,0))*INDEX(Inputs!$E$2:$E$121,MATCH("llm_out_price",Inputs!$A$2:$A$121,0)))/1000000*INDEX(Inputs!$E$2:$E$121,MATCH("usd_zar",Inputs!$A$2:$A$121,0))*INDEX(Inputs!$E$2:$E$121,MATCH("msgs_per_month",Inputs!$A$2:$A$121,0))+INDEX(Inputs!$E$2:$E$121,MATCH("push_cost",Inputs!$A$2:$A$121,0))*INDEX(Inputs!$E$2:$E$121,MATCH("msgs_per_month",Inputs!$A$2:$A$121,0))+INDEX(Inputs!$E$2:$E$121,MATCH("support_per_mau",Inputs!$A$2:$A$121,0)))>0,(INDEX(Inputs!$E$2:$E$121,MATCH("team_fixed",Inputs!$A$2:$A$121,0))+INDEX(Inputs!$E$2:$E$121,MATCH("compliance_fixed",Inputs!$A$2:$A$121,0))+INDEX(Inputs!$E$2:$E$121,MATCH("db_base",Inputs!$A$2:$A$121,0))*INDEX(Inputs!$E$2:$E$121,MATCH("usd_zar",Inputs!$A$2:$A$121,0)))/(INDEX(Inputs!$E$2:$E$121,MATCH("lic_fee_per_mau",Inputs!$A$2:$A$121,0))-(INDEX(Inputs!$D$2:$D$121,MATCH("hosting_per_mau",Inputs!$A$2:$A$121,0))+INDEX(Inputs!$E$2:$E$121,MATCH("forecast_compute",Inputs!$A$2:$A$121,0))+(INDEX(Inputs!$E$2:$E$121,MATCH("tokens_in_msg",Inputs!$A$2:$A$121,0))*INDEX(Inputs!$E$2:$E$121,MATCH("llm_in_price",Inputs!$A$2:$A$121,0))+INDEX(Inputs!$E$2:$E$121,MATCH("tokens_out_msg",Inputs!$A$2:$A$121,0))*INDEX(Inputs!$E$2:$E$121,MATCH("llm_out_price",Inputs!$A$2:$A$121,0)))/1000000*INDEX(Inputs!$E$2:$E$121,MATCH("usd_zar",Inputs!$A$2:$A$121,0))*INDEX(Inputs!$E$2:$E$121,MATCH("msgs_per_month",Inputs!$A$2:$A$121,0))+INDEX(Inputs!$E$2:$E$121,MATCH("push_cost",Inputs!$A$2:$A$121,0))*INDEX(Inputs!$E$2:$E$121,MATCH("msgs_per_month",Inputs!$A$2:$A$121,0))+INDEX(Inputs!$E$2:$E$121,MATCH("support_per_mau",Inputs!$A$2:$A$121,0)))),""),"") | E9: =IFERROR(IF(INDEX(Inputs!$E$2:$E$121,MATCH("lic_fee_per_mau",Inputs!$A$2:$A$121,0))-(INDEX(Inputs!$F$2:$F$121,MATCH("hosting_per_mau",Inputs!$A$2:$A$121,0))+INDEX(Inputs!$E$2:$E$121,MATCH("forecast_compute",Inputs!$A$2:$A$121,0))+(INDEX(Inputs!$E$2:$E$121,MATCH("tokens_in_msg",Inputs!$A$2:$A$121,0))*INDEX(Inputs!$E$2:$E$121,MATCH("llm_in_price",Inputs!$A$2:$A$121,0))+INDEX(Inputs!$E$2:$E$121,MATCH("tokens_out_msg",Inputs!$A$2:$A$121,0))*INDEX(Inputs!$E$2:$E$121,MATCH("llm_out_price",Inputs!$A$2:$A$121,0)))/1000000*INDEX(Inputs!$E$2:$E$121,MATCH("usd_zar",Inputs!$A$2:$A$121,0))*INDEX(Inputs!$E$2:$E$121,MATCH("msgs_per_month",Inputs!$A$2:$A$121,0))+INDEX(Inputs!$E$2:$E$121,MATCH("push_cost",Inputs!$A$2:$A$121,0))*INDEX(Inputs!$E$2:$E$121,MATCH("msgs_per_month",Inputs!$A$2:$A$121,0))+INDEX(Inputs!$E$2:$E$121,MATCH("support_per_mau",Inputs!$A$2:$A$121,0)))>0,(INDEX(Inputs!$E$2:$E$121,MATCH("team_fixed",Inputs!$A$2:$A$121,0))+INDEX(Inputs!$E$2:$E$121,MATCH("compliance_fixed",Inputs!$A$2:$A$121,0))+INDEX(Inputs!$E$2:$E$121,MATCH("db_base",Inputs!$A$2:$A$121,0))*INDEX(Inputs!$E$2:$E$121,MATCH("usd_zar",Inputs!$A$2:$A$121,0)))/(INDEX(Inputs!$E$2:$E$121,MATCH("lic_fee_per_mau",Inputs!$A$2:$A$121,0))-(INDEX(Inputs!$F$2:$F$121,MATCH("hosting_per_mau",Inputs!$A$2:$A$121,0))+INDEX(Inputs!$E$2:$E$121,MATCH("forecast_compute",Inputs!$A$2:$A$121,0))+(INDEX(Inputs!$E$2:$E$121,MATCH("tokens_in_msg",Inputs!$A$2:$A$121,0))*INDEX(Inputs!$E$2:$E$121,MATCH("llm_in_price",Inputs!$A$2:$A$121,0))+INDEX(Inputs!$E$2:$E$121,MATCH("tokens_out_msg",Inputs!$A$2:$A$121,0))*INDEX(Inputs!$E$2:$E$121,MATCH("llm_out_price",Inputs!$A$2:$A$121,0)))/1000000*INDEX(Inputs!$E$2:$E$121,MATCH("usd_zar",Inputs!$A$2:$A$121,0))*INDEX(Inputs!$E$2:$E$121,MATCH("msgs_per_month",Inputs!$A$2:$A$121,0))+INDEX(Inputs!$E$2:$E$121,MATCH("push_cost",Inputs!$A$2:$A$121,0))*INDEX(Inputs!$E$2:$E$121,MATCH("msgs_per_month",Inputs!$A$2:$A$121,0))+INDEX(Inputs!$E$2:$E$121,MATCH("support_per_mau",Inputs!$A$2:$A$121,0)))),""),"") | F9: =IFERROR(ABS(E9-D9),"") | G9: =$G$4
A10: msgs_per_month | B10: =INDEX(Inputs!$D$2:$D$121,MATCH("msgs_per_month",Inputs!$A$2:$A$121,0)) | C10: =INDEX(Inputs!$F$2:$F$121,MATCH("msgs_per_month",Inputs!$A$2:$A$121,0)) | D10: =IFERROR(IF(INDEX(Inputs!$E$2:$E$121,MATCH("lic_fee_per_mau",Inputs!$A$2:$A$121,0))-(INDEX(Inputs!$E$2:$E$121,MATCH("hosting_per_mau",Inputs!$A$2:$A$121,0))+INDEX(Inputs!$E$2:$E$121,MATCH("forecast_compute",Inputs!$A$2:$A$121,0))+(INDEX(Inputs!$E$2:$E$121,MATCH("tokens_in_msg",Inputs!$A$2:$A$121,0))*INDEX(Inputs!$E$2:$E$121,MATCH("llm_in_price",Inputs!$A$2:$A$121,0))+INDEX(Inputs!$E$2:$E$121,MATCH("tokens_out_msg",Inputs!$A$2:$A$121,0))*INDEX(Inputs!$E$2:$E$121,MATCH("llm_out_price",Inputs!$A$2:$A$121,0)))/1000000*INDEX(Inputs!$E$2:$E$121,MATCH("usd_zar",Inputs!$A$2:$A$121,0))*INDEX(Inputs!$D$2:$D$121,MATCH("msgs_per_month",Inputs!$A$2:$A$121,0))+INDEX(Inputs!$E$2:$E$121,MATCH("push_cost",Inputs!$A$2:$A$121,0))*INDEX(Inputs!$D$2:$D$121,MATCH("msgs_per_month",Inputs!$A$2:$A$121,0))+INDEX(Inputs!$E$2:$E$121,MATCH("support_per_mau",Inputs!$A$2:$A$121,0)))>0,(INDEX(Inputs!$E$2:$E$121,MATCH("team_fixed",Inputs!$A$2:$A$121,0))+INDEX(Inputs!$E$2:$E$121,MATCH("compliance_fixed",Inputs!$A$2:$A$121,0))+INDEX(Inputs!$E$2:$E$121,MATCH("db_base",Inputs!$A$2:$A$121,0))*INDEX(Inputs!$E$2:$E$121,MATCH("usd_zar",Inputs!$A$2:$A$121,0)))/(INDEX(Inputs!$E$2:$E$121,MATCH("lic_fee_per_mau",Inputs!$A$2:$A$121,0))-(INDEX(Inputs!$E$2:$E$121,MATCH("hosting_per_mau",Inputs!$A$2:$A$121,0))+INDEX(Inputs!$E$2:$E$121,MATCH("forecast_compute",Inputs!$A$2:$A$121,0))+(INDEX(Inputs!$E$2:$E$121,MATCH("tokens_in_msg",Inputs!$A$2:$A$121,0))*INDEX(Inputs!$E$2:$E$121,MATCH("llm_in_price",Inputs!$A$2:$A$121,0))+INDEX(Inputs!$E$2:$E$121,MATCH("tokens_out_msg",Inputs!$A$2:$A$121,0))*INDEX(Inputs!$E$2:$E$121,MATCH("llm_out_price",Inputs!$A$2:$A$121,0)))/1000000*INDEX(Inputs!$E$2:$E$121,MATCH("usd_zar",Inputs!$A$2:$A$121,0))*INDEX(Inputs!$D$2:$D$121,MATCH("msgs_per_month",Inputs!$A$2:$A$121,0))+INDEX(Inputs!$E$2:$E$121,MATCH("push_cost",Inputs!$A$2:$A$121,0))*INDEX(Inputs!$D$2:$D$121,MATCH("msgs_per_month",Inputs!$A$2:$A$121,0))+INDEX(Inputs!$E$2:$E$121,MATCH("support_per_mau",Inputs!$A$2:$A$121,0)))),""),"") | E10: =IFERROR(IF(INDEX(Inputs!$E$2:$E$121,MATCH("lic_fee_per_mau",Inputs!$A$2:$A$121,0))-(INDEX(Inputs!$E$2:$E$121,MATCH("hosting_per_mau",Inputs!$A$2:$A$121,0))+INDEX(Inputs!$E$2:$E$121,MATCH("forecast_compute",Inputs!$A$2:$A$121,0))+(INDEX(Inputs!$E$2:$E$121,MATCH("tokens_in_msg",Inputs!$A$2:$A$121,0))*INDEX(Inputs!$E$2:$E$121,MATCH("llm_in_price",Inputs!$A$2:$A$121,0))+INDEX(Inputs!$E$2:$E$121,MATCH("tokens_out_msg",Inputs!$A$2:$A$121,0))*INDEX(Inputs!$E$2:$E$121,MATCH("llm_out_price",Inputs!$A$2:$A$121,0)))/1000000*INDEX(Inputs!$E$2:$E$121,MATCH("usd_zar",Inputs!$A$2:$A$121,0))*INDEX(Inputs!$F$2:$F$121,MATCH("msgs_per_month",Inputs!$A$2:$A$121,0))+INDEX(Inputs!$E$2:$E$121,MATCH("push_cost",Inputs!$A$2:$A$121,0))*INDEX(Inputs!$F$2:$F$121,MATCH("msgs_per_month",Inputs!$A$2:$A$121,0))+INDEX(Inputs!$E$2:$E$121,MATCH("support_per_mau",Inputs!$A$2:$A$121,0)))>0,(INDEX(Inputs!$E$2:$E$121,MATCH("team_fixed",Inputs!$A$2:$A$121,0))+INDEX(Inputs!$E$2:$E$121,MATCH("compliance_fixed",Inputs!$A$2:$A$121,0))+INDEX(Inputs!$E$2:$E$121,MATCH("db_base",Inputs!$A$2:$A$121,0))*INDEX(Inputs!$E$2:$E$121,MATCH("usd_zar",Inputs!$A$2:$A$121,0)))/(INDEX(Inputs!$E$2:$E$121,MATCH("lic_fee_per_mau",Inputs!$A$2:$A$121,0))-(INDEX(Inputs!$E$2:$E$121,MATCH("hosting_per_mau",Inputs!$A$2:$A$121,0))+INDEX(Inputs!$E$2:$E$121,MATCH("forecast_compute",Inputs!$A$2:$A$121,0))+(INDEX(Inputs!$E$2:$E$121,MATCH("tokens_in_msg",Inputs!$A$2:$A$121,0))*INDEX(Inputs!$E$2:$E$121,MATCH("llm_in_price",Inputs!$A$2:$A$121,0))+INDEX(Inputs!$E$2:$E$121,MATCH("tokens_out_msg",Inputs!$A$2:$A$121,0))*INDEX(Inputs!$E$2:$E$121,MATCH("llm_out_price",Inputs!$A$2:$A$121,0)))/1000000*INDEX(Inputs!$E$2:$E$121,MATCH("usd_zar",Inputs!$A$2:$A$121,0))*INDEX(Inputs!$F$2:$F$121,MATCH("msgs_per_month",Inputs!$A$2:$A$121,0))+INDEX(Inputs!$E$2:$E$121,MATCH("push_cost",Inputs!$A$2:$A$121,0))*INDEX(Inputs!$F$2:$F$121,MATCH("msgs_per_month",Inputs!$A$2:$A$121,0))+INDEX(Inputs!$E$2:$E$121,MATCH("support_per_mau",Inputs!$A$2:$A$121,0)))),""),"") | F10: =IFERROR(ABS(E10-D10),"") | G10: =$G$4
A11: tokens_out_msg | B11: =INDEX(Inputs!$D$2:$D$121,MATCH("tokens_out_msg",Inputs!$A$2:$A$121,0)) | C11: =INDEX(Inputs!$F$2:$F$121,MATCH("tokens_out_msg",Inputs!$A$2:$A$121,0)) | D11: =IFERROR(IF(INDEX(Inputs!$E$2:$E$121,MATCH("lic_fee_per_mau",Inputs!$A$2:$A$121,0))-(INDEX(Inputs!$E$2:$E$121,MATCH("hosting_per_mau",Inputs!$A$2:$A$121,0))+INDEX(Inputs!$E$2:$E$121,MATCH("forecast_compute",Inputs!$A$2:$A$121,0))+(INDEX(Inputs!$E$2:$E$121,MATCH("tokens_in_msg",Inputs!$A$2:$A$121,0))*INDEX(Inputs!$E$2:$E$121,MATCH("llm_in_price",Inputs!$A$2:$A$121,0))+INDEX(Inputs!$D$2:$D$121,MATCH("tokens_out_msg",Inputs!$A$2:$A$121,0))*INDEX(Inputs!$E$2:$E$121,MATCH("llm_out_price",Inputs!$A$2:$A$121,0)))/1000000*INDEX(Inputs!$E$2:$E$121,MATCH("usd_zar",Inputs!$A$2:$A$121,0))*INDEX(Inputs!$E$2:$E$121,MATCH("msgs_per_month",Inputs!$A$2:$A$121,0))+INDEX(Inputs!$E$2:$E$121,MATCH("push_cost",Inputs!$A$2:$A$121,0))*INDEX(Inputs!$E$2:$E$121,MATCH("msgs_per_month",Inputs!$A$2:$A$121,0))+INDEX(Inputs!$E$2:$E$121,MATCH("support_per_mau",Inputs!$A$2:$A$121,0)))>0,(INDEX(Inputs!$E$2:$E$121,MATCH("team_fixed",Inputs!$A$2:$A$121,0))+INDEX(Inputs!$E$2:$E$121,MATCH("compliance_fixed",Inputs!$A$2:$A$121,0))+INDEX(Inputs!$E$2:$E$121,MATCH("db_base",Inputs!$A$2:$A$121,0))*INDEX(Inputs!$E$2:$E$121,MATCH("usd_zar",Inputs!$A$2:$A$121,0)))/(INDEX(Inputs!$E$2:$E$121,MATCH("lic_fee_per_mau",Inputs!$A$2:$A$121,0))-(INDEX(Inputs!$E$2:$E$121,MATCH("hosting_per_mau",Inputs!$A$2:$A$121,0))+INDEX(Inputs!$E$2:$E$121,MATCH("forecast_compute",Inputs!$A$2:$A$121,0))+(INDEX(Inputs!$E$2:$E$121,MATCH("tokens_in_msg",Inputs!$A$2:$A$121,0))*INDEX(Inputs!$E$2:$E$121,MATCH("llm_in_price",Inputs!$A$2:$A$121,0))+INDEX(Inputs!$D$2:$D$121,MATCH("tokens_out_msg",Inputs!$A$2:$A$121,0))*INDEX(Inputs!$E$2:$E$121,MATCH("llm_out_price",Inputs!$A$2:$A$121,0)))/1000000*INDEX(Inputs!$E$2:$E$121,MATCH("usd_zar",Inputs!$A$2:$A$121,0))*INDEX(Inputs!$E$2:$E$121,MATCH("msgs_per_month",Inputs!$A$2:$A$121,0))+INDEX(Inputs!$E$2:$E$121,MATCH("push_cost",Inputs!$A$2:$A$121,0))*INDEX(Inputs!$E$2:$E$121,MATCH("msgs_per_month",Inputs!$A$2:$A$121,0))+INDEX(Inputs!$E$2:$E$121,MATCH("support_per_mau",Inputs!$A$2:$A$121,0)))),""),"") | E11: =IFERROR(IF(INDEX(Inputs!$E$2:$E$121,MATCH("lic_fee_per_mau",Inputs!$A$2:$A$121,0))-(INDEX(Inputs!$E$2:$E$121,MATCH("hosting_per_mau",Inputs!$A$2:$A$121,0))+INDEX(Inputs!$E$2:$E$121,MATCH("forecast_compute",Inputs!$A$2:$A$121,0))+(INDEX(Inputs!$E$2:$E$121,MATCH("tokens_in_msg",Inputs!$A$2:$A$121,0))*INDEX(Inputs!$E$2:$E$121,MATCH("llm_in_price",Inputs!$A$2:$A$121,0))+INDEX(Inputs!$F$2:$F$121,MATCH("tokens_out_msg",Inputs!$A$2:$A$121,0))*INDEX(Inputs!$E$2:$E$121,MATCH("llm_out_price",Inputs!$A$2:$A$121,0)))/1000000*INDEX(Inputs!$E$2:$E$121,MATCH("usd_zar",Inputs!$A$2:$A$121,0))*INDEX(Inputs!$E$2:$E$121,MATCH("msgs_per_month",Inputs!$A$2:$A$121,0))+INDEX(Inputs!$E$2:$E$121,MATCH("push_cost",Inputs!$A$2:$A$121,0))*INDEX(Inputs!$E$2:$E$121,MATCH("msgs_per_month",Inputs!$A$2:$A$121,0))+INDEX(Inputs!$E$2:$E$121,MATCH("support_per_mau",Inputs!$A$2:$A$121,0)))>0,(INDEX(Inputs!$E$2:$E$121,MATCH("team_fixed",Inputs!$A$2:$A$121,0))+INDEX(Inputs!$E$2:$E$121,MATCH("compliance_fixed",Inputs!$A$2:$A$121,0))+INDEX(Inputs!$E$2:$E$121,MATCH("db_base",Inputs!$A$2:$A$121,0))*INDEX(Inputs!$E$2:$E$121,MATCH("usd_zar",Inputs!$A$2:$A$121,0)))/(INDEX(Inputs!$E$2:$E$121,MATCH("lic_fee_per_mau",Inputs!$A$2:$A$121,0))-(INDEX(Inputs!$E$2:$E$121,MATCH("hosting_per_mau",Inputs!$A$2:$A$121,0))+INDEX(Inputs!$E$2:$E$121,MATCH("forecast_compute",Inputs!$A$2:$A$121,0))+(INDEX(Inputs!$E$2:$E$121,MATCH("tokens_in_msg",Inputs!$A$2:$A$121,0))*INDEX(Inputs!$E$2:$E$121,MATCH("llm_in_price",Inputs!$A$2:$A$121,0))+INDEX(Inputs!$F$2:$F$121,MATCH("tokens_out_msg",Inputs!$A$2:$A$121,0))*INDEX(Inputs!$E$2:$E$121,MATCH("llm_out_price",Inputs!$A$2:$A$121,0)))/1000000*INDEX(Inputs!$E$2:$E$121,MATCH("usd_zar",Inputs!$A$2:$A$121,0))*INDEX(Inputs!$E$2:$E$121,MATCH("msgs_per_month",Inputs!$A$2:$A$121,0))+INDEX(Inputs!$E$2:$E$121,MATCH("push_cost",Inputs!$A$2:$A$121,0))*INDEX(Inputs!$E$2:$E$121,MATCH("msgs_per_month",Inputs!$A$2:$A$121,0))+INDEX(Inputs!$E$2:$E$121,MATCH("support_per_mau",Inputs!$A$2:$A$121,0)))),""),"") | F11: =IFERROR(ABS(E11-D11),"") | G11: =$G$4
A12: llm_out_price | B12: =INDEX(Inputs!$D$2:$D$121,MATCH("llm_out_price",Inputs!$A$2:$A$121,0)) | C12: =INDEX(Inputs!$F$2:$F$121,MATCH("llm_out_price",Inputs!$A$2:$A$121,0)) | D12: =IFERROR(IF(INDEX(Inputs!$E$2:$E$121,MATCH("lic_fee_per_mau",Inputs!$A$2:$A$121,0))-(INDEX(Inputs!$E$2:$E$121,MATCH("hosting_per_mau",Inputs!$A$2:$A$121,0))+INDEX(Inputs!$E$2:$E$121,MATCH("forecast_compute",Inputs!$A$2:$A$121,0))+(INDEX(Inputs!$E$2:$E$121,MATCH("tokens_in_msg",Inputs!$A$2:$A$121,0))*INDEX(Inputs!$E$2:$E$121,MATCH("llm_in_price",Inputs!$A$2:$A$121,0))+INDEX(Inputs!$E$2:$E$121,MATCH("tokens_out_msg",Inputs!$A$2:$A$121,0))*INDEX(Inputs!$D$2:$D$121,MATCH("llm_out_price",Inputs!$A$2:$A$121,0)))/1000000*INDEX(Inputs!$E$2:$E$121,MATCH("usd_zar",Inputs!$A$2:$A$121,0))*INDEX(Inputs!$E$2:$E$121,MATCH("msgs_per_month",Inputs!$A$2:$A$121,0))+INDEX(Inputs!$E$2:$E$121,MATCH("push_cost",Inputs!$A$2:$A$121,0))*INDEX(Inputs!$E$2:$E$121,MATCH("msgs_per_month",Inputs!$A$2:$A$121,0))+INDEX(Inputs!$E$2:$E$121,MATCH("support_per_mau",Inputs!$A$2:$A$121,0)))>0,(INDEX(Inputs!$E$2:$E$121,MATCH("team_fixed",Inputs!$A$2:$A$121,0))+INDEX(Inputs!$E$2:$E$121,MATCH("compliance_fixed",Inputs!$A$2:$A$121,0))+INDEX(Inputs!$E$2:$E$121,MATCH("db_base",Inputs!$A$2:$A$121,0))*INDEX(Inputs!$E$2:$E$121,MATCH("usd_zar",Inputs!$A$2:$A$121,0)))/(INDEX(Inputs!$E$2:$E$121,MATCH("lic_fee_per_mau",Inputs!$A$2:$A$121,0))-(INDEX(Inputs!$E$2:$E$121,MATCH("hosting_per_mau",Inputs!$A$2:$A$121,0))+INDEX(Inputs!$E$2:$E$121,MATCH("forecast_compute",Inputs!$A$2:$A$121,0))+(INDEX(Inputs!$E$2:$E$121,MATCH("tokens_in_msg",Inputs!$A$2:$A$121,0))*INDEX(Inputs!$E$2:$E$121,MATCH("llm_in_price",Inputs!$A$2:$A$121,0))+INDEX(Inputs!$E$2:$E$121,MATCH("tokens_out_msg",Inputs!$A$2:$A$121,0))*INDEX(Inputs!$D$2:$D$121,MATCH("llm_out_price",Inputs!$A$2:$A$121,0)))/1000000*INDEX(Inputs!$E$2:$E$121,MATCH("usd_zar",Inputs!$A$2:$A$121,0))*INDEX(Inputs!$E$2:$E$121,MATCH("msgs_per_month",Inputs!$A$2:$A$121,0))+INDEX(Inputs!$E$2:$E$121,MATCH("push_cost",Inputs!$A$2:$A$121,0))*INDEX(Inputs!$E$2:$E$121,MATCH("msgs_per_month",Inputs!$A$2:$A$121,0))+INDEX(Inputs!$E$2:$E$121,MATCH("support_per_mau",Inputs!$A$2:$A$121,0)))),""),"") | E12: =IFERROR(IF(INDEX(Inputs!$E$2:$E$121,MATCH("lic_fee_per_mau",Inputs!$A$2:$A$121,0))-(INDEX(Inputs!$E$2:$E$121,MATCH("hosting_per_mau",Inputs!$A$2:$A$121,0))+INDEX(Inputs!$E$2:$E$121,MATCH("forecast_compute",Inputs!$A$2:$A$121,0))+(INDEX(Inputs!$E$2:$E$121,MATCH("tokens_in_msg",Inputs!$A$2:$A$121,0))*INDEX(Inputs!$E$2:$E$121,MATCH("llm_in_price",Inputs!$A$2:$A$121,0))+INDEX(Inputs!$E$2:$E$121,MATCH("tokens_out_msg",Inputs!$A$2:$A$121,0))*INDEX(Inputs!$F$2:$F$121,MATCH("llm_out_price",Inputs!$A$2:$A$121,0)))/1000000*INDEX(Inputs!$E$2:$E$121,MATCH("usd_zar",Inputs!$A$2:$A$121,0))*INDEX(Inputs!$E$2:$E$121,MATCH("msgs_per_month",Inputs!$A$2:$A$121,0))+INDEX(Inputs!$E$2:$E$121,MATCH("push_cost",Inputs!$A$2:$A$121,0))*INDEX(Inputs!$E$2:$E$121,MATCH("msgs_per_month",Inputs!$A$2:$A$121,0))+INDEX(Inputs!$E$2:$E$121,MATCH("support_per_mau",Inputs!$A$2:$A$121,0)))>0,(INDEX(Inputs!$E$2:$E$121,MATCH("team_fixed",Inputs!$A$2:$A$121,0))+INDEX(Inputs!$E$2:$E$121,MATCH("compliance_fixed",Inputs!$A$2:$A$121,0))+INDEX(Inputs!$E$2:$E$121,MATCH("db_base",Inputs!$A$2:$A$121,0))*INDEX(Inputs!$E$2:$E$121,MATCH("usd_zar",Inputs!$A$2:$A$121,0)))/(INDEX(Inputs!$E$2:$E$121,MATCH("lic_fee_per_mau",Inputs!$A$2:$A$121,0))-(INDEX(Inputs!$E$2:$E$121,MATCH("hosting_per_mau",Inputs!$A$2:$A$121,0))+INDEX(Inputs!$E$2:$E$121,MATCH("forecast_compute",Inputs!$A$2:$A$121,0))+(INDEX(Inputs!$E$2:$E$121,MATCH("tokens_in_msg",Inputs!$A$2:$A$121,0))*INDEX(Inputs!$E$2:$E$121,MATCH("llm_in_price",Inputs!$A$2:$A$121,0))+INDEX(Inputs!$E$2:$E$121,MATCH("tokens_out_msg",Inputs!$A$2:$A$121,0))*INDEX(Inputs!$F$2:$F$121,MATCH("llm_out_price",Inputs!$A$2:$A$121,0)))/1000000*INDEX(Inputs!$E$2:$E$121,MATCH("usd_zar",Inputs!$A$2:$A$121,0))*INDEX(Inputs!$E$2:$E$121,MATCH("msgs_per_month",Inputs!$A$2:$A$121,0))+INDEX(Inputs!$E$2:$E$121,MATCH("push_cost",Inputs!$A$2:$A$121,0))*INDEX(Inputs!$E$2:$E$121,MATCH("msgs_per_month",Inputs!$A$2:$A$121,0))+INDEX(Inputs!$E$2:$E$121,MATCH("support_per_mau",Inputs!$A$2:$A$121,0)))),""),"") | F12: =IFERROR(ABS(E12-D12),"") | G12: =$G$4
A13: usd_zar | B13: =INDEX(Inputs!$D$2:$D$121,MATCH("usd_zar",Inputs!$A$2:$A$121,0)) | C13: =INDEX(Inputs!$F$2:$F$121,MATCH("usd_zar",Inputs!$A$2:$A$121,0)) | D13: =IFERROR(IF(INDEX(Inputs!$E$2:$E$121,MATCH("lic_fee_per_mau",Inputs!$A$2:$A$121,0))-(INDEX(Inputs!$E$2:$E$121,MATCH("hosting_per_mau",Inputs!$A$2:$A$121,0))+INDEX(Inputs!$E$2:$E$121,MATCH("forecast_compute",Inputs!$A$2:$A$121,0))+(INDEX(Inputs!$E$2:$E$121,MATCH("tokens_in_msg",Inputs!$A$2:$A$121,0))*INDEX(Inputs!$E$2:$E$121,MATCH("llm_in_price",Inputs!$A$2:$A$121,0))+INDEX(Inputs!$E$2:$E$121,MATCH("tokens_out_msg",Inputs!$A$2:$A$121,0))*INDEX(Inputs!$E$2:$E$121,MATCH("llm_out_price",Inputs!$A$2:$A$121,0)))/1000000*INDEX(Inputs!$D$2:$D$121,MATCH("usd_zar",Inputs!$A$2:$A$121,0))*INDEX(Inputs!$E$2:$E$121,MATCH("msgs_per_month",Inputs!$A$2:$A$121,0))+INDEX(Inputs!$E$2:$E$121,MATCH("push_cost",Inputs!$A$2:$A$121,0))*INDEX(Inputs!$E$2:$E$121,MATCH("msgs_per_month",Inputs!$A$2:$A$121,0))+INDEX(Inputs!$E$2:$E$121,MATCH("support_per_mau",Inputs!$A$2:$A$121,0)))>0,(INDEX(Inputs!$E$2:$E$121,MATCH("team_fixed",Inputs!$A$2:$A$121,0))+INDEX(Inputs!$E$2:$E$121,MATCH("compliance_fixed",Inputs!$A$2:$A$121,0))+INDEX(Inputs!$E$2:$E$121,MATCH("db_base",Inputs!$A$2:$A$121,0))*INDEX(Inputs!$D$2:$D$121,MATCH("usd_zar",Inputs!$A$2:$A$121,0)))/(INDEX(Inputs!$E$2:$E$121,MATCH("lic_fee_per_mau",Inputs!$A$2:$A$121,0))-(INDEX(Inputs!$E$2:$E$121,MATCH("hosting_per_mau",Inputs!$A$2:$A$121,0))+INDEX(Inputs!$E$2:$E$121,MATCH("forecast_compute",Inputs!$A$2:$A$121,0))+(INDEX(Inputs!$E$2:$E$121,MATCH("tokens_in_msg",Inputs!$A$2:$A$121,0))*INDEX(Inputs!$E$2:$E$121,MATCH("llm_in_price",Inputs!$A$2:$A$121,0))+INDEX(Inputs!$E$2:$E$121,MATCH("tokens_out_msg",Inputs!$A$2:$A$121,0))*INDEX(Inputs!$E$2:$E$121,MATCH("llm_out_price",Inputs!$A$2:$A$121,0)))/1000000*INDEX(Inputs!$D$2:$D$121,MATCH("usd_zar",Inputs!$A$2:$A$121,0))*INDEX(Inputs!$E$2:$E$121,MATCH("msgs_per_month",Inputs!$A$2:$A$121,0))+INDEX(Inputs!$E$2:$E$121,MATCH("push_cost",Inputs!$A$2:$A$121,0))*INDEX(Inputs!$E$2:$E$121,MATCH("msgs_per_month",Inputs!$A$2:$A$121,0))+INDEX(Inputs!$E$2:$E$121,MATCH("support_per_mau",Inputs!$A$2:$A$121,0)))),""),"") | E13: =IFERROR(IF(INDEX(Inputs!$E$2:$E$121,MATCH("lic_fee_per_mau",Inputs!$A$2:$A$121,0))-(INDEX(Inputs!$E$2:$E$121,MATCH("hosting_per_mau",Inputs!$A$2:$A$121,0))+INDEX(Inputs!$E$2:$E$121,MATCH("forecast_compute",Inputs!$A$2:$A$121,0))+(INDEX(Inputs!$E$2:$E$121,MATCH("tokens_in_msg",Inputs!$A$2:$A$121,0))*INDEX(Inputs!$E$2:$E$121,MATCH("llm_in_price",Inputs!$A$2:$A$121,0))+INDEX(Inputs!$E$2:$E$121,MATCH("tokens_out_msg",Inputs!$A$2:$A$121,0))*INDEX(Inputs!$E$2:$E$121,MATCH("llm_out_price",Inputs!$A$2:$A$121,0)))/1000000*INDEX(Inputs!$F$2:$F$121,MATCH("usd_zar",Inputs!$A$2:$A$121,0))*INDEX(Inputs!$E$2:$E$121,MATCH("msgs_per_month",Inputs!$A$2:$A$121,0))+INDEX(Inputs!$E$2:$E$121,MATCH("push_cost",Inputs!$A$2:$A$121,0))*INDEX(Inputs!$E$2:$E$121,MATCH("msgs_per_month",Inputs!$A$2:$A$121,0))+INDEX(Inputs!$E$2:$E$121,MATCH("support_per_mau",Inputs!$A$2:$A$121,0)))>0,(INDEX(Inputs!$E$2:$E$121,MATCH("team_fixed",Inputs!$A$2:$A$121,0))+INDEX(Inputs!$E$2:$E$121,MATCH("compliance_fixed",Inputs!$A$2:$A$121,0))+INDEX(Inputs!$E$2:$E$121,MATCH("db_base",Inputs!$A$2:$A$121,0))*INDEX(Inputs!$F$2:$F$121,MATCH("usd_zar",Inputs!$A$2:$A$121,0)))/(INDEX(Inputs!$E$2:$E$121,MATCH("lic_fee_per_mau",Inputs!$A$2:$A$121,0))-(INDEX(Inputs!$E$2:$E$121,MATCH("hosting_per_mau",Inputs!$A$2:$A$121,0))+INDEX(Inputs!$E$2:$E$121,MATCH("forecast_compute",Inputs!$A$2:$A$121,0))+(INDEX(Inputs!$E$2:$E$121,MATCH("tokens_in_msg",Inputs!$A$2:$A$121,0))*INDEX(Inputs!$E$2:$E$121,MATCH("llm_in_price",Inputs!$A$2:$A$121,0))+INDEX(Inputs!$E$2:$E$121,MATCH("tokens_out_msg",Inputs!$A$2:$A$121,0))*INDEX(Inputs!$E$2:$E$121,MATCH("llm_out_price",Inputs!$A$2:$A$121,0)))/1000000*INDEX(Inputs!$F$2:$F$121,MATCH("usd_zar",Inputs!$A$2:$A$121,0))*INDEX(Inputs!$E$2:$E$121,MATCH("msgs_per_month",Inputs!$A$2:$A$121,0))+INDEX(Inputs!$E$2:$E$121,MATCH("push_cost",Inputs!$A$2:$A$121,0))*INDEX(Inputs!$E$2:$E$121,MATCH("msgs_per_month",Inputs!$A$2:$A$121,0))+INDEX(Inputs!$E$2:$E$121,MATCH("support_per_mau",Inputs!$A$2:$A$121,0)))),""),"") | F13: =IFERROR(ABS(E13-D13),"") | G13: =$G$4
A16: Bank value per MAU per year (ZAR) | B16: Input at low | C16: Input at high | D16: Value at low | E16: Value at high | F16: Swing | G16: Base value
A17: Base case | G17: =(INDEX(Inputs!$E$2:$E$121,MATCH("share_users_unpaid",Inputs!$A$2:$A$121,0))*INDEX(Inputs!$E$2:$E$121,MATCH("unpaid_events_per_user",Inputs!$A$2:$A$121,0))*INDEX(Inputs!$E$2:$E$121,MATCH("unpaid_reduction",Inputs!$A$2:$A$121,0)))*INDEX(Inputs!$E$2:$E$121,MATCH("bank_cost_per_unpaid",Inputs!$A$2:$A$121,0))-(INDEX(Inputs!$E$2:$E$121,MATCH("share_users_unpaid",Inputs!$A$2:$A$121,0))*INDEX(Inputs!$E$2:$E$121,MATCH("unpaid_events_per_user",Inputs!$A$2:$A$121,0))*INDEX(Inputs!$E$2:$E$121,MATCH("unpaid_reduction",Inputs!$A$2:$A$121,0)))*INDEX(Inputs!$E$2:$E$121,MATCH("sb_unpaid_payt",Inputs!$A$2:$A$121,0))+INDEX(Inputs!$E$2:$E$121,MATCH("deposit_uplift",Inputs!$A$2:$A$121,0))*INDEX(Inputs!$E$2:$E$121,MATCH("nim_on_deposits",Inputs!$A$2:$A$121,0))+INDEX(Inputs!$E$2:$E$121,MATCH("attrition_reduction",Inputs!$A$2:$A$121,0))*INDEX(Inputs!$E$2:$E$121,MATCH("value_per_customer_year",Inputs!$A$2:$A$121,0))+INDEX(Inputs!$E$2:$E$121,MATCH("contact_avoided",Inputs!$A$2:$A$121,0))*INDEX(Inputs!$E$2:$E$121,MATCH("cost_per_call",Inputs!$A$2:$A$121,0))
A18: share_users_unpaid | B18: =INDEX(Inputs!$D$2:$D$121,MATCH("share_users_unpaid",Inputs!$A$2:$A$121,0)) | C18: =INDEX(Inputs!$F$2:$F$121,MATCH("share_users_unpaid",Inputs!$A$2:$A$121,0)) | D18: =(INDEX(Inputs!$D$2:$D$121,MATCH("share_users_unpaid",Inputs!$A$2:$A$121,0))*INDEX(Inputs!$E$2:$E$121,MATCH("unpaid_events_per_user",Inputs!$A$2:$A$121,0))*INDEX(Inputs!$E$2:$E$121,MATCH("unpaid_reduction",Inputs!$A$2:$A$121,0)))*INDEX(Inputs!$E$2:$E$121,MATCH("bank_cost_per_unpaid",Inputs!$A$2:$A$121,0))-(INDEX(Inputs!$D$2:$D$121,MATCH("share_users_unpaid",Inputs!$A$2:$A$121,0))*INDEX(Inputs!$E$2:$E$121,MATCH("unpaid_events_per_user",Inputs!$A$2:$A$121,0))*INDEX(Inputs!$E$2:$E$121,MATCH("unpaid_reduction",Inputs!$A$2:$A$121,0)))*INDEX(Inputs!$E$2:$E$121,MATCH("sb_unpaid_payt",Inputs!$A$2:$A$121,0))+INDEX(Inputs!$E$2:$E$121,MATCH("deposit_uplift",Inputs!$A$2:$A$121,0))*INDEX(Inputs!$E$2:$E$121,MATCH("nim_on_deposits",Inputs!$A$2:$A$121,0))+INDEX(Inputs!$E$2:$E$121,MATCH("attrition_reduction",Inputs!$A$2:$A$121,0))*INDEX(Inputs!$E$2:$E$121,MATCH("value_per_customer_year",Inputs!$A$2:$A$121,0))+INDEX(Inputs!$E$2:$E$121,MATCH("contact_avoided",Inputs!$A$2:$A$121,0))*INDEX(Inputs!$E$2:$E$121,MATCH("cost_per_call",Inputs!$A$2:$A$121,0)) | E18: =(INDEX(Inputs!$F$2:$F$121,MATCH("share_users_unpaid",Inputs!$A$2:$A$121,0))*INDEX(Inputs!$E$2:$E$121,MATCH("unpaid_events_per_user",Inputs!$A$2:$A$121,0))*INDEX(Inputs!$E$2:$E$121,MATCH("unpaid_reduction",Inputs!$A$2:$A$121,0)))*INDEX(Inputs!$E$2:$E$121,MATCH("bank_cost_per_unpaid",Inputs!$A$2:$A$121,0))-(INDEX(Inputs!$F$2:$F$121,MATCH("share_users_unpaid",Inputs!$A$2:$A$121,0))*INDEX(Inputs!$E$2:$E$121,MATCH("unpaid_events_per_user",Inputs!$A$2:$A$121,0))*INDEX(Inputs!$E$2:$E$121,MATCH("unpaid_reduction",Inputs!$A$2:$A$121,0)))*INDEX(Inputs!$E$2:$E$121,MATCH("sb_unpaid_payt",Inputs!$A$2:$A$121,0))+INDEX(Inputs!$E$2:$E$121,MATCH("deposit_uplift",Inputs!$A$2:$A$121,0))*INDEX(Inputs!$E$2:$E$121,MATCH("nim_on_deposits",Inputs!$A$2:$A$121,0))+INDEX(Inputs!$E$2:$E$121,MATCH("attrition_reduction",Inputs!$A$2:$A$121,0))*INDEX(Inputs!$E$2:$E$121,MATCH("value_per_customer_year",Inputs!$A$2:$A$121,0))+INDEX(Inputs!$E$2:$E$121,MATCH("contact_avoided",Inputs!$A$2:$A$121,0))*INDEX(Inputs!$E$2:$E$121,MATCH("cost_per_call",Inputs!$A$2:$A$121,0)) | F18: =ABS(E18-D18) | G18: =$G$17
A19: unpaid_events_per_user | B19: =INDEX(Inputs!$D$2:$D$121,MATCH("unpaid_events_per_user",Inputs!$A$2:$A$121,0)) | C19: =INDEX(Inputs!$F$2:$F$121,MATCH("unpaid_events_per_user",Inputs!$A$2:$A$121,0)) | D19: =(INDEX(Inputs!$E$2:$E$121,MATCH("share_users_unpaid",Inputs!$A$2:$A$121,0))*INDEX(Inputs!$D$2:$D$121,MATCH("unpaid_events_per_user",Inputs!$A$2:$A$121,0))*INDEX(Inputs!$E$2:$E$121,MATCH("unpaid_reduction",Inputs!$A$2:$A$121,0)))*INDEX(Inputs!$E$2:$E$121,MATCH("bank_cost_per_unpaid",Inputs!$A$2:$A$121,0))-(INDEX(Inputs!$E$2:$E$121,MATCH("share_users_unpaid",Inputs!$A$2:$A$121,0))*INDEX(Inputs!$D$2:$D$121,MATCH("unpaid_events_per_user",Inputs!$A$2:$A$121,0))*INDEX(Inputs!$E$2:$E$121,MATCH("unpaid_reduction",Inputs!$A$2:$A$121,0)))*INDEX(Inputs!$E$2:$E$121,MATCH("sb_unpaid_payt",Inputs!$A$2:$A$121,0))+INDEX(Inputs!$E$2:$E$121,MATCH("deposit_uplift",Inputs!$A$2:$A$121,0))*INDEX(Inputs!$E$2:$E$121,MATCH("nim_on_deposits",Inputs!$A$2:$A$121,0))+INDEX(Inputs!$E$2:$E$121,MATCH("attrition_reduction",Inputs!$A$2:$A$121,0))*INDEX(Inputs!$E$2:$E$121,MATCH("value_per_customer_year",Inputs!$A$2:$A$121,0))+INDEX(Inputs!$E$2:$E$121,MATCH("contact_avoided",Inputs!$A$2:$A$121,0))*INDEX(Inputs!$E$2:$E$121,MATCH("cost_per_call",Inputs!$A$2:$A$121,0)) | E19: =(INDEX(Inputs!$E$2:$E$121,MATCH("share_users_unpaid",Inputs!$A$2:$A$121,0))*INDEX(Inputs!$F$2:$F$121,MATCH("unpaid_events_per_user",Inputs!$A$2:$A$121,0))*INDEX(Inputs!$E$2:$E$121,MATCH("unpaid_reduction",Inputs!$A$2:$A$121,0)))*INDEX(Inputs!$E$2:$E$121,MATCH("bank_cost_per_unpaid",Inputs!$A$2:$A$121,0))-(INDEX(Inputs!$E$2:$E$121,MATCH("share_users_unpaid",Inputs!$A$2:$A$121,0))*INDEX(Inputs!$F$2:$F$121,MATCH("unpaid_events_per_user",Inputs!$A$2:$A$121,0))*INDEX(Inputs!$E$2:$E$121,MATCH("unpaid_reduction",Inputs!$A$2:$A$121,0)))*INDEX(Inputs!$E$2:$E$121,MATCH("sb_unpaid_payt",Inputs!$A$2:$A$121,0))+INDEX(Inputs!$E$2:$E$121,MATCH("deposit_uplift",Inputs!$A$2:$A$121,0))*INDEX(Inputs!$E$2:$E$121,MATCH("nim_on_deposits",Inputs!$A$2:$A$121,0))+INDEX(Inputs!$E$2:$E$121,MATCH("attrition_reduction",Inputs!$A$2:$A$121,0))*INDEX(Inputs!$E$2:$E$121,MATCH("value_per_customer_year",Inputs!$A$2:$A$121,0))+INDEX(Inputs!$E$2:$E$121,MATCH("contact_avoided",Inputs!$A$2:$A$121,0))*INDEX(Inputs!$E$2:$E$121,MATCH("cost_per_call",Inputs!$A$2:$A$121,0)) | F19: =ABS(E19-D19) | G19: =$G$17
A20: unpaid_reduction | B20: =INDEX(Inputs!$D$2:$D$121,MATCH("unpaid_reduction",Inputs!$A$2:$A$121,0)) | C20: =INDEX(Inputs!$F$2:$F$121,MATCH("unpaid_reduction",Inputs!$A$2:$A$121,0)) | D20: =(INDEX(Inputs!$E$2:$E$121,MATCH("share_users_unpaid",Inputs!$A$2:$A$121,0))*INDEX(Inputs!$E$2:$E$121,MATCH("unpaid_events_per_user",Inputs!$A$2:$A$121,0))*INDEX(Inputs!$D$2:$D$121,MATCH("unpaid_reduction",Inputs!$A$2:$A$121,0)))*INDEX(Inputs!$E$2:$E$121,MATCH("bank_cost_per_unpaid",Inputs!$A$2:$A$121,0))-(INDEX(Inputs!$E$2:$E$121,MATCH("share_users_unpaid",Inputs!$A$2:$A$121,0))*INDEX(Inputs!$E$2:$E$121,MATCH("unpaid_events_per_user",Inputs!$A$2:$A$121,0))*INDEX(Inputs!$D$2:$D$121,MATCH("unpaid_reduction",Inputs!$A$2:$A$121,0)))*INDEX(Inputs!$E$2:$E$121,MATCH("sb_unpaid_payt",Inputs!$A$2:$A$121,0))+INDEX(Inputs!$E$2:$E$121,MATCH("deposit_uplift",Inputs!$A$2:$A$121,0))*INDEX(Inputs!$E$2:$E$121,MATCH("nim_on_deposits",Inputs!$A$2:$A$121,0))+INDEX(Inputs!$E$2:$E$121,MATCH("attrition_reduction",Inputs!$A$2:$A$121,0))*INDEX(Inputs!$E$2:$E$121,MATCH("value_per_customer_year",Inputs!$A$2:$A$121,0))+INDEX(Inputs!$E$2:$E$121,MATCH("contact_avoided",Inputs!$A$2:$A$121,0))*INDEX(Inputs!$E$2:$E$121,MATCH("cost_per_call",Inputs!$A$2:$A$121,0)) | E20: =(INDEX(Inputs!$E$2:$E$121,MATCH("share_users_unpaid",Inputs!$A$2:$A$121,0))*INDEX(Inputs!$E$2:$E$121,MATCH("unpaid_events_per_user",Inputs!$A$2:$A$121,0))*INDEX(Inputs!$F$2:$F$121,MATCH("unpaid_reduction",Inputs!$A$2:$A$121,0)))*INDEX(Inputs!$E$2:$E$121,MATCH("bank_cost_per_unpaid",Inputs!$A$2:$A$121,0))-(INDEX(Inputs!$E$2:$E$121,MATCH("share_users_unpaid",Inputs!$A$2:$A$121,0))*INDEX(Inputs!$E$2:$E$121,MATCH("unpaid_events_per_user",Inputs!$A$2:$A$121,0))*INDEX(Inputs!$F$2:$F$121,MATCH("unpaid_reduction",Inputs!$A$2:$A$121,0)))*INDEX(Inputs!$E$2:$E$121,MATCH("sb_unpaid_payt",Inputs!$A$2:$A$121,0))+INDEX(Inputs!$E$2:$E$121,MATCH("deposit_uplift",Inputs!$A$2:$A$121,0))*INDEX(Inputs!$E$2:$E$121,MATCH("nim_on_deposits",Inputs!$A$2:$A$121,0))+INDEX(Inputs!$E$2:$E$121,MATCH("attrition_reduction",Inputs!$A$2:$A$121,0))*INDEX(Inputs!$E$2:$E$121,MATCH("value_per_customer_year",Inputs!$A$2:$A$121,0))+INDEX(Inputs!$E$2:$E$121,MATCH("contact_avoided",Inputs!$A$2:$A$121,0))*INDEX(Inputs!$E$2:$E$121,MATCH("cost_per_call",Inputs!$A$2:$A$121,0)) | F20: =ABS(E20-D20) | G20: =$G$17
A21: bank_cost_per_unpaid | B21: =INDEX(Inputs!$D$2:$D$121,MATCH("bank_cost_per_unpaid",Inputs!$A$2:$A$121,0)) | C21: =INDEX(Inputs!$F$2:$F$121,MATCH("bank_cost_per_unpaid",Inputs!$A$2:$A$121,0)) | D21: =(INDEX(Inputs!$E$2:$E$121,MATCH("share_users_unpaid",Inputs!$A$2:$A$121,0))*INDEX(Inputs!$E$2:$E$121,MATCH("unpaid_events_per_user",Inputs!$A$2:$A$121,0))*INDEX(Inputs!$E$2:$E$121,MATCH("unpaid_reduction",Inputs!$A$2:$A$121,0)))*INDEX(Inputs!$D$2:$D$121,MATCH("bank_cost_per_unpaid",Inputs!$A$2:$A$121,0))-(INDEX(Inputs!$E$2:$E$121,MATCH("share_users_unpaid",Inputs!$A$2:$A$121,0))*INDEX(Inputs!$E$2:$E$121,MATCH("unpaid_events_per_user",Inputs!$A$2:$A$121,0))*INDEX(Inputs!$E$2:$E$121,MATCH("unpaid_reduction",Inputs!$A$2:$A$121,0)))*INDEX(Inputs!$E$2:$E$121,MATCH("sb_unpaid_payt",Inputs!$A$2:$A$121,0))+INDEX(Inputs!$E$2:$E$121,MATCH("deposit_uplift",Inputs!$A$2:$A$121,0))*INDEX(Inputs!$E$2:$E$121,MATCH("nim_on_deposits",Inputs!$A$2:$A$121,0))+INDEX(Inputs!$E$2:$E$121,MATCH("attrition_reduction",Inputs!$A$2:$A$121,0))*INDEX(Inputs!$E$2:$E$121,MATCH("value_per_customer_year",Inputs!$A$2:$A$121,0))+INDEX(Inputs!$E$2:$E$121,MATCH("contact_avoided",Inputs!$A$2:$A$121,0))*INDEX(Inputs!$E$2:$E$121,MATCH("cost_per_call",Inputs!$A$2:$A$121,0)) | E21: =(INDEX(Inputs!$E$2:$E$121,MATCH("share_users_unpaid",Inputs!$A$2:$A$121,0))*INDEX(Inputs!$E$2:$E$121,MATCH("unpaid_events_per_user",Inputs!$A$2:$A$121,0))*INDEX(Inputs!$E$2:$E$121,MATCH("unpaid_reduction",Inputs!$A$2:$A$121,0)))*INDEX(Inputs!$F$2:$F$121,MATCH("bank_cost_per_unpaid",Inputs!$A$2:$A$121,0))-(INDEX(Inputs!$E$2:$E$121,MATCH("share_users_unpaid",Inputs!$A$2:$A$121,0))*INDEX(Inputs!$E$2:$E$121,MATCH("unpaid_events_per_user",Inputs!$A$2:$A$121,0))*INDEX(Inputs!$E$2:$E$121,MATCH("unpaid_reduction",Inputs!$A$2:$A$121,0)))*INDEX(Inputs!$E$2:$E$121,MATCH("sb_unpaid_payt",Inputs!$A$2:$A$121,0))+INDEX(Inputs!$E$2:$E$121,MATCH("deposit_uplift",Inputs!$A$2:$A$121,0))*INDEX(Inputs!$E$2:$E$121,MATCH("nim_on_deposits",Inputs!$A$2:$A$121,0))+INDEX(Inputs!$E$2:$E$121,MATCH("attrition_reduction",Inputs!$A$2:$A$121,0))*INDEX(Inputs!$E$2:$E$121,MATCH("value_per_customer_year",Inputs!$A$2:$A$121,0))+INDEX(Inputs!$E$2:$E$121,MATCH("contact_avoided",Inputs!$A$2:$A$121,0))*INDEX(Inputs!$E$2:$E$121,MATCH("cost_per_call",Inputs!$A$2:$A$121,0)) | F21: =ABS(E21-D21) | G21: =$G$17
A22: sb_unpaid_payt | B22: =INDEX(Inputs!$D$2:$D$121,MATCH("sb_unpaid_payt",Inputs!$A$2:$A$121,0)) | C22: =INDEX(Inputs!$F$2:$F$121,MATCH("sb_unpaid_payt",Inputs!$A$2:$A$121,0)) | D22: =(INDEX(Inputs!$E$2:$E$121,MATCH("share_users_unpaid",Inputs!$A$2:$A$121,0))*INDEX(Inputs!$E$2:$E$121,MATCH("unpaid_events_per_user",Inputs!$A$2:$A$121,0))*INDEX(Inputs!$E$2:$E$121,MATCH("unpaid_reduction",Inputs!$A$2:$A$121,0)))*INDEX(Inputs!$E$2:$E$121,MATCH("bank_cost_per_unpaid",Inputs!$A$2:$A$121,0))-(INDEX(Inputs!$E$2:$E$121,MATCH("share_users_unpaid",Inputs!$A$2:$A$121,0))*INDEX(Inputs!$E$2:$E$121,MATCH("unpaid_events_per_user",Inputs!$A$2:$A$121,0))*INDEX(Inputs!$E$2:$E$121,MATCH("unpaid_reduction",Inputs!$A$2:$A$121,0)))*INDEX(Inputs!$D$2:$D$121,MATCH("sb_unpaid_payt",Inputs!$A$2:$A$121,0))+INDEX(Inputs!$E$2:$E$121,MATCH("deposit_uplift",Inputs!$A$2:$A$121,0))*INDEX(Inputs!$E$2:$E$121,MATCH("nim_on_deposits",Inputs!$A$2:$A$121,0))+INDEX(Inputs!$E$2:$E$121,MATCH("attrition_reduction",Inputs!$A$2:$A$121,0))*INDEX(Inputs!$E$2:$E$121,MATCH("value_per_customer_year",Inputs!$A$2:$A$121,0))+INDEX(Inputs!$E$2:$E$121,MATCH("contact_avoided",Inputs!$A$2:$A$121,0))*INDEX(Inputs!$E$2:$E$121,MATCH("cost_per_call",Inputs!$A$2:$A$121,0)) | E22: =(INDEX(Inputs!$E$2:$E$121,MATCH("share_users_unpaid",Inputs!$A$2:$A$121,0))*INDEX(Inputs!$E$2:$E$121,MATCH("unpaid_events_per_user",Inputs!$A$2:$A$121,0))*INDEX(Inputs!$E$2:$E$121,MATCH("unpaid_reduction",Inputs!$A$2:$A$121,0)))*INDEX(Inputs!$E$2:$E$121,MATCH("bank_cost_per_unpaid",Inputs!$A$2:$A$121,0))-(INDEX(Inputs!$E$2:$E$121,MATCH("share_users_unpaid",Inputs!$A$2:$A$121,0))*INDEX(Inputs!$E$2:$E$121,MATCH("unpaid_events_per_user",Inputs!$A$2:$A$121,0))*INDEX(Inputs!$E$2:$E$121,MATCH("unpaid_reduction",Inputs!$A$2:$A$121,0)))*INDEX(Inputs!$F$2:$F$121,MATCH("sb_unpaid_payt",Inputs!$A$2:$A$121,0))+INDEX(Inputs!$E$2:$E$121,MATCH("deposit_uplift",Inputs!$A$2:$A$121,0))*INDEX(Inputs!$E$2:$E$121,MATCH("nim_on_deposits",Inputs!$A$2:$A$121,0))+INDEX(Inputs!$E$2:$E$121,MATCH("attrition_reduction",Inputs!$A$2:$A$121,0))*INDEX(Inputs!$E$2:$E$121,MATCH("value_per_customer_year",Inputs!$A$2:$A$121,0))+INDEX(Inputs!$E$2:$E$121,MATCH("contact_avoided",Inputs!$A$2:$A$121,0))*INDEX(Inputs!$E$2:$E$121,MATCH("cost_per_call",Inputs!$A$2:$A$121,0)) | F22: =ABS(E22-D22) | G22: =$G$17
A23: deposit_uplift | B23: =INDEX(Inputs!$D$2:$D$121,MATCH("deposit_uplift",Inputs!$A$2:$A$121,0)) | C23: =INDEX(Inputs!$F$2:$F$121,MATCH("deposit_uplift",Inputs!$A$2:$A$121,0)) | D23: =(INDEX(Inputs!$E$2:$E$121,MATCH("share_users_unpaid",Inputs!$A$2:$A$121,0))*INDEX(Inputs!$E$2:$E$121,MATCH("unpaid_events_per_user",Inputs!$A$2:$A$121,0))*INDEX(Inputs!$E$2:$E$121,MATCH("unpaid_reduction",Inputs!$A$2:$A$121,0)))*INDEX(Inputs!$E$2:$E$121,MATCH("bank_cost_per_unpaid",Inputs!$A$2:$A$121,0))-(INDEX(Inputs!$E$2:$E$121,MATCH("share_users_unpaid",Inputs!$A$2:$A$121,0))*INDEX(Inputs!$E$2:$E$121,MATCH("unpaid_events_per_user",Inputs!$A$2:$A$121,0))*INDEX(Inputs!$E$2:$E$121,MATCH("unpaid_reduction",Inputs!$A$2:$A$121,0)))*INDEX(Inputs!$E$2:$E$121,MATCH("sb_unpaid_payt",Inputs!$A$2:$A$121,0))+INDEX(Inputs!$D$2:$D$121,MATCH("deposit_uplift",Inputs!$A$2:$A$121,0))*INDEX(Inputs!$E$2:$E$121,MATCH("nim_on_deposits",Inputs!$A$2:$A$121,0))+INDEX(Inputs!$E$2:$E$121,MATCH("attrition_reduction",Inputs!$A$2:$A$121,0))*INDEX(Inputs!$E$2:$E$121,MATCH("value_per_customer_year",Inputs!$A$2:$A$121,0))+INDEX(Inputs!$E$2:$E$121,MATCH("contact_avoided",Inputs!$A$2:$A$121,0))*INDEX(Inputs!$E$2:$E$121,MATCH("cost_per_call",Inputs!$A$2:$A$121,0)) | E23: =(INDEX(Inputs!$E$2:$E$121,MATCH("share_users_unpaid",Inputs!$A$2:$A$121,0))*INDEX(Inputs!$E$2:$E$121,MATCH("unpaid_events_per_user",Inputs!$A$2:$A$121,0))*INDEX(Inputs!$E$2:$E$121,MATCH("unpaid_reduction",Inputs!$A$2:$A$121,0)))*INDEX(Inputs!$E$2:$E$121,MATCH("bank_cost_per_unpaid",Inputs!$A$2:$A$121,0))-(INDEX(Inputs!$E$2:$E$121,MATCH("share_users_unpaid",Inputs!$A$2:$A$121,0))*INDEX(Inputs!$E$2:$E$121,MATCH("unpaid_events_per_user",Inputs!$A$2:$A$121,0))*INDEX(Inputs!$E$2:$E$121,MATCH("unpaid_reduction",Inputs!$A$2:$A$121,0)))*INDEX(Inputs!$E$2:$E$121,MATCH("sb_unpaid_payt",Inputs!$A$2:$A$121,0))+INDEX(Inputs!$F$2:$F$121,MATCH("deposit_uplift",Inputs!$A$2:$A$121,0))*INDEX(Inputs!$E$2:$E$121,MATCH("nim_on_deposits",Inputs!$A$2:$A$121,0))+INDEX(Inputs!$E$2:$E$121,MATCH("attrition_reduction",Inputs!$A$2:$A$121,0))*INDEX(Inputs!$E$2:$E$121,MATCH("value_per_customer_year",Inputs!$A$2:$A$121,0))+INDEX(Inputs!$E$2:$E$121,MATCH("contact_avoided",Inputs!$A$2:$A$121,0))*INDEX(Inputs!$E$2:$E$121,MATCH("cost_per_call",Inputs!$A$2:$A$121,0)) | F23: =ABS(E23-D23) | G23: =$G$17
A24: nim_on_deposits | B24: =INDEX(Inputs!$D$2:$D$121,MATCH("nim_on_deposits",Inputs!$A$2:$A$121,0)) | C24: =INDEX(Inputs!$F$2:$F$121,MATCH("nim_on_deposits",Inputs!$A$2:$A$121,0)) | D24: =(INDEX(Inputs!$E$2:$E$121,MATCH("share_users_unpaid",Inputs!$A$2:$A$121,0))*INDEX(Inputs!$E$2:$E$121,MATCH("unpaid_events_per_user",Inputs!$A$2:$A$121,0))*INDEX(Inputs!$E$2:$E$121,MATCH("unpaid_reduction",Inputs!$A$2:$A$121,0)))*INDEX(Inputs!$E$2:$E$121,MATCH("bank_cost_per_unpaid",Inputs!$A$2:$A$121,0))-(INDEX(Inputs!$E$2:$E$121,MATCH("share_users_unpaid",Inputs!$A$2:$A$121,0))*INDEX(Inputs!$E$2:$E$121,MATCH("unpaid_events_per_user",Inputs!$A$2:$A$121,0))*INDEX(Inputs!$E$2:$E$121,MATCH("unpaid_reduction",Inputs!$A$2:$A$121,0)))*INDEX(Inputs!$E$2:$E$121,MATCH("sb_unpaid_payt",Inputs!$A$2:$A$121,0))+INDEX(Inputs!$E$2:$E$121,MATCH("deposit_uplift",Inputs!$A$2:$A$121,0))*INDEX(Inputs!$D$2:$D$121,MATCH("nim_on_deposits",Inputs!$A$2:$A$121,0))+INDEX(Inputs!$E$2:$E$121,MATCH("attrition_reduction",Inputs!$A$2:$A$121,0))*INDEX(Inputs!$E$2:$E$121,MATCH("value_per_customer_year",Inputs!$A$2:$A$121,0))+INDEX(Inputs!$E$2:$E$121,MATCH("contact_avoided",Inputs!$A$2:$A$121,0))*INDEX(Inputs!$E$2:$E$121,MATCH("cost_per_call",Inputs!$A$2:$A$121,0)) | E24: =(INDEX(Inputs!$E$2:$E$121,MATCH("share_users_unpaid",Inputs!$A$2:$A$121,0))*INDEX(Inputs!$E$2:$E$121,MATCH("unpaid_events_per_user",Inputs!$A$2:$A$121,0))*INDEX(Inputs!$E$2:$E$121,MATCH("unpaid_reduction",Inputs!$A$2:$A$121,0)))*INDEX(Inputs!$E$2:$E$121,MATCH("bank_cost_per_unpaid",Inputs!$A$2:$A$121,0))-(INDEX(Inputs!$E$2:$E$121,MATCH("share_users_unpaid",Inputs!$A$2:$A$121,0))*INDEX(Inputs!$E$2:$E$121,MATCH("unpaid_events_per_user",Inputs!$A$2:$A$121,0))*INDEX(Inputs!$E$2:$E$121,MATCH("unpaid_reduction",Inputs!$A$2:$A$121,0)))*INDEX(Inputs!$E$2:$E$121,MATCH("sb_unpaid_payt",Inputs!$A$2:$A$121,0))+INDEX(Inputs!$E$2:$E$121,MATCH("deposit_uplift",Inputs!$A$2:$A$121,0))*INDEX(Inputs!$F$2:$F$121,MATCH("nim_on_deposits",Inputs!$A$2:$A$121,0))+INDEX(Inputs!$E$2:$E$121,MATCH("attrition_reduction",Inputs!$A$2:$A$121,0))*INDEX(Inputs!$E$2:$E$121,MATCH("value_per_customer_year",Inputs!$A$2:$A$121,0))+INDEX(Inputs!$E$2:$E$121,MATCH("contact_avoided",Inputs!$A$2:$A$121,0))*INDEX(Inputs!$E$2:$E$121,MATCH("cost_per_call",Inputs!$A$2:$A$121,0)) | F24: =ABS(E24-D24) | G24: =$G$17
A25: attrition_reduction | B25: =INDEX(Inputs!$D$2:$D$121,MATCH("attrition_reduction",Inputs!$A$2:$A$121,0)) | C25: =INDEX(Inputs!$F$2:$F$121,MATCH("attrition_reduction",Inputs!$A$2:$A$121,0)) | D25: =(INDEX(Inputs!$E$2:$E$121,MATCH("share_users_unpaid",Inputs!$A$2:$A$121,0))*INDEX(Inputs!$E$2:$E$121,MATCH("unpaid_events_per_user",Inputs!$A$2:$A$121,0))*INDEX(Inputs!$E$2:$E$121,MATCH("unpaid_reduction",Inputs!$A$2:$A$121,0)))*INDEX(Inputs!$E$2:$E$121,MATCH("bank_cost_per_unpaid",Inputs!$A$2:$A$121,0))-(INDEX(Inputs!$E$2:$E$121,MATCH("share_users_unpaid",Inputs!$A$2:$A$121,0))*INDEX(Inputs!$E$2:$E$121,MATCH("unpaid_events_per_user",Inputs!$A$2:$A$121,0))*INDEX(Inputs!$E$2:$E$121,MATCH("unpaid_reduction",Inputs!$A$2:$A$121,0)))*INDEX(Inputs!$E$2:$E$121,MATCH("sb_unpaid_payt",Inputs!$A$2:$A$121,0))+INDEX(Inputs!$E$2:$E$121,MATCH("deposit_uplift",Inputs!$A$2:$A$121,0))*INDEX(Inputs!$E$2:$E$121,MATCH("nim_on_deposits",Inputs!$A$2:$A$121,0))+INDEX(Inputs!$D$2:$D$121,MATCH("attrition_reduction",Inputs!$A$2:$A$121,0))*INDEX(Inputs!$E$2:$E$121,MATCH("value_per_customer_year",Inputs!$A$2:$A$121,0))+INDEX(Inputs!$E$2:$E$121,MATCH("contact_avoided",Inputs!$A$2:$A$121,0))*INDEX(Inputs!$E$2:$E$121,MATCH("cost_per_call",Inputs!$A$2:$A$121,0)) | E25: =(INDEX(Inputs!$E$2:$E$121,MATCH("share_users_unpaid",Inputs!$A$2:$A$121,0))*INDEX(Inputs!$E$2:$E$121,MATCH("unpaid_events_per_user",Inputs!$A$2:$A$121,0))*INDEX(Inputs!$E$2:$E$121,MATCH("unpaid_reduction",Inputs!$A$2:$A$121,0)))*INDEX(Inputs!$E$2:$E$121,MATCH("bank_cost_per_unpaid",Inputs!$A$2:$A$121,0))-(INDEX(Inputs!$E$2:$E$121,MATCH("share_users_unpaid",Inputs!$A$2:$A$121,0))*INDEX(Inputs!$E$2:$E$121,MATCH("unpaid_events_per_user",Inputs!$A$2:$A$121,0))*INDEX(Inputs!$E$2:$E$121,MATCH("unpaid_reduction",Inputs!$A$2:$A$121,0)))*INDEX(Inputs!$E$2:$E$121,MATCH("sb_unpaid_payt",Inputs!$A$2:$A$121,0))+INDEX(Inputs!$E$2:$E$121,MATCH("deposit_uplift",Inputs!$A$2:$A$121,0))*INDEX(Inputs!$E$2:$E$121,MATCH("nim_on_deposits",Inputs!$A$2:$A$121,0))+INDEX(Inputs!$F$2:$F$121,MATCH("attrition_reduction",Inputs!$A$2:$A$121,0))*INDEX(Inputs!$E$2:$E$121,MATCH("value_per_customer_year",Inputs!$A$2:$A$121,0))+INDEX(Inputs!$E$2:$E$121,MATCH("contact_avoided",Inputs!$A$2:$A$121,0))*INDEX(Inputs!$E$2:$E$121,MATCH("cost_per_call",Inputs!$A$2:$A$121,0)) | F25: =ABS(E25-D25) | G25: =$G$17
A26: value_per_customer_year | B26: =INDEX(Inputs!$D$2:$D$121,MATCH("value_per_customer_year",Inputs!$A$2:$A$121,0)) | C26: =INDEX(Inputs!$F$2:$F$121,MATCH("value_per_customer_year",Inputs!$A$2:$A$121,0)) | D26: =(INDEX(Inputs!$E$2:$E$121,MATCH("share_users_unpaid",Inputs!$A$2:$A$121,0))*INDEX(Inputs!$E$2:$E$121,MATCH("unpaid_events_per_user",Inputs!$A$2:$A$121,0))*INDEX(Inputs!$E$2:$E$121,MATCH("unpaid_reduction",Inputs!$A$2:$A$121,0)))*INDEX(Inputs!$E$2:$E$121,MATCH("bank_cost_per_unpaid",Inputs!$A$2:$A$121,0))-(INDEX(Inputs!$E$2:$E$121,MATCH("share_users_unpaid",Inputs!$A$2:$A$121,0))*INDEX(Inputs!$E$2:$E$121,MATCH("unpaid_events_per_user",Inputs!$A$2:$A$121,0))*INDEX(Inputs!$E$2:$E$121,MATCH("unpaid_reduction",Inputs!$A$2:$A$121,0)))*INDEX(Inputs!$E$2:$E$121,MATCH("sb_unpaid_payt",Inputs!$A$2:$A$121,0))+INDEX(Inputs!$E$2:$E$121,MATCH("deposit_uplift",Inputs!$A$2:$A$121,0))*INDEX(Inputs!$E$2:$E$121,MATCH("nim_on_deposits",Inputs!$A$2:$A$121,0))+INDEX(Inputs!$E$2:$E$121,MATCH("attrition_reduction",Inputs!$A$2:$A$121,0))*INDEX(Inputs!$D$2:$D$121,MATCH("value_per_customer_year",Inputs!$A$2:$A$121,0))+INDEX(Inputs!$E$2:$E$121,MATCH("contact_avoided",Inputs!$A$2:$A$121,0))*INDEX(Inputs!$E$2:$E$121,MATCH("cost_per_call",Inputs!$A$2:$A$121,0)) | E26: =(INDEX(Inputs!$E$2:$E$121,MATCH("share_users_unpaid",Inputs!$A$2:$A$121,0))*INDEX(Inputs!$E$2:$E$121,MATCH("unpaid_events_per_user",Inputs!$A$2:$A$121,0))*INDEX(Inputs!$E$2:$E$121,MATCH("unpaid_reduction",Inputs!$A$2:$A$121,0)))*INDEX(Inputs!$E$2:$E$121,MATCH("bank_cost_per_unpaid",Inputs!$A$2:$A$121,0))-(INDEX(Inputs!$E$2:$E$121,MATCH("share_users_unpaid",Inputs!$A$2:$A$121,0))*INDEX(Inputs!$E$2:$E$121,MATCH("unpaid_events_per_user",Inputs!$A$2:$A$121,0))*INDEX(Inputs!$E$2:$E$121,MATCH("unpaid_reduction",Inputs!$A$2:$A$121,0)))*INDEX(Inputs!$E$2:$E$121,MATCH("sb_unpaid_payt",Inputs!$A$2:$A$121,0))+INDEX(Inputs!$E$2:$E$121,MATCH("deposit_uplift",Inputs!$A$2:$A$121,0))*INDEX(Inputs!$E$2:$E$121,MATCH("nim_on_deposits",Inputs!$A$2:$A$121,0))+INDEX(Inputs!$E$2:$E$121,MATCH("attrition_reduction",Inputs!$A$2:$A$121,0))*INDEX(Inputs!$F$2:$F$121,MATCH("value_per_customer_year",Inputs!$A$2:$A$121,0))+INDEX(Inputs!$E$2:$E$121,MATCH("contact_avoided",Inputs!$A$2:$A$121,0))*INDEX(Inputs!$E$2:$E$121,MATCH("cost_per_call",Inputs!$A$2:$A$121,0)) | F26: =ABS(E26-D26) | G26: =$G$17
A27: contact_avoided | B27: =INDEX(Inputs!$D$2:$D$121,MATCH("contact_avoided",Inputs!$A$2:$A$121,0)) | C27: =INDEX(Inputs!$F$2:$F$121,MATCH("contact_avoided",Inputs!$A$2:$A$121,0)) | D27: =(INDEX(Inputs!$E$2:$E$121,MATCH("share_users_unpaid",Inputs!$A$2:$A$121,0))*INDEX(Inputs!$E$2:$E$121,MATCH("unpaid_events_per_user",Inputs!$A$2:$A$121,0))*INDEX(Inputs!$E$2:$E$121,MATCH("unpaid_reduction",Inputs!$A$2:$A$121,0)))*INDEX(Inputs!$E$2:$E$121,MATCH("bank_cost_per_unpaid",Inputs!$A$2:$A$121,0))-(INDEX(Inputs!$E$2:$E$121,MATCH("share_users_unpaid",Inputs!$A$2:$A$121,0))*INDEX(Inputs!$E$2:$E$121,MATCH("unpaid_events_per_user",Inputs!$A$2:$A$121,0))*INDEX(Inputs!$E$2:$E$121,MATCH("unpaid_reduction",Inputs!$A$2:$A$121,0)))*INDEX(Inputs!$E$2:$E$121,MATCH("sb_unpaid_payt",Inputs!$A$2:$A$121,0))+INDEX(Inputs!$E$2:$E$121,MATCH("deposit_uplift",Inputs!$A$2:$A$121,0))*INDEX(Inputs!$E$2:$E$121,MATCH("nim_on_deposits",Inputs!$A$2:$A$121,0))+INDEX(Inputs!$E$2:$E$121,MATCH("attrition_reduction",Inputs!$A$2:$A$121,0))*INDEX(Inputs!$E$2:$E$121,MATCH("value_per_customer_year",Inputs!$A$2:$A$121,0))+INDEX(Inputs!$D$2:$D$121,MATCH("contact_avoided",Inputs!$A$2:$A$121,0))*INDEX(Inputs!$E$2:$E$121,MATCH("cost_per_call",Inputs!$A$2:$A$121,0)) | E27: =(INDEX(Inputs!$E$2:$E$121,MATCH("share_users_unpaid",Inputs!$A$2:$A$121,0))*INDEX(Inputs!$E$2:$E$121,MATCH("unpaid_events_per_user",Inputs!$A$2:$A$121,0))*INDEX(Inputs!$E$2:$E$121,MATCH("unpaid_reduction",Inputs!$A$2:$A$121,0)))*INDEX(Inputs!$E$2:$E$121,MATCH("bank_cost_per_unpaid",Inputs!$A$2:$A$121,0))-(INDEX(Inputs!$E$2:$E$121,MATCH("share_users_unpaid",Inputs!$A$2:$A$121,0))*INDEX(Inputs!$E$2:$E$121,MATCH("unpaid_events_per_user",Inputs!$A$2:$A$121,0))*INDEX(Inputs!$E$2:$E$121,MATCH("unpaid_reduction",Inputs!$A$2:$A$121,0)))*INDEX(Inputs!$E$2:$E$121,MATCH("sb_unpaid_payt",Inputs!$A$2:$A$121,0))+INDEX(Inputs!$E$2:$E$121,MATCH("deposit_uplift",Inputs!$A$2:$A$121,0))*INDEX(Inputs!$E$2:$E$121,MATCH("nim_on_deposits",Inputs!$A$2:$A$121,0))+INDEX(Inputs!$E$2:$E$121,MATCH("attrition_reduction",Inputs!$A$2:$A$121,0))*INDEX(Inputs!$E$2:$E$121,MATCH("value_per_customer_year",Inputs!$A$2:$A$121,0))+INDEX(Inputs!$F$2:$F$121,MATCH("contact_avoided",Inputs!$A$2:$A$121,0))*INDEX(Inputs!$E$2:$E$121,MATCH("cost_per_call",Inputs!$A$2:$A$121,0)) | F27: =ABS(E27-D27) | G27: =$G$17
A28: cost_per_call | B28: =INDEX(Inputs!$D$2:$D$121,MATCH("cost_per_call",Inputs!$A$2:$A$121,0)) | C28: =INDEX(Inputs!$F$2:$F$121,MATCH("cost_per_call",Inputs!$A$2:$A$121,0)) | D28: =(INDEX(Inputs!$E$2:$E$121,MATCH("share_users_unpaid",Inputs!$A$2:$A$121,0))*INDEX(Inputs!$E$2:$E$121,MATCH("unpaid_events_per_user",Inputs!$A$2:$A$121,0))*INDEX(Inputs!$E$2:$E$121,MATCH("unpaid_reduction",Inputs!$A$2:$A$121,0)))*INDEX(Inputs!$E$2:$E$121,MATCH("bank_cost_per_unpaid",Inputs!$A$2:$A$121,0))-(INDEX(Inputs!$E$2:$E$121,MATCH("share_users_unpaid",Inputs!$A$2:$A$121,0))*INDEX(Inputs!$E$2:$E$121,MATCH("unpaid_events_per_user",Inputs!$A$2:$A$121,0))*INDEX(Inputs!$E$2:$E$121,MATCH("unpaid_reduction",Inputs!$A$2:$A$121,0)))*INDEX(Inputs!$E$2:$E$121,MATCH("sb_unpaid_payt",Inputs!$A$2:$A$121,0))+INDEX(Inputs!$E$2:$E$121,MATCH("deposit_uplift",Inputs!$A$2:$A$121,0))*INDEX(Inputs!$E$2:$E$121,MATCH("nim_on_deposits",Inputs!$A$2:$A$121,0))+INDEX(Inputs!$E$2:$E$121,MATCH("attrition_reduction",Inputs!$A$2:$A$121,0))*INDEX(Inputs!$E$2:$E$121,MATCH("value_per_customer_year",Inputs!$A$2:$A$121,0))+INDEX(Inputs!$E$2:$E$121,MATCH("contact_avoided",Inputs!$A$2:$A$121,0))*INDEX(Inputs!$D$2:$D$121,MATCH("cost_per_call",Inputs!$A$2:$A$121,0)) | E28: =(INDEX(Inputs!$E$2:$E$121,MATCH("share_users_unpaid",Inputs!$A$2:$A$121,0))*INDEX(Inputs!$E$2:$E$121,MATCH("unpaid_events_per_user",Inputs!$A$2:$A$121,0))*INDEX(Inputs!$E$2:$E$121,MATCH("unpaid_reduction",Inputs!$A$2:$A$121,0)))*INDEX(Inputs!$E$2:$E$121,MATCH("bank_cost_per_unpaid",Inputs!$A$2:$A$121,0))-(INDEX(Inputs!$E$2:$E$121,MATCH("share_users_unpaid",Inputs!$A$2:$A$121,0))*INDEX(Inputs!$E$2:$E$121,MATCH("unpaid_events_per_user",Inputs!$A$2:$A$121,0))*INDEX(Inputs!$E$2:$E$121,MATCH("unpaid_reduction",Inputs!$A$2:$A$121,0)))*INDEX(Inputs!$E$2:$E$121,MATCH("sb_unpaid_payt",Inputs!$A$2:$A$121,0))+INDEX(Inputs!$E$2:$E$121,MATCH("deposit_uplift",Inputs!$A$2:$A$121,0))*INDEX(Inputs!$E$2:$E$121,MATCH("nim_on_deposits",Inputs!$A$2:$A$121,0))+INDEX(Inputs!$E$2:$E$121,MATCH("attrition_reduction",Inputs!$A$2:$A$121,0))*INDEX(Inputs!$E$2:$E$121,MATCH("value_per_customer_year",Inputs!$A$2:$A$121,0))+INDEX(Inputs!$E$2:$E$121,MATCH("contact_avoided",Inputs!$A$2:$A$121,0))*INDEX(Inputs!$F$2:$F$121,MATCH("cost_per_call",Inputs!$A$2:$A$121,0)) | F28: =ABS(E28-D28) | G28: =$G$17
A31: Two-way: break-even MAU for model (a), licence fee per MAU (rows) against fixed cost per month (columns)
A32: Licence fee / Fixed cost | B32: 200000 | C32: 310000 | D32: 450000 | E32: 600000
A33: 2 | B33: =IF($A33-Model!$C$84>0,B$32/($A33-Model!$C$84),"never") | C33: =IF($A33-Model!$C$84>0,C$32/($A33-Model!$C$84),"never") | D33: =IF($A33-Model!$C$84>0,D$32/($A33-Model!$C$84),"never") | E33: =IF($A33-Model!$C$84>0,E$32/($A33-Model!$C$84),"never")
A34: 3 | B34: =IF($A34-Model!$C$84>0,B$32/($A34-Model!$C$84),"never") | C34: =IF($A34-Model!$C$84>0,C$32/($A34-Model!$C$84),"never") | D34: =IF($A34-Model!$C$84>0,D$32/($A34-Model!$C$84),"never") | E34: =IF($A34-Model!$C$84>0,E$32/($A34-Model!$C$84),"never")
A35: 5 | B35: =IF($A35-Model!$C$84>0,B$32/($A35-Model!$C$84),"never") | C35: =IF($A35-Model!$C$84>0,C$32/($A35-Model!$C$84),"never") | D35: =IF($A35-Model!$C$84>0,D$32/($A35-Model!$C$84),"never") | E35: =IF($A35-Model!$C$84>0,E$32/($A35-Model!$C$84),"never")
A36: 8 | B36: =IF($A36-Model!$C$84>0,B$32/($A36-Model!$C$84),"never") | C36: =IF($A36-Model!$C$84>0,C$32/($A36-Model!$C$84),"never") | D36: =IF($A36-Model!$C$84>0,D$32/($A36-Model!$C$84),"never") | E36: =IF($A36-Model!$C$84>0,E$32/($A36-Model!$C$84),"never")
A37: 12 | B37: =IF($A37-Model!$C$84>0,B$32/($A37-Model!$C$84),"never") | C37: =IF($A37-Model!$C$84>0,C$32/($A37-Model!$C$84),"never") | D37: =IF($A37-Model!$C$84>0,D$32/($A37-Model!$C$84),"never") | E37: =IF($A37-Model!$C$84>0,E$32/($A37-Model!$C$84),"never")
A39: Variable cost per MAU is the Base scenario embedded cost from the Model sheet. Fixed cost options and fees are blue inputs to vary.

Sheet Metrics
A1: Metrics: what to track, and the values measured in this review
A3: Product metrics to track in a pilot (definitions; no values exist yet)
A4: Metric | B4: Value | C4: Definition | D4: Source
A5: Activation | B5: not measured yet | C5: Share of offered users who complete consent and see a date | D5: Pilot analytics (needs consent)
A6: Weekly active use | B6: not measured yet | C6: Users who open Home at least once in a week, over MAU | D6: Pilot analytics
A7: Retention day 7 and day 30 | B7: not measured yet | C7: Share of activated users active on day 7 and day 30 | D7: Pilot analytics
A8: Statement imports completed | B8: not measured yet | C8: Imports confirmed over imports started | D8: Pilot analytics
A9: Messages opted in | B9: not measured yet | C9: Users with daily messages on over activated users | D9: Consent records
A10: Forecast accuracy in the field | B10: not measured yet | C10: Mean absolute error in days between forecast date and actual run-out | D10: Stored forecasts plus later balances
A11: State transitions acted on | B11: not measured yet | C11: Users who use Plan or change spend within 3 days of a Tight or Short state | D11: Pilot analytics
A13: Forecast quality (synthetic backtest, seeds, 90 day history, all personas)
A14: Metric | B14: Value | C14: Definition | D14: Source
A15: Mean absolute error, days | B15: 2.073 | C15: Forecast runway date against held-out actual | D15: docs/review/backtest/results/summary_headline.csv
A16: Within 3 days, percent | B16: 0.7807 | C16: Share of cases within three days | D16: same file
A17: Range band coverage, percent | B17: 0.7177 | C17: Actual date inside the stated range | D17: same file
A18: State accuracy, percent | B18: 0.7185 | C18: Shown state right in hindsight (20 percent buffer rule) | D18: same file
A19: False reassurance, percent | B19: 0.0759 | C19: Shown covered, actually short | D19: same file
A20: Mean absolute error with 14 days of history, days | B20: 5.4 | C20: Seeds, 14 day history | D20: docs/review/data-scientist.md, Backtest summary
A22: Technical metrics (measured 2026-10-20 at commit d114497)
A23: Metric | B23: Value | C23: Definition | D23: Source
A24: Unit tests | B24: 66 | C24: Vitest, all passing | D24: docs/review/prep/checks.md
A25: Playwright tests | B25: 221 | C25: Screenshot, flow, phone and axe suites, all passing | D25: docs/review/prep/playwright.txt
A26: Unit coverage, engine statements | B26: 0.9755 | C26: src/engine | D26: docs/review/prep/coverage.txt
A27: Unit coverage, all statements | B27: 0.1995 | C27: All of src | D27: docs/review/prep/coverage.txt
A28: Lighthouse mobile performance, landing | B28: 94 | C28: Simulated slow 4G, 4x CPU | D28: docs/review/prep/lighthouse/landing.report.json
A29: Lighthouse mobile accessibility, landing | B29: 100 | C29: Same run | D29: same file
A30: JavaScript bundle, gzip KB | B30: 141.9 | C30: One file including all 11 locales | D30: docs/review/prep/audit.md
A31: Home first paint, cold, throttled, ms | B31: 1188 | C31: 390 px, 4x CPU, 1.6 Mbps | D31: docs/review/prep/perf-home.json
A32: axe violations in the app test suite | B32: 0 | C32: tests/a11y.spec.ts, both themes, 390 and 1280 | D32: docs/review/prep/playwright.txt
A33: npm audit, production dependencies | B33: 2 | C33: Moderate, react-router | D33: docs/review/prep/audit.md
A34: npm audit, all dependencies | B34: 12 | C34: 2 critical, 5 high, 5 moderate, dev tooling | D34: docs/review/prep/audit.md
A35: Production licences | B35: MIT 18, OFL 2, ISC 1, Apache 1 | C35: license-checker summary | D35: docs/review/prep/audit.md
